Workbook

Sheet Menu Item Price vs POS Price
A1: ITEM NAME | B1: ITEM PRICE | C1: POS PRICE | D1: AFTER TAX PRICE | E1: PROFIT MARGIN
A2: BIG BREAKFAST W/BACON | B2: ='Menu item calculator'!F12 -> 15.227749 | C2: 33 | D2: =C2+(C2*6%)+(C2*10%) -> 38.28 | E2: =(C2-B2)/C2 -> 0.53855307
A3: BIG BREAKFAST W/CHICKEN | B3: ='Menu item calculator'!F26 -> 15.227749 | C3: 33 | D3: =C3+(C3*6%)+(C3*10%) -> 38.28 | E3: =(C3-B3)/C3 -> 0.53855307
A4: BIG BREAKFAST W/PORK | B4: ='Menu item calculator'!F40 -> 15.227749 | C4: 33 | D4: =C4+(C4*6%)+(C4*10%) -> 38.28 | E4: =(C4-B4)/C4 -> 0.53855307
A5: BIG BREAKFAST W/BEEF | B5: ='Menu item calculator'!F54 -> 15.619249 | C5: 33 | D5: =C5+(C5*6%)+(C5*10%) -> 38.28 | E5: =(C5-B5)/C5 -> 0.52668943
A6: ALL DAY W/BACON | B6: ='Menu item calculator'!F68 -> 12.302455 | C6: 32 | D6: =C6+(C6*6%)+(C6*10%) -> 37.12 | E6: =(C6-B6)/C6 -> 0.61554828
A7: ALL DAY W/CHICKEN | B7: ='Menu item calculator'!F82 -> 12.302455 | C7: 32 | D7: =C7+(C7*6%)+(C7*10%) -> 37.12 | E7: =(C7-B7)/C7 -> 0.61554828
A8: ALL DAY W/PORK | B8: ='Menu item calculator'!F96 -> 12.302455 | C8: 32 | D8: =C8+(C8*6%)+(C8*10%) -> 37.12 | E8: =(C8-B8)/C8 -> 0.61554828
A9: ALL DAY W/BEEF | B9: ='Menu item calculator'!F110 -> 12.693955 | C9: 32 | D9: =C9+(C9*6%)+(C9*10%) -> 37.12 | E9: =(C9-B9)/C9 -> 0.6033139
A10: CREPPES W/CARAMELIZED BANANA | B10: ='Menu item calculator'!F121 -> 3.7039399 | C10: 24 | D10: =C10+(C10*6%)+(C10*10%) -> 27.84 | E10: =(C10-B10)/C10 -> 0.84566917
A11: CREPPES W/LEMON & SUGAR | B11: ='Menu item calculator'!F133 -> 2.8514399 | C11: 24 | D11: =C11+(C11*6%)+(C11*10%) -> 27.84 | E11: =(C11-B11)/C11 -> 0.88119
A12: CREPPES W/NUTELLA | B12: ='Menu item calculator'!F144 -> 4.2102046 | C12: 24 | D12: =C12+(C12*6%)+(C12*10%) -> 27.84 | E12: =(C12-B12)/C12 -> 0.82457481
A13: OMELETTE PLAIN | B13: ='Menu item calculator'!F156 -> 6.0332661 | C13: 28 | D13: =C13+(C13*6%)+(C13*10%) -> 32.48 | E13: =(C13-B13)/C13 -> 0.78452621
A14: OMELETTE W/SALMON 50GM | B14: ='Menu item calculator'!F169 -> 12.433266 | C14: 32 | D14: =C14+(C14*6%)+(C14*10%) -> 37.12 | E14: =(C14-B14)/C14 -> 0.61146043
A15: OMELETTE W/CHEESE & MUSHROOM | B15: ='Menu item calculator'!F183 -> 8.7232661 | C15: 28 | D15: =C15+(C15*6%)+(C15*10%) -> 32.48 | E15: =(C15-B15)/C15 -> 0.68845478
A16: EGGS BENEDICT W/BACON | B16: ='Menu item calculator'!F197 -> 10.626496 | C16: 33 | D16: =C16+(C16*6%)+(C16*10%) -> 38.28 | E16: =(C16-B16)/C16 -> 0.67798497
A17: EGGS MARLBOROUGH W/SALMON | B17: ='Menu item calculator'!F211 -> 13.598996 | C17: 33 | D17: =C17+(C17*6%)+(C17*10%) -> 38.28 | E17: =(C17-B17)/C17 -> 0.58790921
A18: TOAST W/BUTTER & JAM | B18: ='Menu item calculator'!F220 -> 0.28246867 | C18: 13 | D18: =C18+(C18*6%)+(C18*10%) -> 15.08 | E18: =(C18-B18)/C18 -> 0.97827164
A19: SWEET CORN PANCAKES W/BACON | B19: RECIPE MISSING | C19: 29 | D19: =C19+(C19*6%)+(C19*10%) -> 33.64 | E19: =(C19-B19)/C19 -> #VALUE!
A20: MUESLI W/HONEY,YOGHURT,FRUIT | B20: ='Menu item calculator'!F245 -> 4.7135225 | C20: 25 | D20: =C20+(C20*6%)+(C20*10%) -> 29 | E20: =(C20-B20)/C20 -> 0.8114591
A21: PANCAKE BANANA | B21: ='Menu item calculator'!F255 -> 6.893627 | C21: 28 | D21: =C21+(C21*6%)+(C21*10%) -> 32.48 | E21: =(C21-B21)/C21 -> 0.75379904
A22: PORRIDGE W/HONEY & BANANA | B22: ='Menu item calculator'!F268 -> 3.5439749 | C22: 20 | D22: =C22+(C22*6%)+(C22*10%) -> 23.2 | E22: =(C22-B22)/C22 -> 0.82280126
A23: ASPARAGUS W/BACON | B23: ='Menu item calculator'!F279 -> 11.724653 | C23: 28 | D23: =C23+(C23*6%)+(C23*10%) -> 32.48 | E23: =(C23-B23)/C23 -> 0.5812624
A24: SCRAMBLED EGGS W/SALMON 50G | B24: ='Menu item calculator'!F291 -> 12.345573 | C24: 32 | D24: =C24+(C24*6%)+(C24*10%) -> 37.12 | E24: =(C24-B24)/C24 -> 0.61420085
A25: FRESH FRUIT SALAD W/YOGHURT | B25: ='Menu item calculator'!F298 -> 2.9467 | C25: 20 | D25: =C25+(C25*6%)+(C25*10%) -> 23.2 | E25: =(C25-B25)/C25 -> 0.852665
A26: FRENCH TOAST W/BERRY COMPOTE | B26: ='Menu item calculator'!F309 -> 5.3527634 | C26: 28 | D26: =C26+(C26*6%)+(C26*10%) -> 32.48 | E26: =(C26-B26)/C26 -> 0.80882988
A27: FRENCH TOAST W/BANANA BACON | B27: ='Menu item calculator'!F320 -> 5.8647389 | C27: 30 | D27: =C27+(C27*6%)+(C27*10%) -> 34.8 | E27: =(C27-B27)/C27 -> 0.8045087
A28: FRENCH TOAST W/BACON & MAPLE | B28: ='Menu item calculator'!F331 -> 5.7092389 | C28: 30 | D28: =C28+(C28*6%)+(C28*10%) -> 34.8 | E28: =(C28-B28)/C28 -> 0.80969204
A29: FRENCH TOAST W/PEARS & BACON | B29: 7.8397811 | C29: 26 | D29: =C29+(C29*6%)+(C29*10%) -> 30.16 | E29: =(C29-B29)/C29 -> 0.69846996
A30: TOMATO W/ MUSHROOM ON TOAST | B30: ='Menu item calculator'!F360 -> 6.7422917 | C30: 29 | D30: =C30+(C30*6%)+(C30*10%) -> 33.64 | E30: =(C30-B30)/C30 -> 0.76750718
A31: BACON & EGG PIE | B31: ='Menu item calculator'!F378 -> 10.595723 | C31: 30 | D31: =C31+(C31*6%)+(C31*10%) -> 34.8 | E31: =(C31-B31)/C31 -> 0.64680924
A32: SCRAMBLED EGGS FETA W/SPINACH | B32: ='Menu item calculator'!F389 -> 6.4831278 | C32: 28 | D32: =C32+(C32*6%)+(C32*10%) -> 32.48 | E32: =(C32-B32)/C32 -> 0.76845972
A33: AVOCADO BACON ON TOAST | B33: ='Menu item calculator'!F402 -> 3.4825109 | C33: 33 | D33: =C33+(C33*6%)+(C33*10%) -> 38.28 | E33: =(C33-B33)/C33 -> 0.89446937
A34: AVOCADO HALOUMI CHEES ON TOAST | B34: ='Menu item calculator'!F415 -> 7.4961841 | C34: 33 | D34: =C34+(C34*6%)+(C34*10%) -> 38.28 | E34: =(C34-B34)/C34 -> 0.77284291
A35: AVOCADO ON TOAST W/ SALMON | B35: ='Menu item calculator'!F430 -> 8.1066261 | C35: 33 | D35: =C35+(C35*6%)+(C35*10%) -> 38.28 | E35: =(C35-B35)/C35 -> 0.75434467
A36: NASI GORENG | B36: ='Menu item calculator'!F447 -> 5.6296128 | C36: 34 | D36: =C36+(C36*6%)+(C36*10%) -> 39.44 | E36: =(C36-B36)/C36 -> 0.83442315
A37: OPEN BACON ROCKET SANDWICH | B37: ='Menu item calculator'!F459 -> 6.5508333 | C37: 28 | D37: =C37+(C37*6%)+(C37*10%) -> 32.48 | E37: =(C37-B37)/C37 -> 0.76604167
A38: OPEN BACON LETTUCE SANDWICH | B38: ='Menu item calculator'!F471 -> 6.0708333 | C38: 28 | D38: =C38+(C38*6%)+(C38*10%) -> 32.48 | E38: =(C38-B38)/C38 -> 0.78318452
A39: OPEN CHICKEN SANDWICH | B39: ='Menu item calculator'!F483 -> 3.6417156 | C39: 28 | D39: =C39+(C39*6%)+(C39*10%) -> 32.48 | E39: =(C39-B39)/C39 -> 0.86993873
A40: THAI CHICKEN SATAY | B40: ='Menu item calculator'!F494 -> 4.7674818 | C40: 26 | D40: =C40+(C40*6%)+(C40*10%) -> 30.16 | E40: =(C40-B40)/C40 -> 0.81663532
A41: VIETNAMESE BEEF NOODLE | B41: ='Menu item calculator'!F510 -> 12.452476 | C41: 26 | D41: =C41+(C41*6%)+(C41*10%) -> 30.16 | E41: =(C41-B41)/C41 -> 0.52105861
A42: DOUBLE SALMON FISH CAKE | B42: ='Menu item calculator'!F522 -> 7.9840294 | C42: 28 | D42: =C42+(C42*6%)+(C42*10%) -> 32.48 | E42: =(C42-B42)/C42 -> 0.71485609
A43: GRILLED CHICKEN W/TOMATOES | B43: ='Menu item calculator'!F536 -> 6.2855289 | C43: 28 | D43: =C43+(C43*6%)+(C43*10%) -> 32.48 | E43: =(C43-B43)/C43 -> 0.77551683
A44: FISH & CHIPS | B44: ='Menu item calculator'!F550 -> 14.40425 | C44: 34 | D44: =C44+(C44*6%)+(C44*10%) -> 39.44 | E44: =(C44-B44)/C44 -> 0.5763456
A45: FRENCH FRIES | B45: ='Menu item calculator'!F557 -> 2.288 | C45: 14 | D45: =C45+(C45*6%)+(C45*10%) -> 16.24 | E45: =(C45-B45)/C45 -> 0.83657143
A46: WEDGES | B46: ='Menu item calculator'!F565 -> 3.7911271 | C46: 14 | D46: =C46+(C46*6%)+(C46*10%) -> 16.24 | E46: =(C46-B46)/C46 -> 0.72920521
A47: KUMERA WEDGES | B47: ='Menu item calculator'!F573 -> 1.0111271 | C47: 14 | D47: =C47+(C47*6%)+(C47*10%) -> 16.24 | E47: =(C47-B47)/C47 -> 0.92777664
A48: CHICKEN KEBAB | B48: ='Menu item calculator'!F585 -> 8.6910762 | C48: 34 | D48: =C48+(C48*6%)+(C48*10%) -> 39.44 | E48: =(C48-B48)/C48 -> 0.74438011
A49: BEEF KEBAB | B49: ='Menu item calculator'!F597 -> 25.822882 | C49: 42 | D49: =C49+(C49*6%)+(C49*10%) -> 48.72 | E49: =(C49-B49)/C49 -> 0.38516948
A50: LAMB KEBAB | B50: ='Menu item calculator'!F609 -> 20.535478 | C50: 42 | D50: =C50+(C50*6%)+(C50*10%) -> 48.72 | E50: =(C50-B50)/C50 -> 0.51106006
A51: WHAKATIKI CHICKEN | B51: ='Menu item calculator'!F624 -> 6.8691815 | C51: 34 | D51: =C51+(C51*6%)+(C51*10%) -> 39.44 | E51: =(C51-B51)/C51 -> 0.79796525
A52: SWEET PAPRIKA CHICKEN | B52: ='Menu item calculator'!F634 -> 4.7293686 | C52: 28 | D52: =C52+(C52*6%)+(C52*10%) -> 32.48 | E52: =(C52-B52)/C52 -> 0.83109398
A53: RED SOUP | B53: ='Menu item calculator'!F643 -> 2.4317299 | C53: 18 | D53: =C53+(C53*6%)+(C53*10%) -> 20.88 | E53: =(C53-B53)/C53 -> 0.8649039
A54: PUMPKIN SOUP | B54: ='Menu item calculator'!F653 -> 1.9642361 | C54: 18 | D54: =C54+(C54*6%)+(C54*10%) -> 20.88 | E54: =(C54-B54)/C54 -> 0.89087577
A55: ---- EXTRAS ---- | D55: =C55+(C55*6%)+(C55*10%) -> 0 | E55: =(C55-B55)/C55 -> #DIV/0!
A56: SALMON 50GM | B56: 6.4 | C56: 14 | D56: =C56+(C56*6%)+(C56*10%) -> 16.24 | E56: =(C56-B56)/C56 -> 0.54285714
A57: SALMON 100GM | B57: 12.8 | C57: 28 | D57: =C57+(C57*6%)+(C57*10%) -> 32.48 | E57: =(C57-B57)/C57 -> 0.54285714
A58: ROCKET | C58: 14 | D58: =C58+(C58*6%)+(C58*10%) -> 16.24 | E58: =(C58-B58)/C58 -> 1
A59: SPINACH | B59: 2.18 | C59: 14 | D59: =C59+(C59*6%)+(C59*10%) -> 16.24 | E59: =(C59-B59)/C59 -> 0.84428571
A60: HASHBROWN | B60: 1.5 | C60: 13 | D60: =C60+(C60*6%)+(C60*10%) -> 15.08 | E60: =(C60-B60)/C60 -> 0.88461538
A61: BAKED BEANS | B61: 0.8 | C61: 14 | D61: =C61+(C61*6%)+(C61*10%) -> 16.24 | E61: =(C61-B61)/C61 -> 0.94285714
A62: MUSHROOMS | B62: 4.8 | C62: 14 | D62: =C62+(C62*6%)+(C62*10%) -> 16.24 | E62: =(C62-B62)/C62 -> 0.65714286
A63: TOMATO | B63: 0.96 | C63: 13 | D63: =C63+(C63*6%)+(C63*10%) -> 15.08 | E63: =(C63-B63)/C63 -> 0.92615385
A64: BACK BACON | B64: 9.2 | C64: 14 | D64: =C64+(C64*6%)+(C64*10%) -> 16.24 | E64: =(C64-B64)/C64 -> 0.34285714
A65: STREAKY BACON | B65: 9.4 | C65: 14 | D65: =C65+(C65*6%)+(C65*10%) -> 16.24 | E65: =(C65-B65)/C65 -> 0.32857143
A66: CHEESE | B66: 16.3 | C66: 13 | D66: =C66+(C66*6%)+(C66*10%) -> 15.08 | E66: =(C66-B66)/C66 -> -0.25384615
A67: SAUSAGE - CHICKEN | B67: 4.56 | C67: 14 | D67: =C67+(C67*6%)+(C67*10%) -> 16.24 | E67: =(C67-B67)/C67 -> 0.67428571
A68: SAUSAGE - BEEF | B68: 5.1 | C68: 14 | D68: =C68+(C68*6%)+(C68*10%) -> 16.24 | E68: =(C68-B68)/C68 -> 0.63571429
A69: SAUSAGE - PORK | B69: 4.57 | C69: 14 | D69: =C69+(C69*6%)+(C69*10%) -> 16.24 | E69: =(C69-B69)/C69 -> 0.67357143
A70: GRILLED CHICKEN | B70: 2.18 | C70: 14 | D70: =C70+(C70*6%)+(C70*10%) -> 16.24 | E70: =(C70-B70)/C70 -> 0.84428571
... A73: SALAD | B73: 1.5 | C73: 13 | D73: =C73+(C73*6%)+(C73*10%) -> 15.08 | E73: =(C73-B73)/C73 -> 0.88461538
A74: ---- BURGER ---- | C74: 2 | D74: =C74+(C74*6%)+(C74*10%) -> 2.32 | E74: =(C74-B74)/C74 -> 1
A75: LAMB BURGER | B75: ='Menu item calculator'!F670 -> 15.236594 | C75: 28 | D75: =C75+(C75*6%)+(C75*10%) -> 32.48 | E75: =(C75-B75)/C75 -> 0.45583595
A76: BEEF BURGER | B76: ='Menu item calculator'!F687 -> 12.068348 | C76: 28 | D76: =C76+(C76*6%)+(C76*10%) -> 32.48 | E76: =(C76-B76)/C76 -> 0.56898756
A77: ---- PANINI ---- | D77: =C77+(C77*6%)+(C77*10%) -> 0 | E77: =(C77-B77)/C77 -> #DIV/0!
A78: TOASTED SANDWICH W/MEATBALL | B78: ='Menu item calculator'!F702 -> 10.53688 | C78: 29 | D78: =C78+(C78*6%)+(C78*10%) -> 33.64 | E78: =(C78-B78)/C78 -> 0.63665932
A79: TOASTED SANDWICH W/CHEESE | B79: ='Menu item calculator'!F717 -> 6.6146118 | C79: 28 | D79: =C79+(C79*6%)+(C79*10%) -> 32.48 | E79: =(C79-B79)/C79 -> 0.76376387
A80: TOASTED SANDWICH W/BACON | B80: ='Menu item calculator'!F732 -> 9.314629 | C80: 29 | D80: =C80+(C80*6%)+(C80*10%) -> 33.64 | E80: =(C80-B80)/C80 -> 0.6788059
A81: ---- BAGEL ---- | D81: =C81+(C81*6%)+(C81*10%) -> 0 | E81: =(C81-B81)/C81 -> #DIV/0!
A82: BAGEL W/CHORIZO | B82: ='Menu item calculator'!F747 -> 8.7762664 | C82: 28 | D82: =C82+(C82*6%)+(C82*10%) -> 32.48 | E82: =(C82-B82)/C82 -> 0.68656192
A83: BAGEL W/FRIED EGG & BACON | B83: ='Menu item calculator'!F759 -> 8.4688572 | C83: 28 | D83: =C83+(C83*6%)+(C83*10%) -> 32.48 | E83: =(C83-B83)/C83 -> 0.69754081
A84: BAGEL W/BACON TOMATO PESTO | B84: ='Menu item calculator'!F771 -> 6.7752239 | C84: 28 | D84: =C84+(C84*6%)+(C84*10%) -> 32.48 | E84: =(C84-B84)/C84 -> 0.75802772
A85: BAGEL W/SALMON & CAPERS | B85: ='Menu item calculator'!F785 -> 11.938032 | C85: 26 | D85: =C85+(C85*6%)+(C85*10%) -> 30.16 | E85: =(C85-B85)/C85 -> 0.54084491
A86: BAGEL W/BLUEBERRY | B86: ='Menu item calculator'!F796 -> 7.8541174 | C86: 16 | D86: =C86+(C86*6%)+(C86*10%) -> 18.56 | E86: =(C86-B86)/C86 -> 0.50911766
A87: BAGEL W/CREAM CHEESE | B87: ='Menu item calculator'!F804 -> 3.2159121 | C87: 16 | D87: =C87+(C87*6%)+(C87*10%) -> 18.56 | E87: =(C87-B87)/C87 -> 0.79900549
A88: ---- CROISSANT ---- | D88: =C88+(C88*6%)+(C88*10%) -> 0 | E88: =(C88-B88)/C88 -> #DIV/0!
A89: CROISSANT W/BUTTER & JAM | B89: ='Menu item calculator'!F813 -> 1.5932233 | C89: 16 | D89: =C89+(C89*6%)+(C89*10%) -> 18.56 | E89: =(C89-B89)/C89 -> 0.90042354
A90: CROISSANT SM EGGS W/CHICKEN | B90: ='Menu item calculator'!F823 -> 8.2742778 | C90: 26 | D90: =C90+(C90*6%)+(C90*10%) -> 30.16 | E90: =(C90-B90)/C90 -> 0.68175855
A91: CROISSANT SM EGGS W/BEEF | B91: ='Menu item calculator'!F833 -> 8.6657778 | C91: 26 | D91: =C91+(C91*6%)+(C91*10%) -> 30.16 | E91: =(C91-B91)/C91 -> 0.66670085
A92: CROISSANT SM EGGS W/PORK | B92: ='Menu item calculator'!F843 -> 8.2742778 | C92: 26 | D92: =C92+(C92*6%)+(C92*10%) -> 30.16 | E92: =(C92-B92)/C92 -> 0.68175855
A93: CROISSANT SM EGGS W/BACON | B93: ='Menu item calculator'!F853 -> 8.2742778 | C93: 27 | D93: =C93+(C93*6%)+(C93*10%) -> 31.32 | E93: =(C93-B93)/C93 -> 0.69354527
A94: ---- SALAD ---- | D94: =C94+(C94*6%)+(C94*10%) -> 0 | E94: =(C94-B94)/C94 -> #DIV/0!
A95: BURMESE SHREDDED CHICKEN | B95: ='Menu item calculator'!F866 -> 2.0725221 | C95: 25 | D95: =C95+(C95*6%)+(C95*10%) -> 29 | E95: =(C95-B95)/C95 -> 0.91709912
A96: CHICKPEAS FETA W/ CORRIANDER | B96: ='Menu item calculator'!F875 -> 2.9904747 | C96: 22 | D96: =C96+(C96*6%)+(C96*10%) -> 25.52 | E96: =(C96-B96)/C96 -> 0.86406933
A97: ROAST VEGE SALAD | B97: ='Menu item calculator'!F885 -> 4.2914643 | C97: 28 | D97: =C97+(C97*6%)+(C97*10%) -> 32.48 | E97: =(C97-B97)/C97 -> 0.84673342
A98: THAI BEEF SALAD | B98: ='Menu item calculator'!F902 -> 11.494405 | C98: 30 | D98: =C98+(C98*6%)+(C98*10%) -> 34.8 | E98: =(C98-B98)/C98 -> 0.61685317
A99: MIX SALAD W/COUS COUS | B99: ='Menu item calculator'!F914 -> 7.0877778 | C99: 24 | D99: =C99+(C99*6%)+(C99*10%) -> 27.84 | E99: =(C99-B99)/C99 -> 0.70467593
A100: BEETROOT & NUTS SALAD | B100: 3.3643375 | C100: 24 | D100: =C100+(C100*6%)+(C100*10%) -> 27.84 | E100: =(C100-B100)/C100 -> 0.85981927 | F100: Missing recipe
A101: GREEK SALAD | B101: ='Menu item calculator'!F928 -> 3.4122727 | C101: 24 | D101: =C101+(C101*6%)+(C101*10%) -> 27.84 | E101: =(C101-B101)/C101 -> 0.85782197
A102: BUFFALO MOZZARELLA | B102: ='Menu item calculator'!F940 -> 17.072 | C102: 30 | D102: =C102+(C102*6%)+(C102*10%) -> 34.8 | E102: =(C102-B102)/C102 -> 0.43093333
...

Sheet Master Price list
A1: SUPPLIER NAME | B1: OUTLET ITEM CODE | C1: ITEM DESCRIPTION | D1: SUPPLIER UOM | E1: CONVERTED UOM | F1: SUPPLIER PRICE | G1: CONVERTED PRICE
A2: LEE'S FROZEN SDN BHD | B2: MT-01 | C2: BEEF STRIPLOIN (BURGER) | D2: KG | E2: KG | F2: 56 | G2: 56
A3: LEE'S FROZEN SDN BHD | B3: MT-02 | C3: BEEF TENDERLOIN (KEBAB/SALAD/NOODLE) | D3: KG | E3: KG | F3: 100 | G3: 100
A4: NEW CUISINEFINE FOODS SDN BHD | B4: MT-03 | C4: LAMB LEG (KEBAB/BURGER) | D4: KG | E4: KG | F4: 71 | G4: 71
A5: NEW CUISINEFINE FOODS SDN BHD | B5: MT-04 | C5: MINCED BEEF | D5: KG | E5: KG | F5: 40 | G5: 40
A6: NEW CUISINEFINE FOODS SDN BHD | B6: MT-05 | C6: MINCED LAMB | D6: KG | E6: KG | F6: 56.5 | G6: 56.5
A7: ORIENTS FRESH DELI SDN BHD | B7: MT-06 | C7: BACK BACON, SLICED | D7: KG | E7: KG | F7: 45.7 | G7: 45.7
A8: ORIENTS FRESH DELI SDN BHD | B8: MT-07 | C8: STREAKY BACON, SLICED | D8: KG | E8: KG | F8: 47 | G8: 39.38
A9: EURO DELI MANUFACTURING SDN BHD | B9: MT-08 | C9: BEEF SAUSAGE | D9: KG | E9: KG | F9: 50.92 | G9: 50.92
A10: EURO DELI MANUFACTURING SDN BHD | B10: MT-09 | C10: CHORIZO SAUSAGE | D10: KG | E10: KG | F10: 42.94 | G10: 42.94
A11: EURO DELI MANUFACTURING SDN BHD | B11: MT-10 | C11: PORK SAUSAGE, BANGER | D11: KG | E11: KG | F11: 45.7 | G11: 45.7
A12: HANKEE PROCESSING SDN BHD | B12: PT-01 | C12: CHICKEN FILLET | D12: CTN / 6PKT/ 2KG | E12: KG | F12: 18 | G12: =F12/2 -> 9
A13: HANKEE PROCESSING SDN BHD | B13: PT-02 | C13: CHICKEN BREAST, WITH SKIN | D13: CTN / 6PKT/ 2KG | E13: KG | F13: 20.6 | G13: =F13/2 -> 10.3
A14: EURO DELI MANUFACTURING SDN BHD | B14: PT-04 | C14: CHICKEN SAUSAGE, BLACK PEPPER | D14: KG | E14: KG | F14: 45.7 | G14: 45.7
A15: ORIENTS FRESH DELI SDN BHD | B15: PT-05 | C15: SMOKED CHICKEN | D15: KG | E15: KG | F15: 26.57 | G15: 26.57
A16: NEW CUISINEFINE FOODS SDN BHD | B16: FISH-01 | C16: SALMON FILLET, NORWAY | D16: KG | E16: KG | F16: 80 | G16: 80
A17: NEW CUISINEFINE FOODS SDN BHD | B17: FISH-02 | C17: SMOKED SALMON FILLET, PRESLICED, FROZEN (NOR) | D17: KG | E17: KG | F17: 128 | G17: 128
A18: ALBATROSS EXIM (M) SDN BHD | B18: FISH-03 | C18: HOKI FILLET | D18: KG | E18: KG | F18: 41 | G18: 41
A19: NEW CUISINEFINE FOODS SDN BHD | B19: FISH-04 | C19: DORY FILLET | D19: PKT / 750GM | E19: KG | F19: 43.9 | G19: =F19/750*1000 -> 58.533333
A20: GLOBAL-PACIFIC VICTORY (M) SDN BHD | B20: DR-01 | C20: BUFFALO MOZZARELLA CHEESE | D20: PKT / 125GM | E20: PKT | F20: 15 | G20: 15
A21: NEW CUISINE FINEFOODS SDN BHD | B21: DR-02 | C21: BUTTER, SALTED | D21: CTN / 25KG | E21: KG | F21: 980 | G21: =F21/25 -> 39.2
A22: NEW CUISINE FINEFOODS SDN BHD | B22: DR-03 | C22: CREAME CHEESE | D22: BLOCK / 1.8KG | E22: KG | F22: 68.2 | G22: =F22/1800*1000 -> 37.888889
A23: GLOBAL-PACIFIC VICTORY (M) SDN BHD | B23: DR-04 | C23: CAMEMBERT CHEESE | D23: PKT / 125GM | E23: KG | F23: 16.5 | G23: =F23/125*1000 -> 132
A24: NEW CUISINE FINEFOODS SDN BHD | B24: DR-05 | C24: CHEDDAR CHEESE, SHREDDED | D24: PKT / 2KG | E24: KG | F24: 100 | G24: =F24/2 -> 50
A25: PASTRY PRO SDN BHD | B25: DR-06 | C25: CHOCOLATE CHIPS, COMPOUND DARK | D25: PKT / 5KG | E25: KG | F25: 17.9 | G25: =F25/5 -> 3.58
A26: PASTRY PRO SDN BHD | B26: DR-07 | C26: DARK BITTER SWEET CHOCOLATE, 60% | D26: PKT / 1KG | E26: KG | F26: 50.8 | G26: 50.8
A27: BIDFOOD MALAYSIA SDN BHD | B27: DR-08 | C27: FARMHOUSE COFFEE MILK | D27: CTN / 12 PKT | E27: KG | F27: 108 | G27: =F27/12 -> 9
A28: BIDFOOD MALAYSIA SDN BHD | B28: DR-09 | C28: FARMHOUSE LOW FAT MILK | D28: CTN / 12 PKT | E28: KG | G28: =F28/12 -> 0
A29: NEW CUISINE FINEFOODS SDN BHD | B29: DR-10 | C29: FETA CHEESE | D29: CTN / 6TUB / 200GM | E29: KG | F29: 17 | G29: =F29/200*1000 -> 85
A30: GLOBAL-PACIFIC VICTORY (M) SDN BHD | B30: DR-11 | C30: HALOUMI CHEESE | D30: PKT / 180GM | E30: KG | F30: 26 | G30: =F30/180*1000 -> 144.44444
A31: GLOBAL-PACIFIC VICTORY (M) SDN BHD | B31: DR-12 | C31: MASCARPONE CHEESE | D31: PKT / 1KG | E31: KG | F31: 38.1 | G31: 38.1
A32: NEW CUISINE FINEFOODS SDN BHD | B32: DR-14 | C32: MOZZARELLA CHEESE, SHREDDED | D32: PKT / 2KG | E32: KG | F32: 81.5 | G32: =F32/2 -> 40.75
A33: GLOBAL-PACIFIC VICTORY (M) SDN BHD | B33: DR-15 | C33: PARMESAN CHEESE, PARMIGIANO REGIANO | D33: KG | E33: KG | F33: 95 | G33: 95
A34: GLOBAL-PACIFIC VICTORY (M) SDN BHD | B34: DR-16 | C34: SOUR CREAM | D34: PKT / 1KG | E34: KG | F34: 20.5 | G34: 20.5
A35: NEW CUISINE FINEFOODS SDN BHD | B35: DR-17 | C35: YOGURT | D35: TUB / 1KG | E35: KG | F35: 29 | G35: 29
A36: GLOBAL-PACIFIC VICTORY (M) SDN BHD | B36: DR-18 | C36: WHIPPING CREAM 38% | D36: PKT / 1LITRE | E36: KG | F36: 22 | G36: 22
A37: GLOBAL-PACIFIC VICTORY (M) SDN BHD | B37: DR-19 | C37: WHIPPING CREAM (AEROSOL) | D37: TIN / 400GM | E37: KG | F37: 22 | G37: =F37/400*1000 -> 55
A38: PASTRY PRO SDN BHD | B38: DR-20 | C38: WHITE CHOCOLATE CHIPS 35% | D38: PKT / 1KG | E38: KG | F38: 67.3 | G38: 67.3
A39: FRESHMEN MARKETING SDN BHD | B39: SS-01 | C39: BAY LEAF, DRIED | D39: PKT / 1KG | E39: KG | F39: 15 | G39: 15
A40: FRESHMEN MARKETING SDN BHD | B40: SS-02 | C40: BLACK PEPPERCORN | D40: PKT / 1KG | E40: KG | F40: 48 | G40: 48
A41: YONG WEN FOOD (M) SDN BHD | B41: SS-03 | C41: BLACK PEPPER, FINE COURSE | D41: PKT /500GM | E41: KG | F41: 28 | G41: =F41*2 -> 56
A42: YONG WEN FOOD (M) SDN BHD | B42: SS-04 | C42: CAJUN SPICE | D42: PKT /500GM | E42: KG | F42: 24.5 | G42: =F42*2 -> 49
B43: SS-05 | C43: CARDAMOM POWDER | D43: PKT / 1KG | E43: KG | F43: 115 | G43: 215
A44: FRESHMEN MARKETING SDN BHD | B44: SS-06 | C44: CAYENNE POWDER | D44: PKT / 1KG | E44: KG | F44: 35 | G44: 35
A45: YONG WEN FOOD (M) SDN BHD | B45: SS-07 | C45: CHILLI FLAKES | D45: PKT / 1KG | E45: KG | F45: 28 | G45: 28
A46: FRESHMEN MARKETING SDN BHD | B46: SS-08 | C46: CHILLI POWDER | D46: PKT / 1KG | E46: KG | F46: 29.5 | G46: 29.5
A47: YONG WEN FOOD (M) SDN BHD | B47: SS-09 | C47: CINNAMON GROUND - DRAGON | D47: PKT / 1KG | E47: KG | F47: 35 | G47: 35
A48: FRESHMEN MARKETING SDN BHD | B48: SS-10 | C48: CORIANDER SEED | D48: PKT / 1KG | E48: KG | F48: 12 | G48: 12
A49: FRESHMEN MARKETING SDN BHD | B49: SS-11 | C49: CORIANDER POWDER | D49: PKT / 1KG | E49: KG | F49: 22 | G49: 22
A50: FRESHMEN MARKETING SDN BHD | B50: SS-12 | C50: CUMIN SEEDS | D50: PKT / 1KG | E50: KG | F50: 23 | G50: 23
A51: FRESHMEN MARKETING SDN BHD | B51: SS-13 | C51: CUMIN POWDER | D51: PKT / 1KG | E51: KG | F51: 56 | G51: 56
A52: FRESHMEN MARKETING SDN BHD | B52: SS-14 | C52: CURRY POWDER | D52: PKT / 1KG | E52: KG | F52: 28 | G52: 28
A53: THAI GLOBAL VENTURE | B53: SS-15 | C53: FISH SAUCE, TIPAROS | D53: BTL / 700GM | E53: KG | F53: 60 | G53: =F53/700*1000 -> 85.714286
A54: YONG WEN FOOD (M) SDN BHD | B54: SS-16 | C54: GARLIC POWDER | D54: PKT / 1KG | E54: KG | F54: 43.8 | G54: 43.8
A55: YONG WEN FOOD (M) SDN BHD | B55: SS-17 | C55: GINGER POWDER | D55: PKT / 1KG | E55: KG | F55: 45 | G55: 45
A56: CASH | B56: SS-18 | C56: LEA & PERRINS | D56: BTL / 290ML | E56: KG | F56: 12 | G56: =F56/290*1000 -> 41.37931
A57: YONG WEN FOOD (M) SDN BHD | B57: SS-19 | C57: LEMON & PEPPER SEASONING | D57: PKT / 1KG | E57: KG | F57: 70 | G57: 70
A58: YONG WEN FOOD (M) SDN BHD | B58: SS-20 | C58: NUTMEG POWDER | D58: PKT /500GM | E58: KG | F58: 31 | G58: =F58*2 -> 62
A59: FRESHMEN MARKETING SDN BHD | B59: SS-21 | C59: OREGANO, GROUND | D59: PKT / 1KG | E59: KG | F59: 24 | G59: 24
A60: FRESHMEN MARKETING SDN BHD | B60: SS-22 | C60: PAPRIKA POWDER, SWEET | D60: PKT / 1KG | E60: KG | F60: 42 | G60: 42
A61: YONG WEN FOOD (M) SDN BHD | B61: SS-23 | C61: RAS EL HANOUT | D61: PKT / 1KG | E61: KG | F61: 75 | G61: 75
A62: CASH | B62: SS-24 | C62: SALT, FINE | D62: PKT/ 450GM | E62: KG | F62: 2 | G62: =F62/450*1000 -> 4.4444444
A63: CASH | B63: SS-25 | C63: SUMAC POWDER | D63: PKT / 100GM | E63: KG | F63: 75 | G63: =F63/100*1000 -> 750
A64: YONG WEN FOOD (M) SDN BHD | B64: SS-26 | C64: TURMERIC POWDER | D64: PKT / 1KG | E64: KG | F64: 28 | G64: 28
A65: YONG WEN FOOD (M) SDN BHD | B65: SS-27 | C65: THYME LEAVES , DRIED | D65: PKT /500GM | E65: KG | F65: 27 | G65: =F65*2 -> 54
A66: CASH | B66: SS-28 | C66: ZAATAR SEASONING | D66: PKT / 150GM | E66: KG | F66: 80 | G66: =F66/150*1000 -> 533.33333
A67: DISCONTINUED | B67: BRD-03 | C67: BRIOCHE BURGER BUN SEEDED | D67: CTN / 36PCS | E67: PCS | F67: 68.4 | G67: =F67/36 -> 1.9
A68: ARYZTA FOOD SOLUTIONS MALAYSIA SDN BHD | B68: BRD-04 | C68: CROISSANT, FROZEN, BUTTER GIPFEL CLOSED | D68: CTN / 4PKT / 15PCS | E68: PCS | F68: 40.1 | G68: =F68/60 -> 0.66833333
A69: ARYZTA FOOD SOLUTIONS MALAYSIA SDN BHD | B69: BRD-05 | C69: FRENCH VILLAGE | D69: CTN / 12PCS / 350GM | E69: PCS | F69: 79.81 | G69: =(F69/12)/10 -> 0.66508333
A70: PASTRY WORLD SDN BHD | B70: BRD-06 | C70: TOAST, SANDWICH LOAF, WHITE, UNSLICED | D70: LOAF | E70: SLICE | F70: 8.5 | G70: =F70/10 -> 0.85
A71: ARYZTA FOOD SOLUTIONS MALAYSIA SDN BHD | B71: BRD-08 | C71: SOUR DOUGH | D71: CTN / 12PCS / 500GM | E71: SLICE | F71: 128.7 | G71: =(F71/12)/10 -> 1.0725
A72: CASH | B72: DRI-01 | C72: APPLE JUICE | D72: BTL / 1LITRE | E72: KG | F72: 9.5 | G72: 9.5
A73: YONG WEN FOOD (M) SDN BHD | B73: DRI-02 | C73: ARTICHOKE IN BRINE | D73: TIN | E73: TIN | F73: 12 | G73: 12
A74: PASTRY PRO SDN BHD | B74: DRI-03 | C74: BLACK RAISINS | D74: PKT / 1KG | E74: KG | F74: 18.95 | G74: 18.95
A75: YONG WEN FOOD (M) SDN BHD | B75: DRI-04 | C75: BREAD CRUMBS | D75: PKT / 1KG | E75: KG | F75: 9.2 | G75: 9.2
A76: SUNLAND VOLONTE AGENCY SDN BHD | B76: DRI-05 | C76: CAPERS | D76: BOTTLE / 935GM | E76: KG | F76: 39.5 | G76: =F76/936*1000 -> 42.200855
A77: GLOBAL-PACIFIC VICTORY (M) SDN BHD | B77: DRI-06 | C77: CHICK PEAS IN BRINE | D77: CAN / 400GM | E77: KG | F77: 4.5 | G77: =F77/400*1000 -> 11.25
A78: CASH | B78: DRI-10 | C78: CONDENCED MILK | D78: TIN / 500GM | E78: KG | F78: 2.3 | G78: =F78*2 -> 4.6
A79: GLOBAL-PACIFIC VICTORY (M) SDN BHD | B79: DRI-11 | C79: COUS COUS | D79: PKT / 1KG | E79: KG | F79: 12 | G79: 12
A80: SUNLAND VOLONTE AGENCY SDN BHD | B80: DRI-12 | C80: OLIVE OIL(1L) | D80: BOTTLE / 1LITRE | E80: KG | F80: 42 | G80: 42
A81: PASTRY PRO SDN BHD | B81: DRI-13 | C81: FIG, DRIED | D81: PKT / 1KG | E81: KG | F81: 44.7 | G81: 44.7
A82: SUNLAND VOLONTE AGENCY SDN BHD | B82: DRI-14 | C82: GHERKINS | D82: BTL / 680GM | E82: KG | F82: 8.5 | G82: =F82/680*1000 -> 12.5
A83: CASH | B83: DRI-15 | C83: HONDASHI POWDER | D83: PKT / 1KG | E83: KG | F83: 29.5 | G83: 29.5
A84: YONG WEN FOOD (M) SDN BHD | B84: DRI-17 | C84: KALAMATA OLIVES | D84: TUB / 3.3KG | E84: KG | F84: 75 | G84: =F84/3300*1000 -> 22.727273
A85: YONG WEN FOOD (M) SDN BHD | B85: DRI-18 | C85: LYCHEE IN SYRUP | D85: CTN / 12TIN / 565GM | E85: KG | F85: 4.8 | G85: =F85/565*1000 -> 8.4955752
A86: CASH | B86: DRI-19 | C86: MARMALADE JAM, ORANGE | F86: 5.3 | G86: 5.3
A87: GLOBAL-PACIFIC VICTORY (M) SDN BHD | B87: DRI-23 | C87: ORZO PASTA, GRANORO ROSMARINO (69) | D87: PKT / 500GM | E87: PKT / 500GM | F87: 6 | G87: =F87 -> 6
A88: CASH | B88: DRI-24 | C88: OYSTER SAUCE
A89: YONG WEN FOOD (M) SDN BHD | B89: DRI-25 | C89: PEAR HALVES | D89: TIN / 825GM | E89: TIN / 825GM | F89: 9.55 | G89: 9.55
A90: PASTRY PRO SDN BHD | B90: DRI-26 | C90: QUICK OATS | D90: PKT / 1KG | E90: KG | F90: 10.3 | G90: 10.3
A91: YONG WEN FOOD (M) SDN BHD | B91: DRI-27 | C91: RED WINE VINEGAR | D91: BTL / 500GM | E91: KG | F91: 9.5 | G91: =F91*2 -> 19
A92: PASTRY PRO SDN BHD | B92: DRI-28 | C92: ROLLED OATS | D92: PKT / 1KG | E92: KG | F92: 10.4 | G92: 10.4
A93: YONG WEN FOOD (M) SDN BHD | B93: DRI-29 | C93: SHELL PASTA | D93: PKT / 500GM | E93: PKT / 500GM | F93: 4 | G93: =F93 -> 4
A94: CASH | B94: DRI-30 | C94: SOY SAUCE, ANGEL BRAND | D94: BTL / 750ML | E94: KG | F94: 8.9 | G94: =F94/750*1000 -> 11.866667
A95: GLOBAL-PACIFIC VICTORY (M) SDN BHD | B95: DRI-31 | C95: SPAGHETTI PASTA, SIZE 14 | D95: PKT / 500GM | E95: PKT / 500GM | F95: 6 | G95: =F95 -> 6
A96: SUNLAND VOLONTE AGENCY SDN BHD | B96: DRI-33 | C96: SUNDRIED TOMATOES | D96: BOTTLE / 2.9KG | E96: KG | F96: 135 | G96: =F96/2900*1000 -> 46.551724
A97: YONG WEN FOOD (M) SDN BHD | B97: DRI-34 | C97: SUNFLOWER OIL | D97: BTL / 2LITRE | E97: KG | F97: 27 | G97: =F97/2 -> 13.5
A98: YONG WEN FOOD (M) SDN BHD | B98: DRI-35 | C98: SWEET CORN | D98: TIN / 425GM | E98: KG | F98: 3.1 | G98: =F98/425*1000 -> 7.2941176
A99: GLOBAL-PACIFIC VICTORY (M) SDN BHD | B99: DRI-36 | C99: TOMATO PASTE | D99: TIN / 2.2KG | E99: KG | F99: 36 | G99: =F99/2200*1000 -> 16.363636
A100: CASH | B100: DRI-37 | C100: TOMATO PUREE, PREGO | D100: BTL / 600GM | E100: KG | F100: 11.75 | G100: =F100/600*1000 -> 19.583333
...

Sheet Item list
A1: ITEM NAME | B1: ITEM PRICE | C1: UOM
A2: SCRAMBLED EGGS | B2: ='Item list calculator'!I10 -> 3.6284444 | C2: SERVING
A3: SAUTEED MUSHROOMS | B3: ='Item list calculator'!I23 -> 4.1504444 | C3: SERVING
A4: FRUIT SALAD | B4: ='Item list calculator'!I39 -> 2.9467 | C4: SERVING
A5: BALANA PANCAKE BATTER | B5: ='Item list calculator'!I59 -> 5.4060667 | C5: SERVING
A6: FRENCH TOAST BATTER | B6: ='Item list calculator'!I74 -> 0.67908889 | C6: SERVING
A7: WAFFLE BATTER | B7: ='Item list calculator'!I89 -> 2.3327444 | C7: SERVING
A8: CREPE BATTER | B8: ='Item list calculator'!I102 -> 2.1545599 | C8: SERVING
A9: FISH & CHIPS BATTER | B9: ='Item list calculator'!I115 -> 2.0643378 | C9: SERVING
A10: TOMATO BAGEL | B10: ='Item list calculator'!I132 -> 2.0792454 | C10: PIECE
A11: WHAKATIKI BATTER | B11: ='Item list calculator'!I144 -> 0.94003529 | C11: SERVING
A12: PUMPKIN SOUP | B12: ='Item list calculator'!I158 -> 0.99315278 | C12: SERVING
A13: RED SOUP | B13: ='Item list calculator'!I175 -> 1.1553965 | C13: SERVING
A14: LAMB KEBAB | B14: ='Item list calculator'!I193 -> 15.347866 | C14: SERVING
A15: BEEF KEBAB | B15: ='Item list calculator'!I212 -> 20.63527 | C15: SERVING
A16: GRILLED CHICKEN | B16: ='Item list calculator'!I247 -> 2.0735289 | C16: SERVING
A17: CHICKEN SATAY | B17: ='Item list calculator'!I235 -> 1.9025
A18: SWEET PAPRIKA CHICKEN | B18: ='Item list calculator'!I262 -> 2.8409889 | C18: SERVING
A19: CHICKEN KEBAB | B19: ='Item list calculator'!I282 -> 3.7496444 | C19: SERVING
A20: PIZZA SAUCE | B20: ='Item list calculator'!I299 -> 16.610233 | C20: KG
A21: SALAD DRESSING | B21: ='Item list calculator'!I310 -> 35.2475 | C21: KG
A22: PIZZA DOUGH | B22: ='Item list calculator'!I324 -> 1.2713037 | C22: PIECE
A23: PASTA TOMATO SAUCE | B23: ='Item list calculator'!I338 -> 34.446361 | C23: KG
A24: DOUBLE SALMON FISHCAKE | B24: ='Item list calculator'!I352 -> 4.572451 | C24: SERVING
A25: LAMB BURGER | B25: ='Item list calculator'!I366 -> 9.2651785 | C25: SERVING
A26: BEEF BURGER | B26: ='Item list calculator'!I383 -> 6.0969335 | C26: SERVING
A27: MUESLI | B27: ='Item list calculator'!I394 -> 28.88225 | C27: KG
A28: MEATBALLS | B28: ='Item list calculator'!I408 -> 5.9709 | C28: SERVING
A29: OMELETTE | B29: ='Item list calculator'!I417 -> 7.4593889 | C29: SERVING
A30: HASHBROWN | B30: ='Item list calculator'!I430 -> 1.7707397 | C30: PIECE
A31: HOUSE SALAD | B31: ='Item list calculator'!I442 -> 1.7691118 | C31: SERVING
A32: BEETROOT SALAD | B32: ='Item list calculator'!I456 -> 3.5986875 | C32: SERVING
A33: NUT MIX | B33: ='Item list calculator'!I472 -> 25.96125 | C33: KG
A34: CHICK PEA SALAD | B34: ='Item list calculator'!I486 -> 14.069831 | C34: KG
A35: ROASTED VEGGIE | B35: ='Item list calculator'!I500 -> 1.9002143 | C35: SERVING
A36: AVOCADO SPREAD | B36: ='Item list calculator'!I513 -> 5.5563542 | C36: KG
A37: CHEESE HOLLANDAISE | B37: ='Item list calculator'!I526 -> 48.182254 | C37: KG
A38: TOMATO PESTO | B38: ='Item list calculator'!I540 -> 46.530917 | C38: KG
A39: TARTAR SAUCE | B39: ='Item list calculator'!I555 -> 15.453278 | C39: KG
A40: TZATZIKI SAUCE | B40: ='Item list calculator'!I567 -> 20.794 | C40: KG
A41: SATAY SAUCE | B41: ='Item list calculator'!I578 -> 37.5435 | C41: KG
A42: BURMESE SAUCE | B42: ='Item list calculator'!I591 -> 20.517179 | C42: KG
A43: SANDWICH SAUCE | B43: ='Item list calculator'!I601 -> 15.033333 | C43: KG
A44: BERRY COMPOTE | B44: ='Item list calculator'!I612 -> 113.13497 | C44: KG
A45: BUTTERSCOTH SAUCE | B45: ='Item list calculator'!I624 -> 13.585343 | C45: KG
A46: SPECIAL PIZZA SAUCE | B46: ='Item list calculator'!I634 -> 11.198701 | C46: KG
A47: JALAPENO | B47: ='Item list calculator'!I644 -> 8.3964286 | C47: KG
A48: TOMATO COMPOTE | B48: ='Item list calculator'!I654 -> 6.135 | C48: KG
A49: HARISSA PASTE | B49: ='Item list calculator'!I670 -> 18.076131 | C49: KG
A50: SAMBAL PASTE | B50: ='Item list calculator'!I697 -> 9.6431382 | C50: KG
A51: TOMATO RELISH | B51: ='Item list calculator'!I713 -> 16.43248 | C51: KG
A52: WHAKATIKI SAUCE | B52: ='Item list calculator'!I724 -> 12.161667 | C52: KG
A53: GOLDEN COUS COUS | B53: ='Item list calculator'!I738 -> 14.314 | C53: KG
A54: LAMB BURGER SAUCE | B54: ='Item list calculator'!I749 -> 24.99981 | C54: KG
A55: STRAWBERRY JAM | B55: ='Item list calculator'!I770 -> 35.526 | C55: KG
A56: BAKED BEANS | B56: ='Item list calculator'!I788 -> 19.81927 | C56: KG
A57: CARAMELIZED BANANA | B57: ='Item list calculator'!I799 -> 0.9055 | C57: SERVING
A58: ASPARAGUS BACON | B58: ='Item list calculator'!I808 -> 7.788 | C58: SERVING
A59: CINNAMON INING | B59: ='Item list calculator'!I817 -> 10.33 | C59: KG
A60: NASI GOREGN PASTE | B60: ='Item list calculator'!I830 -> 10.5075 | C60: KG
A61: BAGEL BLUEBERRY | B61: ='Item list calculator'!I845 -> 2.2885683 | C61: PIECE

Sheet Item list calculator
A1: SCRAMBLED EGG | G1: PORTIONS PER RECIPE | I1: 1
A2: NO | B2: INGREDIENT | C2: QUANTITY | D2: UOM | E2: UNIT PRICE | F2: TOTAL | G2: YIELD LOSS (%) | H2: YIELD LOSS VALUE | I2: GRAND TOTAL
A4: 1 | B4: EGG | C4: 2 | D4: PCS | E4: ='Master Price list'!G207 -> 0.5 | F4: =E4*C4 -> 1 | G4: 0 | H4: =F4/100*G4 -> 0 | I4: =H4+F4 -> 1
A5: 2 | B5: WHIPPING CREAM | C5: 0.09 | D5: KG | E5: ='Master Price list'!G36 -> 22 | F5: =E5*C5 -> 1.98 | G5: 0 | H5: =F5/100*G5 -> 0 | I5: =H5+F5 -> 1.98
A6: 3 | B6: SALT | C6: 0.001 | D6: KG | E6: ='Master Price list'!G62 -> 4.4444444 | F6: =E6*C6 -> 0.0044444444 | G6: 0 | H6: =F6/100*G6 -> 0 | I6: =H6+F6 -> 0.0044444444
A7: 4 | B7: BLACK PEPPER, FINE COURSE | C7: 0.001 | D7: KG | E7: ='Master Price list'!G41 -> 56 | F7: =E7*C7 -> 0.056 | G7: 0 | H7: =F7/100*G7 -> 0 | I7: =H7+F7 -> 0.056
A8: 5 | B8: BUTTER. SALTED | C8: 0.015 | D8: KG | E8: ='Master Price list'!G21 -> 39.2 | F8: =E8*C8 -> 0.588 | G8: 0 | H8: =F8/100*G8 -> 0 | I8: =H8+F8 -> 0.588
G9: TOTAL | I9: =SUM(I4:I8) -> 3.6284444
G10: PRICE PER UNIT | I10: =I9/I1 -> 3.6284444
A13: SAUTEED MUSHROOMS | G13: PORTIONS PER RECIPE | I13: 1
A14: NO | B14: INGREDIENT | C14: QUANTITY | D14: UOM | E14: UNIT PRICE | F14: TOTAL | G14: YIELD LOSS (%) | H14: YIELD LOSS VALUE | I14: GRAND TOTAL
A16: 1 | B16: MUSHROOMS | C16: 0.12 | D16: KG | E16: ='Master Price list'!G182 -> 23.8 | F16: =E16*C16 -> 2.856 | G16: 0 | H16: =F16/100*G16 -> 0 | I16: =H16+F16 -> 2.856
A17: 2 | B17: BUTTER. SALTED | C17: 0.015 | D17: KG | E17: ='Master Price list'!G21 -> 39.2 | F17: =E17*C17 -> 0.588 | G17: 0 | H17: =F17/100*G17 -> 0 | I17: =H17+F17 -> 0.588
A18: 3 | B18: CODIANDER | C18: 0.002 | D18: KG | E18: ='Master Price list'!G174 -> 15 | F18: =E18*C18 -> 0.03 | G18: 20 | H18: =F18/100*G18 -> 0.006 | I18: =H18+F18 -> 0.036
A19: 4 | B19: PARSLEY | C19: 0.002 | D19: KG | E19: ='Master Price list'!G191 -> 15 | F19: =E19*C19 -> 0.03 | G19: 20 | H19: =F19/100*G19 -> 0.006 | I19: =H19+F19 -> 0.036
A20: 5 | B20: SALT | C20: 0.001 | D20: KG | E20: ='Master Price list'!G62 -> 4.4444444 | F20: =E20*C20 -> 0.0044444444 | G20: 0 | H20: =F20/100*G20 -> 0 | I20: =H20+F20 -> 0.0044444444
A21: 6 | B21: OLIVE OIL | C21: 0.015 | D21: KG | E21: ='Master Price list'!G80 -> 42 | F21: =E21*C21 -> 0.63 | G21: 0 | H21: =F21/100*G21 -> 0 | I21: =H21+F21 -> 0.63
G22: TOTAL | I22: =SUM(I16:I21) -> 4.1504444
G23: PRICE PER UNIT (SERVING) | I23: =I22/I13 -> 4.1504444
A26: FRUIT SALAD | G26: PORTIONS PER RECIPE | I26: 1
A27: NO | B27: INGREDIENT | C27: QUANTITY | D27: UOM | E27: UNIT PRICE | F27: TOTAL | G27: YIELD LOSS (%) | H27: YIELD LOSS VALUE | I27: GRAND TOTAL
A29: 1 | B29: BANANA | C29: 0.05 | D29: KG | E29: ='Master Price list'!G158 -> 5.3 | F29: =E29*C29 -> 0.265 | G29: 0 | H29: =F29/100*G29 -> 0 | I29: =H29+F29 -> 0.265
A30: 2 | B30: PINEAPPLE | C30: 0.05 | D30: KG | E30: ='Master Price list'!G220 -> 6.3 | F30: =E30*C30 -> 0.315 | G30: 10 | H30: =F30/100*G30 -> 0.0315 | I30: =H30+F30 -> 0.3465
A31: 3 | B31: MELON | C31: 0.05 | D31: KG | E31: ='Master Price list'!G216 -> 7 | F31: =E31*C31 -> 0.35 | G31: 10 | H31: =F31/100*G31 -> 0.035 | I31: =H31+F31 -> 0.385
A32: 4 | B32: WATERMELON | C32: 0.05 | D32: KG | E32: ='Master Price list'!G221 -> 3.8 | F32: =E32*C32 -> 0.19 | G32: 10 | H32: =F32/100*G32 -> 0.019 | I32: =H32+F32 -> 0.209
A33: 5 | B33: LEMON JUICE | C33: 0.008 | D33: KG | E33: ='Master Price list'!G222 -> 37.8 | F33: =E33*C33 -> 0.3024 | G33: 0 | H33: =F33/100*G33 -> 0 | I33: =H33+F33 -> 0.3024
A34: 6 | B34: BASIL LEAF | C34: 0.001 | D34: KG | E34: ='Master Price list'!G160 -> 86 | F34: =E34*C34 -> 0.086 | G34: 0 | H34: =F34/100*G34 -> 0 | I34: =H34+F34 -> 0.086
A35: 7 | B35: MINT LEAF | C35: 0.001 | D35: KG | E35: ='Master Price list'!G187 -> 8.8 | F35: =E35*C35 -> 0.0088 | G35: 0 | H35: =F35/100*G35 -> 0 | I35: =H35+F35 -> 0.0088
A36: 8 | B36: YOGURT | C36: 0.03 | D36: KG | E36: ='Master Price list'!G35 -> 29 | F36: =E36*C36 -> 0.87 | G36: 0 | H36: =F36/100*G36 -> 0 | I36: =H36+F36 -> 0.87
A37: 9 | B37: HONEY | C37: 0.03 | D37: KG | E37: ='Master Price list'!G146 -> 15.8 | F37: =E37*C37 -> 0.474 | G37: 0 | H37: =F37/100*G37 -> 0 | I37: =H37+F37 -> 0.474
G38: TOTAL | I38: =SUM(I29:I37) -> 2.9467
G39: PRICE PER UNIT (SERVING) | I39: =I38/I26 -> 2.9467
A43: BANANA PANCAKE | G43: PORTIONS PER RECIPE | I43: 2
A44: NO | B44: INGREDIENT | C44: QUANTITY | D44: UOM | E44: UNIT PRICE | F44: TOTAL | G44: YIELD LOSS (%) | H44: YIELD LOSS VALUE | I44: GRAND TOTAL
A46: 1 | B46: BANANA | C46: 0.1 | D46: KG | E46: ='Master Price list'!G158 -> 5.3 | F46: =E46*C46 -> 0.53 | G46: 20 | H46: =F46/100*G46 -> 0.106 | I46: =H46+F46 -> 0.636
A47: 2 | B47: MILK | C47: 0.16 | D47: KG | E47: ='Master Price list'!G27 -> 9 | F47: =E47*C47 -> 1.44 | G47: 0 | H47: =F47/100*G47 -> 0 | I47: =H47+F47 -> 1.44
A48: 3 | B48: EGG | C48: 1 | D48: PCS | E48: ='Master Price list'!G207 -> 0.5 | F48: =E48*C48 -> 0.5 | G48: 0 | H48: =F48/100*G48 -> 0 | I48: =H48+F48 -> 0.5
A49: 4 | B49: VANILLA EXTRACT | C49: 0.01 | D49: KG | E49: ='Master Price list'!G121 -> 39.6 | F49: =E49*C49 -> 0.396 | G49: 0 | H49: =F49/100*G49 -> 0 | I49: =H49+F49 -> 0.396
A50: 5 | B50: BUTTER, MELTED | C50: 0.15 | D50: KG | E50: ='Master Price list'!G21 -> 39.2 | F50: =E50*C50 -> 5.88 | G50: 0 | H50: =F50/100*G50 -> 0 | I50: =H50+F50 -> 5.88
A51: 6 | B51: SUGAR, WHITE | C51: 0.02 | D51: KG | E51: ='Master Price list'!G120 -> 4.6 | F51: =E51*C51 -> 0.092 | G51: 0 | H51: =F51/100*G51 -> 0 | I51: =H51+F51 -> 0.092
A52: 7 | B52: LOW PROTEIN FLOUR | C52: 0.13 | D52: KG | E52: ='Master Price list'!G116 -> 4.51 | F52: =E52*C52 -> 0.5863 | G52: 0 | H52: =F52/100*G52 -> 0 | I52: =H52+F52 -> 0.5863
A53: 8 | B53: BAKING SODA | C53: 0.0025 | D53: KG | E53: ='Master Price list'!G106 -> 5.8 | F53: =E53*C53 -> 0.0145 | G53: 0 | H53: =F53/100*G53 -> 0 | I53: =H53+F53 -> 0.0145
A54: 9 | B54: BAKING POWDER | C54: 0.005 | D54: KG | E54: ='Master Price list'!G105 -> 21.766667 | F54: =E54*C54 -> 0.10883333 | G54: 0 | H54: =F54/100*G54 -> 0 | I54: =H54+F54 -> 0.10883333
A55: 10 | B55: NUTMEG POWDER | C55: 0.0025 | D55: KG | E55: ='Master Price list'!G58 -> 62 | F55: =E55*C55 -> 0.155 | G55: 0 | H55: =F55/100*G55 -> 0 | I55: =H55+F55 -> 0.155
A56: 11 | B56: CINNAMON POWDER | C56: 0.0001 | D56: KG | E56: ='Master Price list'!G47 -> 35 | F56: =E56*C56 -> 0.0035 | G56: 0 | H56: =F56/100*G56 -> 0 | I56: =H56+F56 -> 0.0035
A57: 12 | B57: EGG WHITE | C57: 2 | D57: PCS | E57: ='Master Price list'!G207 -> 0.5 | F57: =E57*C57 -> 1 | G57: 0 | H57: =F57/100*G57 -> 0 | I57: =H57+F57 -> 1
G58: TOTAL | I58: =SUM(I46:I57) -> 10.812133
G59: PRICE PER UNIT (SERVING) | I59: =I58/I43 -> 5.4060667
A62: FRENCH TOAST BATTER | G62: PORTIONS PER RECIPE | I62: 5
A63: NO | B63: INGREDIENT | C63: QUANTITY | D63: UOM | E63: UNIT PRICE | F63: TOTAL | G63: YIELD LOSS (%) | H63: YIELD LOSS VALUE | I63: GRAND TOTAL
A65: 1 | B65: MILK | C65: 0.11 | D65: KG | E65: ='Master Price list'!G27 -> 9 | F65: =E65*C65 -> 0.99 | G65: 0 | H65: =F65/100*G65 -> 0 | I65: =H65+F65 -> 0.99
A66: 2 | B66: EGG | C66: 3 | D66: PCS | E66: ='Master Price list'!G207 -> 0.5 | F66: =E66*C66 -> 1.5 | G66: 0 | H66: =F66/100*G66 -> 0 | I66: =H66+F66 -> 1.5
A67: 3 | B67: ICING SUGAR | C67: 0.06 | D67: KG | E67: ='Master Price list'!G115 -> 7.2 | F67: =E67*C67 -> 0.432 | G67: 0 | H67: =F67/100*G67 -> 0 | I67: =H67+F67 -> 0.432
A68: 4 | B68: VANILLA EXTACT | C68: 0.005 | D68: KG | E68: ='Master Price list'!G121 -> 39.6 | F68: =E68*C68 -> 0.198 | G68: 0 | H68: =F68/100*G68 -> 0 | I68: =H68+F68 -> 0.198
A69: 5 | B69: LEMON ZEST | C69: 0.005 | D69: KG | E69: 0 | F69: =E69*C69 -> 0 | G69: 0 | H69: =F69/100*G69 -> 0 | I69: =H69+F69 -> 0
A70: 6 | B70: CINNAMON POWDER | C70: 0.0025 | D70: KG | E70: ='Master Price list'!G47 -> 35 | F70: =E70*C70 -> 0.0875 | G70: 0 | H70: =F70/100*G70 -> 0 | I70: =H70+F70 -> 0.0875
A71: 7 | B71: RAS EL HANOUT | C71: 0.0025 | D71: KG | E71: ='Master Price list'!G61 -> 75 | F71: =E71*C71 -> 0.1875 | G71: 0 | H71: =F71/100*G71 -> 0 | I71: =H71+F71 -> 0.1875
A72: 8 | B72: SALT | C72: 0.0001 | D72: KG | E72: ='Master Price list'!G62 -> 4.4444444 | F72: =E72*C72 -> 0.00044444444 | G72: 0 | H72: =F72/100*G72 -> 0 | I72: =H72+F72 -> 0.00044444444
G73: TOTAL | I73: =SUM(I65:I72) -> 3.3954444
G74: PRICE PER UNIT (SERVING) | I74: =I73/I62 -> 0.67908889
A77: WAFFLE BATTER | G77: PORTIONS PER RECIPE | I77: 3
A78: NO | B78: INGREDIENT | C78: QUANTITY | D78: UOM | E78: UNIT PRICE | F78: TOTAL | G78: YIELD LOSS (%) | H78: YIELD LOSS VALUE | I78: GRAND TOTAL
A80: 1 | B80: EGG | C80: 2 | D80: PCS | E80: =E66 -> 0.5 | F80: =E80*C80 -> 1 | G80: 0 | H80: =F80/100*G80 -> 0 | I80: =H80+F80 -> 1
A81: 2 | B81: LOW PROTEIN FLOUR | C81: 0.24 | D81: KG | E81: ='Master Price list'!G116 -> 4.51 | F81: =E81*C81 -> 1.0824 | G81: 0 | H81: =F81/100*G81 -> 0 | I81: =H81+F81 -> 1.0824
A82: 3 | B82: CINNAMON POWDER | C82: 0.005 | D82: KG | E82: =E70 -> 35 | F82: =E82*C82 -> 0.175 | G82: 0 | H82: =F82/100*G82 -> 0 | I82: =H82+F82 -> 0.175
A83: 4 | B83: BAKING POWDER | C83: 0.005 | D83: KG | E83: ='Master Price list'!G105 -> 21.766667 | F83: =E83*C83 -> 0.10883333 | G83: 0 | H83: =F83/100*G83 -> 0 | I83: =H83+F83 -> 0.10883333
A84: 5 | B84: ICING SUGAR | C84: 0.03 | D84: KG | E84: ='Master Price list'!G115 -> 7.2 | F84: =E84*C84 -> 0.216 | G84: 0 | H84: =F84/100*G84 -> 0 | I84: =H84+F84 -> 0.216
A85: 6 | B85: MILK | C85: 0.36 | D85: KG | E85: =E65 -> 9 | F85: =E85*C85 -> 3.24 | G85: 0 | H85: =F85/100*G85 -> 0 | I85: =H85+F85 -> 3.24
A86: 7 | B86: ORANGE ZEST | C86: 0.015 | D86: KG | E86: 0 | F86: =E86*C86 -> 0 | G86: 0 | H86: =F86/100*G86 -> 0 | I86: =H86+F86 -> 0
A87: 8 | B87: BUTTER, MELTED | C87: 0.03 | D87: KG | E87: ='Master Price list'!G21 -> 39.2 | F87: =E87*C87 -> 1.176 | G87: 0 | H87: =F87/100*G87 -> 0 | I87: =H87+F87 -> 1.176
G88: TOTAL | I88: =SUM(I80:I87) -> 6.9982333
G89: PRICE PER UNIT (SERVING) | I89: =I88/I77 -> 2.3327444
A92: CREPE BATTER | G92: PORTIONS PER RECIPE | I92: 3
A93: NO | B93: INGREDIENT | C93: QUANTITY | D93: UOM | E93: UNIT PRICE | F93: TOTAL | G93: YIELD LOSS (%) | H93: YIELD LOSS VALUE | I93: GRAND TOTAL
A95: 1 | B95: EGG YOLK | C95: 3 | D95: PCS | E95: =E80 -> 0.5 | F95: =E95*C95 -> 1.5 | G95: 0 | H95: =F95/100*G95 -> 0 | I95: =H95+F95 -> 1.5
A96: 2 | B96: MILK | C96: 0.25 | D96: KG | E96: =E85 -> 9 | F96: =E96*C96 -> 2.25 | G96: 0 | H96: =F96/100*G96 -> 0 | I96: =H96+F96 -> 2.25
A97: 3 | B97: BUTTER, MELTED | C97: 0.06 | D97: KG | E97: =E87 -> 39.2 | F97: =E97*C97 -> 2.352 | G97: 0 | H97: =F97/100*G97 -> 0 | I97: =H97+F97 -> 2.352
A98: 4 | B98: ALL PURPOSE FLOUR | C98: 0.075 | D98: KG | E98: ='Master Price list'!G104 -> 2.1764706 | F98: =E98*C98 -> 0.16323529 | G98: 0 | H98: =F98/100*G98 -> 0 | I98: =H98+F98 -> 0.16323529
A99: 5 | B99: VINALLA EXTRACT | C99: 0.005 | D99: KG | E99: ='Master Price list'!G121 -> 39.6 | F99: =E99*C99 -> 0.198 | G99: 0 | H99: =F99/100*G99 -> 0 | I99: =H99+F99 -> 0.198
A100: 6 | B100: SALT | C100: 0.0001 | D100: KG | E100: =E72 -> 4.4444444 | F100: =E100*C100 -> 0.00044444444 | G100: 0 | H100: =F100/100*G100 -> 0 | I100: =H100+F100 -> 0.00044444444
G101: TOTAL | I101: =SUM(I95:I100) -> 6.4636797
G102: PRICE PER UNIT (SERVING) | I102: =I101/I92 -> 2.1545599
A105: FISH & CHIPS BATTER | G105: PORTIONS PER RECIPE | I105: 5
A106: NO | B106: INGREDIENT | C106: QUANTITY | D106: UOM | E106: UNIT PRICE | F106: TOTAL | G106: YIELD LOSS (%) | H106: YIELD LOSS VALUE | I106: GRAND TOTAL
A108: 1 | B108: LOW PROTEIN FLOUR | C108: 0.18 | D108: KG | E108: =E81 -> 4.51 | F108: =E108*C108 -> 0.8118 | G108: 0 | H108: =F108/100*G108 -> 0 | I108: =H108+F108 -> 0.8118
A109: 2 | B109: BAKING POWDER | C109: 0.01 | D109: KG | E109: =E83 -> 21.766667 | F109: =E109*C109 -> 0.21766667 | G109: 0 | H109: =F109/100*G109 -> 0 | I109: =H109+F109 -> 0.21766667
A110: 3 | B110: BEER | C110: 1 | D110: BTL | E110: 8.29 | F110: =E110*C110 -> 8.29 | G110: 0 | H110: =F110/100*G110 -> 0 | I110: =H110+F110 -> 8.29
A111: 4 | B111: LEMON PEPPER SEASONING | C111: 0.01 | D111: KG | E111: ='Master Price list'!G57 -> 70 | F111: =E111*C111 -> 0.7 | G111: 0 | H111: =F111/100*G111 -> 0 | I111: =H111+F111 -> 0.7
A112: 5 | B112: BLACK PAPPER, FINE COURSE | C112: 0.005 | D112: KG | E112: ='Master Price list'!G41 -> 56 | F112: =E112*C112 -> 0.28 | G112: 0 | H112: =F112/100*G112 -> 0 | I112: =H112+F112 -> 0.28
A113: 6 | B113: SALT | C113: 0.005 | D113: KG | E113: =E100 -> 4.4444444 | F113: =E113*C113 -> 0.022222222 | G113: 0 | H113: =F113/100*G113 -> 0 | I113: =H113+F113 -> 0.022222222
G114: TOTAL | I114: =SUM(I108:I113) -> 10.321689
G115: PRICE PER UNIT (SERVING) | I115: =I114/I105 -> 2.0643378
A118: TOMATO BAGEL | G118: PORTIONS PER RECIPE | I118: 17
A119: NO | B119: INGREDIENT | C119: QUANTITY | D119: UOM | E119: UNIT PRICE | F119: TOTAL | G119: YIELD LOSS (%) | H119: YIELD LOSS VALUE | I119: GRAND TOTAL
A121: 1 | B121: HIGH PROTEIN FLOUR | C121: 1 | D121: KG | E121: ='Master Price list'!G114 -> 4.5 | F121: =E121*C121 -> 4.5 | G121: 0 | H121: =F121/100*G121 -> 0 | I121: =H121+F121 -> 4.5
A122: 2 | B122: SUGAR, WHITE | C122: 0.03 | D122: KG | E122: ='Master Price list'!G120 -> 4.6 | F122: =E122*C122 -> 0.138 | G122: 0 | H122: =F122/100*G122 -> 0 | I122: =H122+F122 -> 0.138
A123: 3 | B123: YEAST | C123: 0.01 | D123: KG | E123: ='Master Price list'!G122 -> 7.4 | F123: =E123*C123 -> 0.074 | G123: 0 | H123: =F123/100*G123 -> 0 | I123: =H123+F123 -> 0.074
A124: 4 | B124: SALT | C124: 0.015 | D124: KG | E124: =E113 -> 4.4444444 | F124: =E124*C124 -> 0.066666667 | G124: 0 | H124: =F124/100*G124 -> 0 | I124: =H124+F124 -> 0.066666667
A125: 5 | B125: WATER | C125: 0.3 | D125: KG | E125: 0 | F125: =E125*C125 -> 0 | G125: 0 | H125: =F125/100*G125 -> 0 | I125: =H125+F125 -> 0
A126: 6 | B126: TOMATO PUREE, PREGO | C126: 0.4 | D126: KG | E126: ='Master Price list'!G100 -> 19.583333 | F126: =E126*C126 -> 7.8333333 | G126: 0 | H126: =F126/100*G126 -> 0 | I126: =H126+F126 -> 7.8333333
...

Sheet Menu Item list
A1: ITEM NAME | B1: ITEM PRICE
A2: BIG BREAKFAST W/BACON | B2: ='Menu item calculator'!F12 -> 15.227749
A3: BIG BREAKFAST W/CHICKEN | B3: ='Menu item calculator'!F26 -> 15.227749
A4: BIG BREAKFAST W/PORK | B4: ='Menu item calculator'!F40 -> 15.227749
A5: BIG BREAKFAST W/BEEF | B5: ='Menu item calculator'!F54 -> 15.619249 | G5: 2 | H5: 5 items | I5: 0.7 | J5: =(80*I5)*G5 -> 112
A6: ALL DAY W/BACON | B6: ='Menu item calculator'!F68 -> 12.302455 | G6: 6 | H6: 5 items | I6: 0.2 | J6: =(80*I6)*G6 -> 96
A7: ALL DAY W/CHICKEN | B7: ='Menu item calculator'!F82 -> 12.302455 | G7: 20 | H7: 3 items | I7: 0.1 | J7: =(80*I7)*G7 -> 160
A8: ALL DAY W/PORK | B8: ='Menu item calculator'!F96 -> 12.302455 | I8: =SUM(I5:I7) -> 1
A9: ALL DAY W/BEEF | B9: ='Menu item calculator'!F110 -> 12.693955 | J9: =SUM(J5:J7) -> 368 | K9: goal is RM350
A10: CREPPES W/CARAMELIZED BANANA | B10: ='Menu item calculator'!F121 -> 3.7039399
A11: CREPPES W/LEMON & SUGAR | B11: ='Menu item calculator'!F133 -> 2.8514399
A12: CREPPES W/NUTELLA | B12: ='Menu item calculator'!F144 -> 4.2102046
A13: OMELETTE PLAIN | B13: ='Menu item calculator'!F156 -> 6.0332661
A14: OMELETTE W/SALMON 50GM | B14: ='Menu item calculator'!F169 -> 12.433266
A15: OMELETTE W/CHEESE & MUSHROOM | B15: ='Menu item calculator'!F183 -> 8.7232661
A16: EGGS BENEDICT W/BACON | B16: ='Menu item calculator'!F197 -> 10.626496
A17: EGGS MARLBOROUGH W/SALMON | B17: ='Menu item calculator'!F211 -> 13.598996
A18: TOAST W/BUTTER & JAM | B18: ='Menu item calculator'!F220 -> 0.28246867
A19: SWEET CORN PANCAKES W/BACON | B19: RECIPE MISSING
A20: MUESLI W/HONEY,YOGHURT,FRUIT | B20: ='Menu item calculator'!F245 -> 4.7135225
A21: PANCAKE BANANA | B21: ='Menu item calculator'!F255 -> 6.893627
A22: PORRIDGE W/HONEY & BANANA | B22: ='Menu item calculator'!F268 -> 3.5439749
A23: ASPARAGUS W/BACON | B23: ='Menu item calculator'!F279 -> 11.724653
A24: SCRAMBLED EGGS W/SALMON 50G | B24: ='Menu item calculator'!F291 -> 12.345573
A25: FRESH FRUIT SALAD W/YOGHURT | B25: ='Menu item calculator'!F298 -> 2.9467
A26: FRENCH TOAST W/BERRY COMPOTE | B26: ='Menu item calculator'!F309 -> 5.3527634
A27: FRENCH TOAST W/BANANA BACON | B27: ='Menu item calculator'!F320 -> 5.8647389
A28: FRENCH TOAST W/BACON & MAPLE | B28: ='Menu item calculator'!F331 -> 5.7092389
A29: FRENCH TOAST W/PEARS & BACON | B29: ='Menu item calculator'!F345 -> 7.9863889
A30: TOMATO W/ MUSHROOM ON TOAST | B30: ='Menu item calculator'!F360 -> 6.7422917
A31: BACON & EGG PIE | B31: ='Menu item calculator'!F378 -> 10.595723
A32: SCRAMBLED EGGS FETA W/SPINACH | B32: ='Menu item calculator'!F389 -> 6.4831278
A33: AVOCADO BACON ON TOAST | B33: ='Menu item calculator'!F402 -> 3.4825109
A34: AVOCADO HALOUMI CHEES ON TOAST | B34: ='Menu item calculator'!F415 -> 7.4961841
A35: AVOCADO ON TOAST W/ SALMON | B35: ='Menu item calculator'!F430 -> 8.1066261
A36: NASI GORENG | B36: ='Menu item calculator'!F447 -> 5.6296128
A37: OPEN BACON ROCKET SANDWICH | B37: ='Menu item calculator'!F459 -> 6.5508333
A38: OPEN BACON LETTUCE SANDWICH | B38: ='Menu item calculator'!F471 -> 6.0708333
A39: OPEN CHICKEN SANDWICH | B39: ='Menu item calculator'!F483 -> 3.6417156
A40: THAI CHICKEN SATAY | B40: ='Menu item calculator'!F494 -> 4.7674818
A41: VIETNAMESE BEEF NOODLE | B41: ='Menu item calculator'!F510 -> 12.452476
A42: DOUBLE SALMON FISH CAKE | B42: ='Menu item calculator'!F522 -> 7.9840294
A43: GRILLED CHICKEN W/TOMATOES | B43: ='Menu item calculator'!F536 -> 6.2855289
A44: FISH & CHIPS | B44: ='Menu item calculator'!F550 -> 14.40425
A45: FRENCH FRIES | B45: ='Menu item calculator'!F557 -> 2.288
A46: WEDGES | B46: ='Menu item calculator'!F565 -> 3.7911271
A47: KUMERA WEDGES | B47: ='Menu item calculator'!F573 -> 1.0111271
A48: CHICKEN KEBAB | B48: ='Menu item calculator'!F585 -> 8.6910762
A49: BEEF KEBAB | B49: ='Menu item calculator'!F597 -> 25.822882
A50: LAMB KEBAB | B50: ='Menu item calculator'!F609 -> 20.535478
A51: WHAKATIKI CHICKEN | B51: ='Menu item calculator'!F624 -> 6.8691815
A52: SWEET PAPRIKA CHICKEN | B52: ='Menu item calculator'!F634 -> 4.7293686
A53: RED SOUP | B53: ='Menu item calculator'!F643 -> 2.4317299
A54: PUMPKIN SOUP | B54: ='Menu item calculator'!F653 -> 1.9642361
A55: ---- EXTRAS ----
A56: SALMON 50GM | B56: 6.4
A57: SALMON 100GM | B57: 12.8
A58: ROCKET
A59: SPINACH
A60: HASHBROWN
A61: BAKED BEANS
A62: MUSHROOMS
A63: TOMATO
A64: BACK BACON
A65: STREAKY BACON
A66: CHEESE
A67: SAUSAGE - CHICKEN
A68: SAUSAGE - BEEF
A69: SAUSAGE - PORK
... A74: ---- BURGER ----
A75: LAMB BURGER | B75: ='Menu item calculator'!F670 -> 15.236594
A76: BEEF BURGER | B76: ='Menu item calculator'!F687 -> 12.068348
A77: ---- PANINI ----
A78: TOASTED SANDWICH W/MEATBALL | B78: ='Menu item calculator'!F702 -> 10.53688
A79: TOASTED SANDWICH W/CHEESE | B79: ='Menu item calculator'!F717 -> 6.6146118
A80: TOASTED SANDWICH W/BACON | B80: ='Menu item calculator'!F732 -> 9.314629
A81: ---- BAGEL ----
A82: BAGEL W/CHORIZO | B82: ='Menu item calculator'!F747 -> 8.7762664
A83: BAGEL W/FRIED EGG & BACON | B83: ='Menu item calculator'!F759 -> 8.4688572
A84: BAGEL W/BACON TOMATO PESTO | B84: ='Menu item calculator'!F771 -> 6.7752239
A85: BAGEL W/SALMON & CAPERS | B85: ='Menu item calculator'!F785 -> 11.938032
A86: BAGEL W/BLUEBERRY | B86: ='Menu item calculator'!F796 -> 7.8541174
A87: BAGEL W/CREAM CHEESE | B87: ='Menu item calculator'!F804 -> 3.2159121
A88: ---- CROISSANT ----
A89: CROISSANT W/BUTTER & JAM | B89: ='Menu item calculator'!F813 -> 1.5932233
A90: CROISSANT SM EGGS W/CHICKEN | B90: ='Menu item calculator'!F823 -> 8.2742778
A91: CROISSANT SM EGGS W/BEEF | B91: ='Menu item calculator'!F833 -> 8.6657778
A92: CROISSANT SM EGGS W/PORK | B92: ='Menu item calculator'!F843 -> 8.2742778
A93: CROISSANT SM EGGS W/BACON | B93: ='Menu item calculator'!F853 -> 8.2742778
A94: ---- SALAD ----
A95: BURMESE SHREDDED CHICKEN | B95: ='Menu item calculator'!F866 -> 2.0725221
A96: CHICKPEAS FETA W/ CORRIANDER | B96: ='Menu item calculator'!F875 -> 2.9904747
A97: ROAST VEGE SALAD | B97: ='Menu item calculator'!F885 -> 4.2914643
A98: THAI BEEF SALAD | B98: ='Menu item calculator'!F902 -> 11.494405
A99: MIX SALAD W/COUS COUS | B99: ='Menu item calculator'!F914 -> 7.0877778
A100: BEETROOT & NUTS SALAD | B100: ='Item list'!B32 -> 3.5986875
A101: GREEK SALAD | B101: ='Menu item calculator'!F928 -> 3.4122727
A102: BUFFALO MOZZARELLA | B102: ='Menu item calculator'!F940 -> 17.072
A103: WAIMAKIRIRI SALAD | B103: ='Menu item calculator'!F953 -> 10.669279
A104: COROMANDEL CHICKEN | B104: ='Menu item calculator'!F967 -> 6.6425
...

Sheet Menu item calculator
A1: BIG BREAKFAST W/BACON
A2: NO | B2: INGREDIENT | C2: QUANTITY | D2: UOM | E2: UNIT PRICE | F2: TOTAL
A4: 1 | B4: FRENCH VILLAGE | C4: 1 | D4: SERVING | E4: ='Master Price list'!G69/10 -> 0.066508333 | F4: =E4*C4 -> 0.066508333
A5: 2 | B5: BUTTER, SALTED | C5: 0.01 | D5: KG | E5: ='Master Price list'!G21 -> 39.2 | F5: =E5*C5 -> 0.392
A6: 3 | B6: HOUSE SALAD | C6: 1 | D6: SERVING | E6: ='Item list'!B31 -> 1.7691118 | F6: =E6*C6 -> 1.7691118
A7: 4 | B7: CHERRY TOMATO | C7: 0.002 | D7: KG | E7: ='Master Price list'!G169 -> 11.5 | F7: =E7*C7 -> 0.023
A8: 5 | B8: SAUTEED MUSHROOM | C8: 1 | D8: SERVING | E8: ='Item list calculator'!I23 -> 4.1504444 | F8: =E8*C8 -> 4.1504444
A9: 6 | B9: SCRAMBLED EGG | C9: 1 | D9: SERVING | E9: ='Item list'!B2 -> 3.6284444 | F9: =E9*C9 -> 3.6284444
A10: 7 | B10: HASHBROWN | C10: 1 | D10: SERVING | E10: ='Item list'!B30 -> 1.7707397 | F10: =E10*C10 -> 1.7707397
A11: 8 | B11: BACK BACON | C11: 0.075 | D11: KG | E11: ='Master Price list'!G7 -> 45.7 | F11: =E11*C11 -> 3.4275
D12: TOTAL | F12: =SUM(F4:F11) -> 15.227749
A15: BIG BREAKFAST W/CHICKEN
A16: NO | B16: INGREDIENT | C16: QUANTITY | D16: UOM | E16: UNIT PRICE | F16: TOTAL
A18: 1 | B18: FRENCH VILLAGE | C18: 1 | D18: SERVING | E18: ='Master Price list'!G69/10 -> 0.066508333 | F18: =E18*C18 -> 0.066508333
A19: 2 | B19: BUTTER, SALTED | C19: 0.01 | D19: KG | E19: ='Master Price list'!G21 -> 39.2 | F19: =E19*C19 -> 0.392
A20: 3 | B20: HOUSE SALAD | C20: 1 | D20: SERVING | E20: ='Item list'!B31 -> 1.7691118 | F20: =E20*C20 -> 1.7691118
A21: 4 | B21: CHERRY TOMATO | C21: 0.002 | D21: KG | E21: =E7 -> 11.5 | F21: =E21*C21 -> 0.023
A22: 5 | B22: SAUTEED MUSHROOM | C22: 1 | D22: SERVING | E22: =E8 -> 4.1504444 | F22: =E22*C22 -> 4.1504444
A23: 6 | B23: SCRAMBLED EGG | C23: 1 | D23: SERVING | E23: =E9 -> 3.6284444 | F23: =E23*C23 -> 3.6284444
A24: 7 | B24: HASHBROWN | C24: 1 | D24: SERVING | E24: =E10 -> 1.7707397 | F24: =E24*C24 -> 1.7707397
A25: 8 | B25: CHICKEN SAUSAGE | C25: 0.075 | D25: KG | E25: ='Master Price list'!G14 -> 45.7 | F25: =E25*C25 -> 3.4275
D26: TOTAL | F26: =SUM(F18:F25) -> 15.227749
A29: BIG BREAKFAST W/PORK
A30: NO | B30: INGREDIENT | C30: QUANTITY | D30: UOM | E30: UNIT PRICE | F30: TOTAL
A32: 1 | B32: FRENCH VILLAGE | C32: 1 | D32: SERVING | E32: =E18 -> 0.066508333 | F32: =E32*C32 -> 0.066508333
A33: 2 | B33: BUTTER, SALTED | C33: 0.01 | D33: KG | E33: =E19 -> 39.2 | F33: =E33*C33 -> 0.392
A34: 3 | B34: HOUSE SALAD | C34: 1 | D34: SERVING | E34: =E20 -> 1.7691118 | F34: =E34*C34 -> 1.7691118
A35: 4 | B35: CHERRY TOMATO | C35: 0.002 | D35: KG | E35: =E21 -> 11.5 | F35: =E35*C35 -> 0.023
A36: 5 | B36: SAUTEED MUSHROOM | C36: 1 | D36: SERVING | E36: =E22 -> 4.1504444 | F36: =E36*C36 -> 4.1504444
A37: 6 | B37: SCRAMBLED EGG | C37: 1 | D37: SERVING | E37: =E23 -> 3.6284444 | F37: =E37*C37 -> 3.6284444
A38: 7 | B38: HASHBROWN | C38: 1 | D38: SERVING | E38: =E24 -> 1.7707397 | F38: =E38*C38 -> 1.7707397
A39: 8 | B39: PORK SAUSAGE | C39: 0.075 | D39: KG | E39: ='Master Price list'!G11 -> 45.7 | F39: =E39*C39 -> 3.4275
D40: TOTAL | F40: =SUM(F32:F39) -> 15.227749
A43: BIG BREAKFAST W/BEEF
A44: NO | B44: INGREDIENT | C44: QUANTITY | D44: UOM | E44: UNIT PRICE | F44: TOTAL
A46: 1 | B46: FRENCH VILLAGE | C46: 1 | D46: SERVING | E46: =E32 -> 0.066508333 | F46: =E46*C46 -> 0.066508333
A47: 2 | B47: BUTTER, SALTED | C47: 0.01 | D47: KG | E47: =E33 -> 39.2 | F47: =E47*C47 -> 0.392
A48: 3 | B48: HOUSE SALAD | C48: 1 | D48: SERVING | E48: =E34 -> 1.7691118 | F48: =E48*C48 -> 1.7691118
A49: 4 | B49: CHERRY TOMATO | C49: 0.002 | D49: KG | E49: =E35 -> 11.5 | F49: =E49*C49 -> 0.023
A50: 5 | B50: SAUTEED MUSHROOM | C50: 1 | D50: SERVING | E50: =E36 -> 4.1504444 | F50: =E50*C50 -> 4.1504444
A51: 6 | B51: SCRAMBLED EGG | C51: 1 | D51: SERVING | E51: =E37 -> 3.6284444 | F51: =E51*C51 -> 3.6284444
A52: 7 | B52: HASHBROWN | C52: 1 | D52: SERVING | E52: =E38 -> 1.7707397 | F52: =E52*C52 -> 1.7707397
A53: 8 | B53: BEEF SAUSAGE | C53: 0.075 | D53: KG | E53: ='Master Price list'!G9 -> 50.92 | F53: =E53*C53 -> 3.819
D54: TOTAL | F54: =SUM(F46:F53) -> 15.619249
A57: ALL DAY W/BACON
A58: NO | B58: INGREDIENT | C58: QUANTITY | D58: UOM | E58: UNIT PRICE | F58: TOTAL
A60: 1 | B60: FRENCH VILLAGE | C60: 1 | D60: SERVING | E60: =E46 -> 0.066508333 | F60: =E60*C60 -> 0.066508333
A61: 2 | B61: BUTTER, SALTED | C61: 0.01 | D61: KG | E61: =E47 -> 39.2 | F61: =E61*C61 -> 0.392
A62: 3 | B62: HOUSE SALAD | C62: 1 | D62: SERVING | E62: =E48 -> 1.7691118 | F62: =E62*C62 -> 1.7691118
A63: 4 | B63: CHERRY TOMATO | C63: 0.002 | D63: KG | E63: =E49 -> 11.5 | F63: =E63*C63 -> 0.023
A64: 5 | B64: CHERRY TOMATO | C64: 0.002 | D64: KG | E64: =E63 -> 11.5 | F64: =E64*C64 -> 0.023
A65: 6 | B65: SCRAMBLED EGG | C65: 1 | D65: SERVING | E65: =E51 -> 3.6284444 | F65: =E65*C65 -> 3.6284444
A66: 7 | B66: BAKED BEANS | C66: 0.15 | D66: SERVING | E66: ='Item list'!B56 -> 19.81927 | F66: =E66*C66 -> 2.9728905
A67: 8 | B67: BACK BACON | C67: 0.075 | D67: KG | E67: =E11 -> 45.7 | F67: =E67*C67 -> 3.4275
D68: TOTAL | F68: =SUM(F60:F67) -> 12.302455
A71: ALL DAY W/CHICKEN
A72: NO | B72: INGREDIENT | C72: QUANTITY | D72: UOM | E72: UNIT PRICE | F72: TOTAL
A74: 1 | B74: FRENCH VILLAGE | C74: 1 | D74: SERVING | E74: =E60 -> 0.066508333 | F74: =E74*C74 -> 0.066508333
A75: 2 | B75: BUTTER, SALTED | C75: 0.01 | D75: KG | E75: =E61 -> 39.2 | F75: =E75*C75 -> 0.392
A76: 3 | B76: HOUSE SALAD | C76: 1 | D76: SERVING | E76: =E62 -> 1.7691118 | F76: =E76*C76 -> 1.7691118
A77: 4 | B77: CHERRY TOMATO | C77: 0.002 | D77: KG | E77: =E63 -> 11.5 | F77: =E77*C77 -> 0.023
A78: 5 | B78: CHERRY TOMATO | C78: 0.002 | D78: KG | E78: =E77 -> 11.5 | F78: =E78*C78 -> 0.023
A79: 6 | B79: SCRAMBLED EGG | C79: 1 | D79: SERVING | E79: =E65 -> 3.6284444 | F79: =E79*C79 -> 3.6284444
A80: 7 | B80: BAKED BEANS | C80: 0.15 | D80: SERVING | E80: ='Item list'!B56 -> 19.81927 | F80: =E80*C80 -> 2.9728905
A81: 8 | B81: CHICKEN SAUSAGE | C81: 0.075 | D81: KG | E81: =E25 -> 45.7 | F81: =E81*C81 -> 3.4275
D82: TOTAL | F82: =SUM(F74:F81) -> 12.302455
A85: ALL DAY W/PORK
A86: NO | B86: INGREDIENT | C86: QUANTITY | D86: UOM | E86: UNIT PRICE | F86: TOTAL
A88: 1 | B88: FRENCH VILLAGE | C88: 1 | D88: SERVING | E88: =E74 -> 0.066508333 | F88: =E88*C88 -> 0.066508333
A89: 2 | B89: BUTTER, SALTED | C89: 0.01 | D89: KG | E89: =E75 -> 39.2 | F89: =E89*C89 -> 0.392
A90: 3 | B90: HOUSE SALAD | C90: 1 | D90: SERVING | E90: =E76 -> 1.7691118 | F90: =E90*C90 -> 1.7691118
A91: 4 | B91: CHERRY TOMATO | C91: 0.002 | D91: KG | E91: =E77 -> 11.5 | F91: =E91*C91 -> 0.023
A92: 5 | B92: CHERRY TOMATO | C92: 0.002 | D92: KG | E92: =E91 -> 11.5 | F92: =E92*C92 -> 0.023
A93: 6 | B93: SCRAMBLED EGG | C93: 1 | D93: SERVING | E93: =E79 -> 3.6284444 | F93: =E93*C93 -> 3.6284444
A94: 7 | B94: BAKED BEANS | C94: 0.15 | D94: SERVING | E94: =E80 -> 19.81927 | F94: =E94*C94 -> 2.9728905
A95: 8 | B95: PORK SAUSAGE | C95: 0.075 | D95: KG | E95: =E39 -> 45.7 | F95: =E95*C95 -> 3.4275
D96: TOTAL | F96: =SUM(F88:F95) -> 12.302455
A99: ALL DAY W/BEEF
A100: NO | B100: INGREDIENT | C100: QUANTITY | D100: UOM | E100: UNIT PRICE | F100: TOTAL
A102: 1 | B102: FRENCH VILLAGE | C102: 1 | D102: SERVING | E102: =E88 -> 0.066508333 | F102: =E102*C102 -> 0.066508333
A103: 2 | B103: BUTTER, SALTED | C103: 0.01 | D103: KG | E103: =E89 -> 39.2 | F103: =E103*C103 -> 0.392
A104: 3 | B104: HOUSE SALAD | C104: 1 | D104: SERVING | E104: =E90 -> 1.7691118 | F104: =E104*C104 -> 1.7691118
A105: 4 | B105: CHERRY TOMATO | C105: 0.002 | D105: KG | E105: =E91 -> 11.5 | F105: =E105*C105 -> 0.023
A106: 5 | B106: CHERRY TOMATO | C106: 0.002 | D106: KG | E106: =E105 -> 11.5 | F106: =E106*C106 -> 0.023
A107: 6 | B107: SCRAMBLED EGG | C107: 1 | D107: SERVING | E107: =E93 -> 3.6284444 | F107: =E107*C107 -> 3.6284444
A108: 7 | B108: BAKED BEANS | C108: 0.15 | D108: SERVING | E108: =E94 -> 19.81927 | F108: =E108*C108 -> 2.9728905
A109: 8 | B109: BEEF SAUSAGE | C109: 0.075 | D109: KG | E109: =E53 -> 50.92 | F109: =E109*C109 -> 3.819
D110: TOTAL | F110: =SUM(F102:F109) -> 12.693955
A113: CREPPES W/CARAMELIZED BANANA
A114: NO | B114: INGREDIENT | C114: QUANTITY | D114: UOM | E114: UNIT PRICE | F114: TOTAL
A116: 1 | B116: CREPE BATTER | C116: 1 | D116: SERVING | E116: ='Item list'!B8 -> 2.1545599 | F116: =E116*C116 -> 2.1545599
A117: 2 | B117: BUTTER | C117: 0.015 | D117: KG | E117: =E103 -> 39.2 | F117: =E117*C117 -> 0.588
A118: 3 | B118: CARAMELIZED BANANA | C118: 1 | D118: SERVING | E118: ='Item list'!B57 -> 0.9055 | F118: =E118*C118 -> 0.9055
A119: 4 | B119: WHIPPING CREAM AEROSOL | C119: 0.001 | D119: KG | E119: ='Master Price list'!G37 -> 55 | F119: =E119*C119 -> 0.055
A120: 5 | B120: MINT LEAF | C120: 0.0001 | D120: KG | E120: ='Master Price list'!G187 -> 8.8 | F120: =E120*C120 -> 0.00088
D121: TOTAL | F121: =SUM(F116:F120) -> 3.7039399
A124: CREPPES W/LEMON & SUGAR
A125: NO | B125: INGREDIENT | C125: QUANTITY | D125: UOM | E125: UNIT PRICE | F125: TOTAL
A127: 1 | B127: CREPE BATTER | C127: 1 | D127: SERVING | E127: =E116 -> 2.1545599 | F127: =E127*C127 -> 2.1545599
A128: 2 | B128: BUTTER | C128: 0.015 | D128: KG | E128: =E117 -> 39.2 | F128: =E128*C128 -> 0.588
...

Sheet INGREDIENTS
B1: SUPLIER & ITEMS | C1: UNIT | D1: PRICE | E1: UNIT | F1: PRICE | H1: Monday Thunder Stock | I1: Min Home Stock | J1: Order Amount
B2: Thunder HOUSE Blend | N2: Blend %
B3: Indonesia Robusta | C3: kg | D3: =3430.7/120 -> 28.589167 | M3: =D3*N3 -> 7.1472917 | N3: 0.25
B4: Ethiopia | C4: kg | D4: 36.4 | M4: =D4*N4 -> 27.3 | N4: 0.75
B5: BLEND PRICE | E5: gm | F5: =M5/1000 -> 0.040526225 | M5: =(SUM(M3:M4))/0.85 -> 40.526225 | N5: KG price
B6: Thunder MAGIC Blend | N6: Blend %
B7: Rwanda | C7: kg | D7: 40 | M7: =D7*N7 -> 20 | N7: 0.5
B8: Ethiopia | C8: kg | D8: 36.4 | M8: =D8*N8 -> 18.2 | N8: 0.5
B9: BLEND PRICE | E9: gm | F9: =M9/1000 -> 0.044941176 | M9: =(SUM(M7:M8))/0.85 -> 44.941176 | N9: KG price
B10: Flacon Greens
B11: Brazil Roasted Beans | C11: kg | D11: 70 | E11: gm | F11: =D11/1000 -> 0.07
D12: 0 | F12: =D12/1000 -> 0
D13: 0 | F13: =D13/1000 -> 0
D14: 0 | F14: =D14/1000 -> 0
D15: 0 | F15: =D15/1000 -> 0
D16: 0 | F16: =D16/1000 -> 0
B18: OBTECH
B19: 12 oz double wall hot cups ( plain white) | C19: ctn | D19: 160 | E19: PCS | F19: =D19/500 -> 0.32
B20: Pla Sipper hot Cup Lids 12oz/16oz white | C20: ctn | D20: 220 | E20: PCS | F20: =D20/1000 -> 0.22
B21: 12 oz Plastic pet cup | C21: ctn | D21: 270 | E21: PCS | F21: =D21/1000 -> 0.27
B22: 12 oz Plastic cup lids | C22: ctn | D22: 230 | E22: PCS | F22: =D22/2000 -> 0.115
B23: 8OZ HOT CUP | C23: ctn | D23: 250 | E23: PCS | F23: =D23/1000 -> 0.25
B24: 8OZ HOT CUP LIDS | C24: ctn | D24: 220 | E24: PCS | F24: =D24/1000 -> 0.22
B25: satchel paper Bag - White | C25: ctn | D25: 270 | E25: PCS | F25: =D25/5000 -> 0.054
B26: 16 oz Plastic Pet cup | C26: ctn | D26: 290 | E26: PCS | F26: =D26/1000 -> 0.29
B27: 16 oz Plastic Pet lids Flate Lids | C27: ctn | D27: 150 | E27: PCS | F27: =D27/1000 -> 0.15
B28: Paper Straw | C28: Ctn | D28: 290 | E28: PCS | F28: =D28/5000 -> 0.058
B29: UGS
B30: 8oz Double wall Paper Cup white | C30: ctn | D30: 130 | F30: =D30/500 -> 0.26
B31: 12oz Double wall Paper cup White | C31: ctn
B32: 16OZ Tall Double Wall Paper Cup White | C32: ctn | D32: 190 | F32: =D32/500 -> 0.38
B33: 12oz 95mm Cleare ICED cup | C33: ctn | D33: 250 | F33: =D33/1000 -> 0.25
B34: Paper Straw White wrapped | C34: ctn | D34: 130 | F34: =D34/5000 -> 0.026
B35: 12oz/16oz ICED lids | C35: ctn | D35: 110 | F35: =D35/2000 -> 0.055
B37: AYC
B38: Farm fresh milk | C38: ctn/6btl/litter | D38: 14.26 | E38: ml | F38: =D38/1000 -> 0.01426
D39: 0 | F39: =D39/1000 -> 0
D40: 0 | F40: =D40/1000 -> 0
D41: 0 | F41: =D41/1000 -> 0
D42: 0 | F42: =D42/1000 -> 0
D43: 0 | F43: =D43/1000 -> 0
D44: 0 | F44: =D44/1000 -> 0
D45: 0 | F45: =D45/1000 -> 0
D46: 0 | F46: =D46/1000 -> 0
D47: 0 | F47: =D47/1000 -> 0
B48: LUCKY FROZEN
B49: Oat milk | C49: ctn/6btl/litter | D49: 9.3 | E49: ml | F49: =D49/1000 -> 0.0093
B50: Chicken Ham | C50: 800gm/30pkt | D50: 19.6 | F50: =D50/30 -> 0.65333333
B51: Bega Cheese | C51: kg/84slices | D51: 34.8 | F51: =D51/84 -> 0.41428571
B52: Greek Yoghurt | C52: ctn/6btl/litter | D52: 20 | E52: gm | F52: =D52/1000 -> 0.02
B53: Whipping Cream | C53: Ctn/ 1L | D53: =254.4/12 -> 21.2 | F53: =D53/1000 -> 0.0212
D54: 0 | F54: =D54/1000 -> 0
D55: 0 | F55: =D55/1000 -> 0
D56: 0 | F56: =D56/1000 -> 0
B57: ECIATTO
B58: Vanilla | C58: btl | D58: 69.5 | E58: ml | F58: =D58/1000 -> 0.0695
B59: Caramel | C59: btl | D59: 69.5 | E59: ml | F59: =D59/1000 -> 0.0695
B60: Salted caeamel | C60: btl | D60: 69.5 | E60: ml | F60: =D60/1000 -> 0.0695
B61: Coconut Syrup | C61: btl | D61: 69.5 | E61: ml | F61: =D61/1000 -> 0.0695
B62: Pineaple Pure | C62: btl | D62: 55 | E62: ml | F62: =D62/1000 -> 0.055
B63: Soda water | C63: lit | D63: 3.5 | E63: ml | F63: =D63/1000 -> 0.0035
B64: Montenee Strawberry real fruits mix | C64: btl | D64: 55 | E64: ml | F64: =D64/1000 -> 0.055
B65: Hazelnut Syrup | C65: btl | D65: 69.5 | E65: ml | F65: =D65/1000 -> 0.0695
B66: Montenee Peach Real fruit Mix | C66: btl | D66: 69.5 | E66: ml | F66: =D66/1000 -> 0.0695
B67: Yuzu Lemon Syrup | C67: btl | D67: 69.5 | E67: ml | F67: =D67/1000 -> 0.0695
B68: Montenee Mango Real Fruit Mix | C68: btl | D68: 69.5 | E68: ml | F68: =D68/1000 -> 0.0695
B69: Montenee Watermelon Real Fruit Mix | C69: btl | D69: 69.5 | E69: ml | F69: =D69/1000 -> 0.0695
... B74: Montenee Mixedberry | C74: btl | D74: 69.9 | E74: ml | F74: =D74/1000 -> 0.0699
F75: =D75/1000 -> 0
B76: YEAST
B77: SCHIACCIATA Bread | C77: TRAY | D77: 48 | E77: PCS | F77: =D77/21 -> 2.2857143
B78: Lemon loaf | C78: loaf | D78: 34 | E78: PCS | F78: =D78/8 -> 4.25
B79: Chocolate Marble Cake | C79: whole | D79: 34 | E79: PCS | F79: =D79/8 -> 4.25
B80: Banana Bread Loaf | C80: whole | D80: 34 | E80: PCS | F80: =D80/8 -> 4.25
B81: Focaccia Bread | C81: pcs | D81: 2 | E81: PCS | F81: =D81/1 -> 2
B82: Brioche Bread | C82: whole | D82: 25 | E82: PCS | F82: =D82/12 -> 2.0833333
B83: Sourdough | C83: 500g | D83: 26 | E83: portion | F83: =D83/12 -> 2.1666667
D84: 0 | F84: 0
D85: 0 | F85: 0
D86: 0 | F86: 0
B87: ANTIPODEAN
B88: Tomato Pest | C88: Tin/2.5kg | D88: 47 | F88: =D88/2500 -> 0.0188
B89: Origano | C89: btl/50gm | D89: 11 | F89: =D89/50 -> 0.22
B90: Whipping Cream | C90: pkt/1L | D90: 26 | F90: =D90/1000 -> 0.026
B91: Black Peper fine course | C91: pkt/500gm | D91: 38 | F91: =D91/500 -> 0.076
B92: Olive Oil | C92: BTL/1000 | D92: 57 | F92: =D92/1000 -> 0.057
B93: Parmesan Cheese | C93: kg/1000 | D93: 70 | F93: =D93/1000 -> 0.07
B94: Black Peper fine course | C94: kg/500 | D94: 38 | F94: =D94/500 -> 0.076
B95: Conchiglie Pasta | C95: pkt/500gm | D95: 8 | F95: =D95/500 -> 0.016
B96: Quick Oat | C96: pkt/1kg | D96: 11.1 | F96: =D96/1000 -> 0.0111
B97: strawberry | C97: pkt/1kg | D97: 30 | F97: =D97/1000 -> 0.03
B98: Blueberry | C98: pkt/400 | D98: 13 | F98: =D98/200 -> 0.065
B99: Cinemon Ground | C99: pkt/500gm | D99: 39 | F99: =D99/500 -> 0.078
B100: Pancake Syrup | C100: btl/1 L | D100: 17.5 | F100: =D100/1000 -> 0.0175
B101: Self Raisin Flour | C101: kg | D101: =22.5 -> 22.5 | E101: gm | F101: =D101/5000 -> 0.0045
B102: Smoke Salmon | C102: kg | D102: 120 | E102: gm | F102: =D102/1000 -> 0.12
B107: HOCK GUAN
B108: Lemon | C108: kg/1000 | D108: 9.5 | E108: slice | F108: =D108/1000 -> 0.0095
B109: Mayonese | C109: kg | D109: 20 | E109: gm | F109: =D109/1000 -> 0.02
B110: Red Onion | C110: kg/1000 | D110: 3.5 | E110: gm | F110: =D110/1000 -> 0.0035
...

Sheet Christmas Drinks 
B3: Eggnog Batch
B5: Ingredients | C5: Quantity | D5: Unit | E5: Cost Price | F5: Total Price
B6: Oat Milk | C6: 1.5 | D6: L | E6: =INGREDIENTS!F196 -> 0.03 | F6: =E6*C6 -> 0.045
B7: Cashew Nut | C7: 300 | D7: gm | E7: =12.9/300 -> 0.043 | F7: =E7*C7 -> 12.9
B8: Staranis | C8: 15 | D8: gm | E8: =3.8/30 -> 0.12666667 | F8: =E8*C8 -> 1.9
B9: Cinamon | C9: 30 | D9: Gm | E9: =3.8/30 -> 0.12666667 | F9: =E9*C9 -> 3.8
B10: Maple Syrup | C10: 90 | D10: ML | E10: =14.1/90 -> 0.15666667 | F10: =E10*C10 -> 14.1
F14: =SUM(F6:F13) -> 32.745
B15: Total Production Yield | C15: 2000
B16: Cost Per gm /ml | C16: =F14/C15 -> 0.0163725
B19: AngelFrost
B21: Ingredients | C21: Quantity | D21: Unit | E21: Cost Price | F21: Total Price
B22: 12oz ICED Cup | C22: 1 | D22: pcs | E22: =INGREDIENTS!F21 -> 0.27 | F22: =E22*C22 -> 0.27
B23: 12oz ICED Lids | C23: 1 | D23: pcs | E23: =INGREDIENTS!F22 -> 0.115 | F23: =E23*C23 -> 0.115
B24: Straw | C24: 1 | D24: Pcs | E24: =INGREDIENTS!F28 -> 0.058 | F24: =E24*C24 -> 0.058
B25: Coconut Cream | C25: 30 | D25: ml | E25: =11.5/1000 -> 0.0115 | F25: =E25*C25 -> 0.345
B26: Blue Syrup | C26: 20 | D26: ml | E26: =69/1000 -> 0.069 | F26: =E26*C26 -> 1.38
B27: Sugar Syrup | C27: 10 | D27: ml | E27: =INGREDIENTS!F179 -> 0.0048 | F27: =E27*C27 -> 0.048
B28: Lemon Juice | C28: 10 | D28: ml | E28: =INGREDIENTS!F108 -> 0.0095 | F28: =E28*C28 -> 0.095
B29: Milk | C29: 90 | D29: ml | E29: =INGREDIENTS!F38 -> 0.01426 | F29: =E29*C29 -> 1.2834
F30: =SUM(F22:F29) -> 3.5944
B31: Selling Price | C31: 13
B32: Cost Price | C32: =F30+5% -> 3.6444 | D32: =C32/C31 -> 0.28033846
B35: Vegan Eggnog
B37: 12oz ICED Cup | C37: 1 | D37: pcs | E37: =INGREDIENTS!F21 -> 0.27 | F37: =E37*C37 -> 0.27
B38: 12oz ICED Lids | C38: 1 | D38: pcs | E38: =INGREDIENTS!F11 -> 0.07 | F38: =E38*C38 -> 0.07
B39: Straw | C39: 1 | D39: Pcs | E39: =INGREDIENTS!F28 -> 0.058 | F39: =E39*C39 -> 0.058
B40: Mixed Eggnog | C40: 180 | D40: ml | E40: =C16 -> 0.0163725 | F40: =E40*C40 -> 2.94705
F45: =SUM(F37:F44) -> 3.34505
B46: Selling Price | C46: 15
B47: Cost Price | C47: =F45+5% -> 3.39505 | D47: =C47/C46 -> 0.22633667

Sheet RAVE EVENT 
D2: Min Pax | E2: 250 | F2: =E2*$C$6 -> 788.62476
D3: Expected Pax | E3: 400 | F3: =E3*$C$6 -> 1261.7996
D4: Max Pax | E4: 550 | F4: =E4*$C$6 -> 1734.9745
B6: Average Profit (less 20%); | C6: =(AVERAGE(C22,C39,C57,C74,C92))*0.8 -> 3.154499 | D6: Total Hous: | E6: 5 | F6: =F3/E6 -> 252.35992
B8: EDFLOWER ICE TEA
B10: Ingredients | C10: Quantity | D10: Unit | E10: Cost Price | F10: Total Price
B11: ElderFlower | C11: 30 | D11: ml | E11: =INGREDIENTS!F201 -> 0.028378378 | F11: =E11*C11 -> 0.85135135
B12: Lemon Juice | C12: 10 | D12: Ml | E12: =INGREDIENTS!F108 -> 0.0095 | F12: =E12*C12 -> 0.095
B13: Black Tea | C13: 1 | D13: Pcs | E13: =INGREDIENTS!F187 -> 0.106 | F13: =E13*C13 -> 0.106
B14: Salt | C14: 0.5 | D14: Gm | E14: =INGREDIENTS!F133 -> 0.01 | F14: =E14*C14 -> 0.005
B15: House Syrup | C15: 5 | D15: ML | E15: =INGREDIENTS!F179 -> 0.0048 | F15: =E15*C15 -> 0.024
B16: 12 Oz ice Cup | C16: 1 | D16: Pcs | E16: =INGREDIENTS!F21 -> 0.27 | F16: =E16*C16 -> 0.27
B17: Ice Lids | C17: 1 | D17: Pcs | E17: =INGREDIENTS!F22 -> 0.115 | F17: =E17*C17 -> 0.115
B18: Straw | C18: 1 | D18: Pcs | E18: =INGREDIENTS!F28 -> 0.058 | F18: =E18*C18 -> 0.058
F19: =SUM(F11:F18) -> 1.5243514
B20: Selling Price | C20: 5.5
B21: Cost Price | C21: =F19+5% -> 1.5743514 | D21: =C21/C20 -> 0.2862457
B22: Profit | C22: =C20-C21 -> 3.9256486
B25: COCO ICEBREW
B27: Ingredients | C27: Quantity | D27: Unit | E27: Cost Price | F27: Total Price
B28: Cold Brew | C28: 90 | D28: ML | E28: ='KITCHEN Prep Cards'!C24 -> 0.0046 | F28: =E28*C28 -> 0.414
B29: Coconut Syrup | C29: 25 | D29: ML | E29: =INGREDIENTS!F198 -> 0.028378378 | F29: =E29*C29 -> 0.70945946
B30: Lemon Juice | C30: 15 | D30: ML | E30: =INGREDIENTS!F108 -> 0.0095 | F30: =E30*C30 -> 0.1425
B31: House Syrup | C31: 5 | D31: ML | E31: =INGREDIENTS!F179 -> 0.0048 | F31: =E31*C31 -> 0.024
B32: Salt | C32: 0.5 | D32: gm | E32: =INGREDIENTS!F133 -> 0.01 | F32: =E32*C32 -> 0.005
B33: 12 Oz ice Cup | C33: 1 | D33: Pcs | E33: =INGREDIENTS!F21 -> 0.27 | F33: =E33*C33 -> 0.27
B34: Ice Lids | C34: 1 | D34: Pcs | E34: =INGREDIENTS!F22 -> 0.115 | F34: =E34*C34 -> 0.115
B35: Straw | C35: 1 | D35: Pcs | E35: =INGREDIENTS!F28 -> 0.058 | F35: =E35*C35 -> 0.058
F36: =SUM(F28:F35) -> 1.7379595
B37: Selling Price | C37: 5.5
B38: Cost Price | C38: =F36+5% -> 1.7879595 | D38: =C38/C37 -> 0.32508354
B39: Profit | C39: =C37-C38 -> 3.7120405
B42: LEMONGRASS ICE TEA
B44: Ingredients | C44: Quantity | D44: Unit | E44: Cost Price | F44: Total Price
B45: Lemon Grass Syrup | C45: 25 | D45: ML | E45: =INGREDIENTS!F202 -> 0.028378378 | F45: =E45*C45 -> 0.70945946
B46: Lemon Juice | C46: 15 | D46: ML | E46: =INGREDIENTS!F108 -> 0.0095 | F46: =E46*C46 -> 0.1425
B47: Mint Leaf | C47: 1 | D47: gm | E47: =INGREDIENTS!F134 -> 0.0888 | F47: =E47*C47 -> 0.0888
B48: Black Tea ( 90 ml ) | C48: 1 | D48: pcs | E48: =INGREDIENTS!F187 -> 0.106 | F48: =E48*C48 -> 0.106
B49: Salt | C49: 0.5 | D49: gm | E49: =INGREDIENTS!F133 -> 0.01 | F49: =E49*C49 -> 0.005
B50: Asam Boi | C50: 3 | D50: gm | E50: =INGREDIENTS!F197 -> 0.018 | F50: =E50*C50 -> 0.054
B51: 12 Oz ice Cup | C51: 1 | D51: Pcs | E51: =INGREDIENTS!F21 -> 0.27 | F51: =E51*C51 -> 0.27
B52: Ice Lids | C52: 1 | D52: Pcs | E52: =INGREDIENTS!F22 -> 0.115 | F52: =E52*C52 -> 0.115
B53: Straw | C53: 1 | D53: Pcs | E53: =INGREDIENTS!F28 -> 0.058 | F53: =E53*C53 -> 0.058
F54: =SUM(F45:F53) -> 1.5487595
B55: Selling Price | C55: 5.5
B56: Cost Price | C56: =F54+5% -> 1.5987595 | D56: =C56/C55 -> 0.29068354
B57: Profit | C57: =C55-C56 -> 3.9012405
B61: AQUA BOI
B63: Ingredients | C63: Quantity | D63: Unit | E63: Cost Price | F63: Total Price
B64: Sweet & Sour Syrup | C64: 25 | D64: ML | E64: =INGREDIENTS!F199 -> 0.028378378 | F64: =E64*C64 -> 0.70945946
B65: Asam Boi | C65: 3 | D65: gm | E65: =INGREDIENTS!F197 -> 0.018 | F65: =E65*C65 -> 0.054
B66: Grenadine Blue | C66: 5 | D66: Ml | E66: =INGREDIENTS!F200 -> 0.028378378 | F66: =E66*C66 -> 0.14189189
B67: House Syrup | C67: 10 | D67: ML | E67: =INGREDIENTS!F179 -> 0.0048 | F67: =E67*C67 -> 0.048
B68: 12 Oz ice Cup | C68: 1 | D68: Pcs | E68: =INGREDIENTS!F21 -> 0.27 | F68: =E68*C68 -> 0.27
B69: Ice Lids | C69: 1 | D69: Pcs | E69: =INGREDIENTS!F22 -> 0.115 | F69: =E69*C69 -> 0.115
B70: Straw | C70: 1 | D70: Pcs | E70: =INGREDIENTS!F28 -> 0.058 | F70: =E70*C70 -> 0.058
F71: =SUM(F64:F70) -> 1.3963514
B72: Selling Price | C72: 5.5
B73: Cost Price | C73: =F71+5% -> 1.4463514 | D73: =C73/C72 -> 0.26297297
B74: Profit | C74: =C72-C73 -> 4.0536486
B78: RUBY REFRESHER
B80: Ingredients | C80: Quantity | D80: Unit | E80: Cost Price | F80: Total Price
B81: Cosmopolitan | C81: 25 | D81: ML | E81: =INGREDIENTS!F203 -> 0.028378378 | F81: =E81*C81 -> 0.70945946
B82: Lemon Juice | C82: 10 | D82: ML | E82: =INGREDIENTS!F108 -> 0.0095 | F82: =E82*C82 -> 0.095
B83: House Syrup | C83: 5 | D83: Ml | E83: =INGREDIENTS!F179 -> 0.0048 | F83: =E83*C83 -> 0.024
B84: Asam Boi | C84: 3 | D84: gm | E84: =INGREDIENTS!F197 -> 0.018 | F84: =E84*C84 -> 0.054
B85: Red Colour | C85: 0.05 | D85: ML | E85: =6/200 -> 0.03 | F85: =E85*C85 -> 0.0015
B86: 12 Oz ice Cup | C86: 1 | D86: Pcs | E86: =INGREDIENTS!F21 -> 0.27 | F86: =E86*C86 -> 0.27
B87: Ice Lids | C87: 1 | D87: Pcs | E87: =INGREDIENTS!F22 -> 0.115 | F87: =E87*C87 -> 0.115
B88: Straw | C88: 1 | D88: Pcs | E88: =INGREDIENTS!F28 -> 0.058 | F88: =E88*C88 -> 0.058
F89: =SUM(F81:F88) -> 1.3269595
B90: Selling Price | C90: 5.5
B91: Cost Price | C91: =F89+5% -> 1.3769595 | D91: =C91/C90 -> 0.25035627
B92: Profit | C92: =C90-C91 -> 4.1230405

Sheet NEW MENU COSTING 
B3: Pesto Chicken Pasta
B5: Ingredients | C5: Quantity | D5: Unit | E5: Cost Price | F5: Total Price
B6: Chicken Breast | C6: 50 | D6: gm | E6: =INGREDIENTS!F$120 -> 0.011 | F6: =Table1[[#This Row],[Cost Price ]]*Table1[[#This Row],[Quantity]] -> 0.55
B7: Sunflower Oil | C7: 15 | D7: ml | E7: =INGREDIENTS!F$131 -> 0.010571429 | F7: =Table1[[#This Row],[Cost Price ]]*Table1[[#This Row],[Quantity]] -> 0.15857143
B8: Parmesan Cheese | C8: 5 | D8: gm | E8: =INGREDIENTS!F$93 -> 0.07 | F8: =Table1[[#This Row],[Cost Price ]]*Table1[[#This Row],[Quantity]] -> 0.35
B9: Spaghethi | C9: 130 | D9: gm | E9: =INGREDIENTS!F$122 -> 0.012 | F9: =Table1[[#This Row],[Cost Price ]]*Table1[[#This Row],[Quantity]] -> 1.56
B10: Tomato | C10: 30 | D10: gm | E10: =INGREDIENTS!F117 -> 0.0045 | F10: =Table1[[#This Row],[Cost Price ]]*Table1[[#This Row],[Quantity]] -> 0.135
B11: Salt | C11: 1 | D11: gm | E11: =INGREDIENTS!F128 -> 0.019 | F11: =Table1[[#This Row],[Cost Price ]]*Table1[[#This Row],[Quantity]] -> 0.019
B12: Pesto Sauce | C12: 25 | D12: gm | E12: ='KITCHEN Prep Cards'!C50 -> 0.051098214 | F12: =Table1[[#This Row],[Cost Price ]]*Table1[[#This Row],[Quantity]] -> 1.2774554
B13: Pepper | C13: 1 | D13: gm | E13: =INGREDIENTS!F133 -> 0.01 | F13: =Table1[[#This Row],[Cost Price ]]*Table1[[#This Row],[Quantity]] -> 0.01
F18: =SUM(F6:F13) -> 4.0600268
B19: Selling Price | C19: 27
B20: Cost Price | C20: =F18+5% -> 4.1100268 | D20: =C20/C19 -> 0.15222321
B21: Profit | C21: =C19-C20 -> 22.889973
B24: Pesto Chicken Sandwich
B26: Ingredients | C26: Quantity | D26: Unit | E26: Cost Price | F26: Total Price
B27: Chicken Breast | C27: 90 | D27: gm | E27: =INGREDIENTS!F137 -> 0.018 | F27: =Table13[[#This Row],[Cost Price ]]*Table13[[#This Row],[Quantity]] -> 1.62
B28: Sunflower Oil | C28: 15 | D28: ml | E28: =INGREDIENTS!F131 -> 0.010571429 | F28: =Table13[[#This Row],[Cost Price ]]*Table13[[#This Row],[Quantity]] -> 0.15857143
B29: Parmesan Cheese | C29: 5 | D29: gm | E29: =INGREDIENTS!F93 -> 0.07 | F29: =Table13[[#This Row],[Cost Price ]]*Table13[[#This Row],[Quantity]] -> 0.35
B30: Tomato | C30: 50 | D30: gm | E30: =INGREDIENTS!F117 -> 0.0045 | F30: =Table13[[#This Row],[Cost Price ]]*Table13[[#This Row],[Quantity]] -> 0.225
B31: Foccacia Bread | C31: 1 | D31: pcs | E31: =INGREDIENTS!D81 -> 2 | F31: =Table13[[#This Row],[Cost Price ]]*Table13[[#This Row],[Quantity]] -> 2
B32: Salt | C32: 1 | D32: gm | E32: =INGREDIENTS!F133 -> 0.01 | F32: =Table13[[#This Row],[Cost Price ]]*Table13[[#This Row],[Quantity]] -> 0.01
B33: Pesto Sauce | C33: 30 | D33: gm | E33: ='KITCHEN Prep Cards'!C50 -> 0.051098214 | F33: =Table13[[#This Row],[Cost Price ]]*Table13[[#This Row],[Quantity]] -> 1.5329464
B34: Pepper | C34: 1 | D34: gm | E34: =INGREDIENTS!F158 -> 0.06 | F34: =Table13[[#This Row],[Cost Price ]]*Table13[[#This Row],[Quantity]] -> 0.06
B35: Bega Cheese | C35: 1 | D35: pcs | E35: =INGREDIENTS!F51 -> 0.41428571 | F35: =Table13[[#This Row],[Cost Price ]]*Table13[[#This Row],[Quantity]] -> 0.41428571
F38: =SUM(F27:F36) -> 6.3708036
B39: Selling Price | C39: 25 | F39: =Table13[[#This Row],[Cost Price ]]*Table13[[#This Row],[Quantity]] -> 0
B40: Cost Price | C40: =F38+5% -> 6.4208036 | D40: =C40/C39 -> 0.25683214 | F40: =Table13[[#This Row],[Cost Price ]]*Table13[[#This Row],[Quantity]] -> 0
B41: Profit | C41: =C39-C40 -> 18.579196 | F41: =Table13[[#This Row],[Cost Price ]]*Table13[[#This Row],[Quantity]] -> 0
B44: Red Creamy Chicken Pasta
B46: Ingredients | C46: Quantity | D46: Unit | E46: Cost Price | F46: Total Price
B47: Whipping Cream | C47: 50 | D47: ml | E47: =INGREDIENTS!$F90 -> 0.026 | F47: =Table134[[#This Row],[Cost Price ]]*Table134[[#This Row],[Quantity]] -> 1.3
B48: Conchiglie Pasta | C48: 130 | D48: gm | E48: =INGREDIENTS!$F95 -> 0.016 | F48: =Table134[[#This Row],[Cost Price ]]*Table134[[#This Row],[Quantity]] -> 2.08
B49: Galice | C49: 5 | D49: gm | E49: =INGREDIENTS!$F123 -> 0.01 | F49: =Table134[[#This Row],[Cost Price ]]*Table134[[#This Row],[Quantity]] -> 0.05
B50: Sunflower Oil | C50: 5 | D50: ml | E50: =INGREDIENTS!F$131 -> 0.010571429 | F50: =Table134[[#This Row],[Cost Price ]]*Table134[[#This Row],[Quantity]] -> 0.052857143
B51: Parmesan Cheese | C51: 10 | D51: gm | E51: =INGREDIENTS!F$93 -> 0.07 | F51: =Table134[[#This Row],[Cost Price ]]*Table134[[#This Row],[Quantity]] -> 0.7
B52: Tamto Pest | C52: 20 | D52: gm | E52: =INGREDIENTS!F88 -> 0.0188 | F52: =Table134[[#This Row],[Cost Price ]]*Table134[[#This Row],[Quantity]] -> 0.376
B53: Half Slice of bread | C53: 0.5 | D53: pcs | E53: =INGREDIENTS!$F77 -> 2.2857143 | F53: =Table134[[#This Row],[Cost Price ]]*Table134[[#This Row],[Quantity]] -> 1.1428571
B54: Chicken Breast | C54: 130 | D54: gm | E54: =INGREDIENTS!$F137 -> 0.018 | F54: =Table134[[#This Row],[Cost Price ]]*Table134[[#This Row],[Quantity]] -> 2.34
B55: Salt | C55: 1 | D55: gm | E55: =INGREDIENTS!F$133 -> 0.01 | F55: =Table134[[#This Row],[Cost Price ]]*Table134[[#This Row],[Quantity]] -> 0.01
B56: Black Pepper | C56: 1 | D56: gm | E56: =INGREDIENTS!$F120 -> 0.011 | F56: =Table134[[#This Row],[Cost Price ]]*Table134[[#This Row],[Quantity]] -> 0.011
F57: =SUM(F47:F53) -> 5.7017143
B58: Selling Price | C58: 27
B59: Cost Price | C59: =F57+5% -> 5.7517143 | D59: =C59/C58 -> 0.21302646
B60: Profit | C60: =C58-C59 -> 21.248286
B63: Red Creamy Pasta
B65: Ingredients | C65: Quantity | D65: Unit | E65: Cost Price | F65: Total Price
B66: Whipping Cream | C66: 50 | D66: ml | E66: =INGREDIENTS!F90 -> 0.026 | F66: =Table1346[[#This Row],[Cost Price ]]*Table1346[[#This Row],[Quantity]] -> 1.3
B67: Fettacini Pasta | C67: 130 | D67: gm | E67: =INGREDIENTS!$F121 -> 0.019 | F67: =Table1346[[#This Row],[Cost Price ]]*Table1346[[#This Row],[Quantity]] -> 2.47
B68: Galice | C68: 5 | D68: gm | E68: =INGREDIENTS!F123 -> 0.01 | F68: =Table1346[[#This Row],[Cost Price ]]*Table1346[[#This Row],[Quantity]] -> 0.05
B69: Sunflower Oil | C69: 5 | D69: ml | E69: =INGREDIENTS!F$131 -> 0.010571429 | F69: =Table1346[[#This Row],[Cost Price ]]*Table1346[[#This Row],[Quantity]] -> 0.052857143
B70: Parmesan Cheese | C70: 10 | D70: gm | E70: =INGREDIENTS!F$93 -> 0.07 | F70: =Table1346[[#This Row],[Cost Price ]]*Table1346[[#This Row],[Quantity]] -> 0.7
B71: Tomato Pest | C71: 20 | D71: gm | E71: =INGREDIENTS!F88 -> 0.0188 | F71: =Table1346[[#This Row],[Cost Price ]]*Table1346[[#This Row],[Quantity]] -> 0.376
B72: Half Slice of bread | C72: 0.5 | D72: pcs | E72: =INGREDIENTS!F77 -> 2.2857143 | F72: =Table1346[[#This Row],[Cost Price ]]*Table1346[[#This Row],[Quantity]] -> 1.1428571
B73: Salt | C73: 1 | D73: gm | E73: =INGREDIENTS!F$133 -> 0.01 | F73: =Table1346[[#This Row],[Cost Price ]]*Table1346[[#This Row],[Quantity]] -> 0.01
B74: Black Pepper | C74: 1 | D74: gm | E74: =INGREDIENTS!F94 -> 0.076 | F74: =Table1346[[#This Row],[Cost Price ]]*Table1346[[#This Row],[Quantity]] -> 0.076
F75: =SUM(F66:F72) -> 6.0917143
B76: Selling Price | C76: 22
B77: Cost Price | C77: =F75+5% -> 6.1417143 | D77: =C77/C76 -> 0.27916883
B78: Profit | C78: =C76-C77 -> 15.858286
B79: October 2025 Special Menu
B81: Cremy Pesto Chicken Pasta
B83: Ingredients | C83: Quantity | D83: Unit | E83: Cost Price | F83: Total Price
B84: Chicken Breast | C84: 50 | D84: gm | E84: =INGREDIENTS!F$120 -> 0.011 | F84: =Table18[[#This Row],[Cost Price ]]*Table18[[#This Row],[Quantity]] -> 0.55
B85: Whipping Cream | C85: 60 | D85: ml | E85: =INGREDIENTS!F53 -> 0.0212 | F85: =Table18[[#This Row],[Cost Price ]]*Table18[[#This Row],[Quantity]] -> 1.272
B86: Sunflower Oil | C86: 15 | D86: ml | E86: =INGREDIENTS!F$131 -> 0.010571429 | F86: =Table18[[#This Row],[Cost Price ]]*Table18[[#This Row],[Quantity]] -> 0.15857143
B87: Parmesan Cheese | C87: 5 | D87: gm | E87: =INGREDIENTS!F$93 -> 0.07 | F87: =Table18[[#This Row],[Cost Price ]]*Table18[[#This Row],[Quantity]] -> 0.35
B88: French Pasta- Fusili- Original | C88: 125 | D88: gm | E88: =INGREDIENTS!F215 -> 0.024 | F88: =Table18[[#This Row],[Cost Price ]]*Table18[[#This Row],[Quantity]] -> 3
B89: Tomato | C89: 30 | D89: gm | E89: =INGREDIENTS!F117 -> 0.0045 | F89: =Table18[[#This Row],[Cost Price ]]*Table18[[#This Row],[Quantity]] -> 0.135
B90: Salt | C90: 1 | D90: gm | E90: =INGREDIENTS!F133 -> 0.01 | F90: =Table18[[#This Row],[Cost Price ]]*Table18[[#This Row],[Quantity]] -> 0.01
B91: Pesto Sauce | C91: 25 | D91: gm | E91: ='KITCHEN Prep Cards'!C50 -> 0.051098214 | F91: =Table18[[#This Row],[Cost Price ]]*Table18[[#This Row],[Quantity]] -> 1.2774554
B92: Pepper | C92: 1 | D92: gm | E92: =INGREDIENTS!F91 -> 0.076 | F92: =Table18[[#This Row],[Cost Price ]]*Table18[[#This Row],[Quantity]] -> 0.076
F93: =SUM(F84:F92) -> 6.8290268
B94: Selling Price | C94: 28
B95: Cost Price | C95: =F93+5% -> 6.8790268 | D95: =C95/C94 -> 0.24567953
B96: Profit | C96: =C94-C95 -> 21.120973
B97: Ham & Mushroom Carbonara
B99: Ingredients | C99: Quantity | D99: Unit | E99: Cost Price | F99: Total Price
B100: Chicken Ham | C100: 1 | D100: pcs | E100: =INGREDIENTS!F50 -> 0.65333333 | F100: =Table189[[#This Row],[Cost Price ]]*Table189[[#This Row],[Quantity]] -> 0.65333333
B101: Mushroom | C101: 30 | D101: gm | E101: =INGREDIENTS!F121 -> 0.019 | F101: =Table189[[#This Row],[Cost Price ]]*Table189[[#This Row],[Quantity]] -> 0.57
B102: French Pasta- Fusili | C102: 125 | D102: gm | E102: =INGREDIENTS!F218 -> 0.024 | F102: =Table189[[#This Row],[Cost Price ]]*Table189[[#This Row],[Quantity]] -> 3
B103: Whipping Cream | C103: 60 | D103: ml | E103: =INGREDIENTS!F53 -> 0.0212 | F103: =Table189[[#This Row],[Cost Price ]]*Table189[[#This Row],[Quantity]] -> 1.272
B104: Egg Yolk | C104: 1 | D104: pcs | E104: =INGREDIENTS!F24 -> 0.22 | F104: =Table189[[#This Row],[Cost Price ]]*Table189[[#This Row],[Quantity]] -> 0.22
B105: Parmesan Cheese | C105: 15 | D105: gm | E105: =INGREDIENTS!F93 -> 0.07 | F105: =Table189[[#This Row],[Cost Price ]]*Table189[[#This Row],[Quantity]] -> 1.05
B106: Salt | C106: 1 | D106: gm | E106: =INGREDIENTS!F133 -> 0.01 | F106: =Table189[[#This Row],[Cost Price ]]*Table189[[#This Row],[Quantity]] -> 0.01
B107: Black Pepper | C107: 1 | D107: gm | E107: =INGREDIENTS!F91 -> 0.076 | F107: =Table189[[#This Row],[Cost Price ]]*Table189[[#This Row],[Quantity]] -> 0.076
F109: =SUM(F100:F108) -> 6.8513333
B110: Selling Price | C110: 29
B111: Cost Price | C111: =F109+5% -> 6.9013333 | D111: =C111/C110 -> 0.23797701
B112: Profit | C112: =C110-C111 -> 22.098667
B113: Creamy Grilled Chicken Fillet
B115: Ingredients | C115: Quantity | D115: Unit | E115: Cost Price | F115: Total Price
B116: Grilled Chicken | C116: 150 | D116: Gm | E116: =INGREDIENTS!F125 -> 0.018 | F116: =E116*C116 -> 2.7
B117: Mushroom | C117: 60 | D117: gm | E117: =INGREDIENTS!F121 -> 0.019 | F117: =E117*C117 -> 1.14
B118: Whipping Cream | C118: 60 | D118: ml | E118: =INGREDIENTS!F53 -> 0.0212 | F118: =E118*C118 -> 1.272
B119: Parmesan Cheese | C119: 15 | D119: gm | E119: =INGREDIENTS!F93 -> 0.07 | F119: =E119*C119 -> 1.05
B120: Grilled Tomato | C120: 30 | D120: gm | E120: =INGREDIENTS!F117 -> 0.0045 | F120: =E120*C120 -> 0.135
B121: Salt | C121: 0.5 | D121: gm | E121: =INGREDIENTS!F133 -> 0.01 | F121: =E121*C121 -> 0.005
B122: Black Pepper | C122: 0.5 | D122: gm | E122: =INGREDIENTS!F94 -> 0.076 | F122: =E122*C122 -> 0.038
B123: Oregano Powder | C123: 0.5 | D123: gm | E123: =INGREDIENTS!F89 -> 0.22 | F123: =E123*C123 -> 0.11
...

Sheet DRINK Prep Cards
B3: CHCOLATE SYRUP BATCH
B5: Ingredients | C5: Quantity | D5: Unit | E5: Cost Price | F5: Total Price
B6: Chocolate Powder | C6: 200 | D6: gm | E6: =50/1000 -> 0.05 | F6: =E6*C6 -> 10
B7: Cocoa Powder | C7: 300 | D7: gm | E7: =INGREDIENTS!F169 -> 0.07 | F7: =E7*C7 -> 21
B8: White Sugar | C8: 150 | D8: gm | E8: =INGREDIENTS!F164 -> 0.0048 | F8: =E8*C8 -> 0.72
B9: Water | C9: 1000 | D9: ml | E9: 0 | F9: =E9*C9 -> 0
B11: Total Production Yield | C11: =SUM(C6:C10) -> 1650 | F11: =SUM(F6:F10) -> 31.72
B12: Cost Per gm | C12: =F11/C11 -> 0.019224242
B15: COLD BREW BATCH
B17: Ingredients | C17: Quantity | D17: Unit | E17: Cost Price | F17: Total Price
B18: Coffee Ground | C18: 230 | D18: gm | E18: =INGREDIENTS!F11 -> 0.07 | F18: =E18*C18 -> 16.1
B19: Filter Water | C19: 3500 | D19: gm | E19: 0 | F19: =E19*C19 -> 0
B23: Total Production Yield | C23: 3500 | F23: =SUM(F18:F22) -> 16.1
B24: Production Per Ml | C24: =F23/C23 -> 0.0046

Sheet HOT Drinks 
B2: 6oz | N2: 12oz | T2: 16oz
B5: Thunder HOUSE Blend | N5: Thunder HOUSE Blend | T5: Thunder HOUSE Blend
B7: Ingredients | C7: Quantity | D7: Unit | E7: Cost Price | F7: Total Price | N7: Ingredients | O7: Quantity | P7: Unit | Q7: Cost Price | R7: Total Price | T7: Ingredients | U7: Quantity | V7: Unit | W7: Cost Price | X7: Total Price
B8: Coffee | C8: =16+(16*0.025) -> 16.4 | D8: gm | E8: =INGREDIENTS!$F$5 -> 0.040526225 | F8: =(E8*C8)/2 -> 0.33231505 | N8: Coffee | O8: =16+(16*0.025) -> 16.4 | P8: gm | Q8: =INGREDIENTS!$F$5 -> 0.040526225 | R8: =Q8*O8 -> 0.6646301 | T8: Coffee | U8: =16+(16*0.025) -> 16.4 | V8: gm | W8: =INGREDIENTS!$F$5 -> 0.040526225 | X8: =W8*U8 -> 0.6646301
B9: Farm Fresh Milk | C9: 110 | D9: ML | E9: =INGREDIENTS!$F$38 -> 0.01426 | F9: =E9*C9 -> 1.5686 | N9: Farm Fresh Milk | O9: 215 | P9: ML | Q9: =INGREDIENTS!$F$38 -> 0.01426 | R9: =Q9*O9 -> 3.0659 | T9: Farm Fresh Milk | U9: 250 | V9: ML | W9: =INGREDIENTS!$F$38 -> 0.01426 | X9: =W9*U9 -> 3.565
B10: 6oz Hot Cup | C10: 1 | D10: pcs | E10: =INGREDIENTS!F211 -> 0.076 | F10: =E10*C10 -> 0.076 | N10: 12oz Hot Cup | O10: 1 | P10: pcs | Q10: =INGREDIENTS!$F$19 -> 0.32 | R10: =Q10*O10 -> 0.32 | T10: 16oz Hot Cup | U10: 1 | V10: pcs | W10: =INGREDIENTS!F26 -> 0.29 | X10: =W10*U10 -> 0.29
N11: 12oz hot Cup Lids | O11: 1 | P11: pcs | Q11: =INGREDIENTS!$F$20 -> 0.22 | R11: =Q11*O11 -> 0.22 | T11: 16oz hot Cup Lids | U11: 1 | V11: pcs | W11: =INGREDIENTS!F27 -> 0.15 | X11: =W11*U11 -> 0.15
F13: =SUM(F8:F12) -> 1.976915 | R13: =SUM(R8:R12) -> 4.2705301 | X13: =SUM(X8:X12) -> 4.6696301
B14: Selling Price | C14: 6 | N14: Selling Price | O14: 8.5 | T14: Selling Price | U14: 10.5
B15: Cost Price | C15: =F13+5% -> 2.026915 | D15: =C15/C14 -> 0.33781917 | N15: Cost Price | O15: =R13+5% -> 4.3205301 | P15: =O15/O14 -> 0.50829766 | T15: Cost Price | U15: =X13+5% -> 4.7196301 | V15: =U15/U14 -> 0.44948858
B16: Profit | C16: =C14-C15 -> 3.973085 | N16: Profit | O16: =O14-O15 -> 4.1794699 | T16: Profit | U16: =U14-U15 -> 5.7803699
B18: 6oz | H18: 8oz | N18: 12oz | T18: 16oz
B21: Traditional Chai | H21: Thunder MAGIC Blend | N21: Thunder MAGIC Blend | T21: Thunder MAGIC Blend
B23: Ingredients | C23: Quantity | D23: Unit | E23: Cost Price | F23: Total Price | H23: Ingredients | I23: Quantity | J23: Unit | K23: Cost Price | L23: Total Price | N23: Ingredients | O23: Quantity | P23: Unit | Q23: Cost Price | R23: Total Price | T23: Ingredients | U23: Quantity | V23: Unit | W23: Cost Price | X23: Total Price
B24: Fresh Milk | C24: 200 | D24: Ml | E24: =INGREDIENTS!$F$38 -> 0.01426 | F24: =E24*C24 -> 2.852 | H24: Coffee | I24: =16+(16*0.025) -> 16.4 | J24: gm | K24: =INGREDIENTS!$F$9 -> 0.044941176 | L24: =(K24*I24)/2 -> 0.36851765 | N24: Coffee | O24: =16+(16*0.025) -> 16.4 | P24: gm | Q24: =INGREDIENTS!$F$9 -> 0.044941176 | R24: =Q24*O24 -> 0.73703529 | T24: Coffee | U24: =16+(16*0.025) -> 16.4 | V24: gm | W24: =INGREDIENTS!$F$9 -> 0.044941176 | X24: =W24*U24 -> 0.73703529
B25: BOH Tea | C25: 2 | D25: Gm | E25: =INGREDIENTS!$F$284 -> 0.0296 | F25: =E25*C25 -> 0.0592 | H25: Farm Fresh Milk | I25: 180 | J25: ML | K25: =INGREDIENTS!$F$38 -> 0.01426 | L25: =K25*I25 -> 2.5668 | N25: Farm Fresh Milk | O25: 215 | P25: ML | Q25: =INGREDIENTS!$F$38 -> 0.01426 | R25: =Q25*O25 -> 3.0659 | T25: Farm Fresh Milk | U25: 225 | V25: ML | W25: =INGREDIENTS!$F$38 -> 0.01426 | X25: =W25*U25 -> 3.2085
B26: White Sugar | C26: 20 | D26: Gm | E26: =INGREDIENTS!$F$164 -> 0.0048 | F26: =E26*C26 -> 0.096 | H26: 8oz Hot Cup | I26: 1 | J26: pcs | K26: =INGREDIENTS!$F$23 -> 0.25 | L26: =K26*I26 -> 0.25 | N26: 12oz Hot Cup | O26: 1 | P26: pcs | Q26: =INGREDIENTS!$F$19 -> 0.32 | R26: =Q26*O26 -> 0.32 | T26: 16oz Hot Cup | U26: 1 | V26: pcs | W26: =INGREDIENTS!F207 -> 0.38 | X26: =W26*U26 -> 0.38
B27: Cardamom | C27: 2 | D27: gm | E27: =INGREDIENTS!$F$282 -> 0.17 | F27: =E27*C27 -> 0.34 | H27: 8oz hot Cup Lids | I27: 1 | J27: pcs | K27: =INGREDIENTS!$F$24 -> 0.22 | L27: =K27*I27 -> 0.22 | N27: 12oz hot Cup Lids | O27: 1 | P27: pcs | Q27: =INGREDIENTS!$F$20 -> 0.22 | R27: =Q27*O27 -> 0.22 | T27: 16oz hot Cup Lids | U27: 1 | V27: pcs | W27: =INGREDIENTS!$F$20 -> 0.22 | X27: =W27*U27 -> 0.22
B28: Young Ginger | C28: 1 | D28: gm | E28: =INGREDIENTS!$F$283 -> 0.03 | F28: =E28*C28 -> 0.03
B29: Gloves | C29: 1 | D29: gm | E29: =INGREDIENTS!F283 -> 0.03 | F29: =E29*C29 -> 0.03
B30: Water | C30: 150 | D30: ML | E30: 0 | F30: =E30*C30 -> 0 | L30: =SUM(L24:L28) -> 3.4053176 | R30: =SUM(R24:R28) -> 4.3429353 | X30: =SUM(X24:X28) -> 4.5455353
B31: 6oz Take Away Paper Cups | C31: 1 | D31: Pcs | E31: =INGREDIENTS!$F$211 -> 0.076 | F31: =E31*C31 -> 0.076
B33: Selling Price | C33: 4 | F33: =SUM(F24:F31) -> 3.4832 | H33: Selling Price | I33: 8.5 | N33: Selling Price | O33: 10 | T33: Selling Price | U33: 12
B34: Cost Price | C34: =F33/2 -> 1.7416 | D34: =C34/C33 -> 0.4354 | H34: Cost Price | I34: =L30+5% -> 3.4553176 | J34: =I34/I33 -> 0.40650796 | N34: Cost Price | O34: =R30+5% -> 4.3929353 | P34: =O34/O33 -> 0.43929353 | T34: Cost Price | U34: =X30+5% -> 4.5955353 | V34: =U34/U33 -> 0.38296127
B35: Profit | C35: =C33-C34 -> 2.2584 | H35: Profit | I35: =I33-I34 -> 5.0446824 | N35: Profit | O35: =O33-O34 -> 5.6070647 | T35: Profit | U35: =U33-U34 -> 7.4044647
H37: 8oz | N37: 12Oz | T37: 16Oz
H40: Falcon Greens - White Coffee Hot Without Flavor 8oz | N40: Falcon Greens - White Coffee Hot Without Flavor 120z | T40: Falcon Greens - White Coffee Hot Without Flavor 160z
H42: Ingredients | I42: Quantity | J42: Unit | K42: Cost Price | L42: Total Price | N42: Ingredients | O42: Quantity | P42: Unit | Q42: Cost Price | R42: Total Price | T42: Ingredients | U42: Quantity | V42: Unit | W42: Cost Price | X42: Total Price
H43: Coffee | I43: =16+(16*0.025) -> 16.4 | J43: gm | K43: =INGREDIENTS!$F$11 -> 0.07 | L43: =K43*I43 -> 1.148 | N43: Coffee | O43: =16+(16*0.025) -> 16.4 | P43: gm | Q43: =INGREDIENTS!F11 -> 0.07 | R43: =Q43*O43 -> 1.148 | T43: Coffee | U43: =16+(16*0.025) -> 16.4 | V43: gm | W43: =INGREDIENTS!F11 -> 0.07 | X43: =W43*U43 -> 1.148
H44: Farm Fresh Milk | I44: 205 | J44: ML | K44: =INGREDIENTS!$F$38 -> 0.01426 | L44: =K44*I44 -> 2.9233 | N44: Farm Fresh Milk | O44: 215 | P44: ML | Q44: =INGREDIENTS!$F$38 -> 0.01426 | R44: =Q44*O44 -> 3.0659 | T44: Farm Fresh Milk | U44: 225 | V44: ML | W44: =INGREDIENTS!$F$38 -> 0.01426 | X44: =W44*U44 -> 3.2085
H45: 8oz Hot Cup | I45: 1 | J45: pcs | K45: =INGREDIENTS!$F$23 -> 0.25 | L45: =K45*I45 -> 0.25 | N45: 12oz Hot Cup | O45: 1 | P45: pcs | Q45: =INGREDIENTS!$F$19 -> 0.32 | R45: =Q45*O45 -> 0.32 | T45: 16oz Hot Cup | U45: 1 | V45: pcs | W45: =INGREDIENTS!F207 -> 0.38 | X45: =W45*U45 -> 0.38
H46: 8oz hot Cup Lids | I46: 1 | J46: pcs | K46: =INGREDIENTS!$F$24 -> 0.22 | L46: =K46*I46 -> 0.22 | N46: 12oz hot Cup Lids | O46: 1 | P46: pcs | Q46: =INGREDIENTS!$F$20 -> 0.22 | R46: =Q46*O46 -> 0.22 | T46: 16oz hot Cup Lids | U46: 1 | V46: pcs | W46: =INGREDIENTS!$F$20 -> 0.22 | X46: =W46*U46 -> 0.22
L48: =SUM(L43:L47) -> 4.5413 | R48: =SUM(R43:R47) -> 4.7539 | X48: =SUM(X43:X47) -> 4.9565
H49: Selling Price | I49: 8 | N49: Selling Price | O49: 8.5 | T49: Selling Price | U49: 11
H50: Cost Price | I50: =L48+5% -> 4.5913 | J50: =I50/I49 -> 0.5739125 | N50: Cost Price | O50: =R48+5% -> 4.8039 | P50: =O50/O49 -> 0.56516471 | T50: Cost Price | U50: =X48+5% -> 5.0065 | V50: =U50/U49 -> 0.45513636
H51: Profit | I51: =I49-I50 -> 3.4087 | N51: Profit | O51: =O49-O50 -> 3.6961 | T51: Profit | U51: =U49-U50 -> 5.9935
H53: Gesha 8oz | N53: 12Oz | T53: 16Oz
H56: Falcon Greens - White Coffee Hot Without Flavor 8oz | N56: Falcon Greens - White Coffee Hot Without Flavor 120z | T56: Falcon Greens - White Coffee Hot Without Flavor 160z
H58: Ingredients | I58: Quantity | J58: Unit | K58: Cost Price | L58: Total Price | N58: Ingredients | O58: Quantity | P58: Unit | Q58: Cost Price | R58: Total Price | T58: Ingredients | U58: Quantity | V58: Unit | W58: Cost Price | X58: Total Price
H59: Coffee | I59: =16+(18*0.025) -> 16.45 | J59: gm | K59: =INGREDIENTS!$F$31 -> 0 | L59: =K59*I59 -> 0 | N59: Coffee | O59: =16+(18*0.025) -> 16.45 | P59: gm | Q59: =INGREDIENTS!F47 -> 0 | R59: =Q59*O59 -> 0 | T59: Coffee | U59: =16+(18*0.025) -> 16.45 | V59: gm | W59: =INGREDIENTS!F47 -> 0 | X59: =W59*U59 -> 0
H60: Farm Fresh Milk | I60: 205 | J60: ML | K60: =INGREDIENTS!$F$38 -> 0.01426 | L60: =K60*I60 -> 2.9233 | N60: Farm Fresh Milk | O60: 215 | P60: ML | Q60: =INGREDIENTS!$F$38 -> 0.01426 | R60: =Q60*O60 -> 3.0659 | T60: Farm Fresh Milk | U60: 225 | V60: ML | W60: =INGREDIENTS!$F$38 -> 0.01426 | X60: =W60*U60 -> 3.2085
H61: 8oz Hot Cup | I61: 1 | J61: pcs | K61: =INGREDIENTS!F13 -> 0 | L61: =K61*I61 -> 0 | N61: 12oz Hot Cup | O61: 1 | P61: pcs | Q61: =INGREDIENTS!$F$19 -> 0.32 | R61: =Q61*O61 -> 0.32 | T61: 16oz Hot Cup | U61: 1 | V61: pcs | W61: =INGREDIENTS!F252 -> 0 | X61: =W61*U61 -> 0
H62: 8oz hot Cup Lids | I62: 1 | J62: pcs | K62: =INGREDIENTS!F14 -> 0 | L62: =K62*I62 -> 0 | N62: 12oz hot Cup Lids | O62: 1 | P62: pcs | Q62: =INGREDIENTS!$F$20 -> 0.22 | R62: =Q62*O62 -> 0.22 | T62: 16oz hot Cup Lids | U62: 1 | V62: pcs | W62: =INGREDIENTS!$F$20 -> 0.22 | X62: =W62*U62 -> 0.22
L64: =SUM(L59:L63) -> 2.9233 | R64: =SUM(R59:R63) -> 3.6059 | X64: =SUM(X59:X63) -> 3.4285
H65: Selling Price | I65: 10 | N65: Selling Price | O65: 8.5 | T65: Selling Price | U65: 11
H66: Cost Price | I66: =L64+5% -> 2.9733 | J66: =I66/I65 -> 0.29733 | N66: Cost Price | O66: =R64+5% -> 3.6559 | P66: =O66/O65 -> 0.43010588 | T66: Cost Price | U66: =X64+5% -> 3.4785 | V66: =U66/U65 -> 0.31622727
H67: Profit | I67: =I65-I66 -> 7.0267 | N67: Profit | O67: =O65-O66 -> 4.8441 | T67: Profit | U67: =U65-U66 -> 7.5215
H69: Falcon Greens - White Coffee With Flavor | N69: Falcon Greens - White Coffee With Flavor | T69: Falcon Greens - White Coffee With Flavor
H71: Ingredients | I71: Quantity | J71: Unit | K71: Cost Price | L71: Total Price | N71: Ingredients | O71: Quantity | P71: Unit | Q71: Cost Price | R71: Total Price | T71: Ingredients | U71: Quantity | V71: Unit | W71: Cost Price | X71: Total Price
H72: Coffee | I72: =16+(18*0.025) -> 16.45 | J72: gm | K72: =INGREDIENTS!F11 -> 0.07 | L72: =K72*I72 -> 1.1515 | N72: Coffee | O72: =16+(18*0.025) -> 16.45 | P72: gm | Q72: =INGREDIENTS!F11 -> 0.07 | R72: =Q72*O72 -> 1.1515 | T72: Coffee | U72: =16+(18*0.025) -> 16.45 | V72: gm | W72: =INGREDIENTS!F11 -> 0.07 | X72: =W72*U72 -> 1.1515
H73: Farm Fresh Milk | I73: 205 | J73: ML | K73: =INGREDIENTS!F38 -> 0.01426 | L73: =K73*I73 -> 2.9233 | N73: Farm Fresh Milk | O73: 215 | P73: ML | Q73: =INGREDIENTS!$F$38 -> 0.01426 | R73: =Q73*O73 -> 3.0659 | T73: Farm Fresh Milk | U73: 225 | V73: ML | W73: =INGREDIENTS!$F$38 -> 0.01426 | X73: =W73*U73 -> 3.2085
H74: 8oz Hot Cup | I74: 1 | J74: pcs | K74: =INGREDIENTS!F23 -> 0.25 | L74: =K74*I74 -> 0.25 | N74: 12oz Hot Cup | O74: 1 | P74: pcs | Q74: =INGREDIENTS!F19 -> 0.32 | R74: =Q74*O74 -> 0.32 | T74: 16oz Hot Cup | U74: 1 | V74: pcs | W74: =INGREDIENTS!F207 -> 0.38 | X74: =W74*U74 -> 0.38
H75: 8oz hot Cup Lids | I75: 1 | J75: pcs | K75: =INGREDIENTS!F24 -> 0.22 | L75: =K75*I75 -> 0.22 | N75: 12oz hot Cup Lids | O75: 1 | P75: pcs | Q75: =INGREDIENTS!F20 -> 0.22 | R75: =Q75*O75 -> 0.22 | T75: 16oz hot Cup Lids | U75: 1 | V75: pcs | W75: =INGREDIENTS!F21 -> 0.27 | X75: =W75*U75 -> 0.27
H76: Add On Any flavor | I76: 10 | J76: ml | K76: =INGREDIENTS!$F$58 -> 0.0695 | L76: =K76*I76 -> 0.695 | N76: Add On Any flavor | O76: 10 | P76: ml | Q76: =INGREDIENTS!$F$58 -> 0.0695 | R76: =Q76*O76 -> 0.695 | T76: Add On Any flavor | U76: 10 | V76: ml | W76: =INGREDIENTS!$F$58 -> 0.0695 | X76: =W76*U76 -> 0.695
L81: =SUM(L72:L80) -> 5.2398 | R81: =SUM(R72:R80) -> 5.4524 | X81: =SUM(X72:X80) -> 5.705
H82: Selling Price | I82: 9 | N82: Selling Price | O82: 10.5 | T82: Selling Price | U82: 12
H83: Cost Price | I83: =L81+5% -> 5.2898 | J83: =I83/I82 -> 0.58775556 | N83: Cost Price | O83: =R81+5% -> 5.5024 | P83: =O83/O82 -> 0.5240381 | T83: Cost Price | U83: =X81+5% -> 5.755 | V83: =U83/U82 -> 0.47958333
H84: Profit | I84: =I82-I83 -> 3.7102 | N84: Profit | O84: =O82-O83 -> 4.9976 | T84: Profit | U84: =U82-U83 -> 6.245
H87: Falcon Greens - White Coffee Hot Mocha | N87: Falcon Greens - White Coffee Hot Mocha | T87: Falcon Greens - White Coffee Hot Mocha
H89: Ingredients | I89: Quantity | J89: Unit | K89: Cost Price | L89: Total Price | N89: Ingredients | O89: Quantity | P89: Unit | Q89: Cost Price | R89: Total Price | T89: Ingredients | U89: Quantity | V89: Unit | W89: Cost Price | X89: Total Price
H90: Coffee | I90: =8+(18*0.025) -> 8.45 | J90: gm | K90: =INGREDIENTS!F11 -> 0.07 | L90: =K90*I90 -> 0.5915 | N90: Coffee | O90: =8+(18*0.025) -> 8.45 | P90: gm | Q90: =INGREDIENTS!F11 -> 0.07 | R90: =Q90*O90 -> 0.5915 | T90: Coffee | U90: =8+(18*0.025) -> 8.45 | V90: gm | W90: =INGREDIENTS!F11 -> 0.07 | X90: =W90*U90 -> 0.5915
H91: Farm Fresh Milk | I91: 205 | J91: ML | K91: =INGREDIENTS!$F$38 -> 0.01426 | L91: =K91*I91 -> 2.9233 | N91: Farm Fresh Milk | O91: 215 | P91: ML | Q91: =INGREDIENTS!$F$38 -> 0.01426 | R91: =Q91*O91 -> 3.0659 | T91: Farm Fresh Milk | U91: 225 | V91: ML | W91: =INGREDIENTS!$F$38 -> 0.01426 | X91: =W91*U91 -> 3.2085
H92: 8oz Hot Cup | I92: 1 | J92: pcs | K92: =INGREDIENTS!F23 -> 0.25 | L92: =K92*I92 -> 0.25 | N92: 12oz Hot Cup | O92: 1 | P92: pcs | Q92: =INGREDIENTS!F19 -> 0.32 | R92: =Q92*O92 -> 0.32 | T92: 16oz Hot Cup | V92: pcs | W92: =INGREDIENTS!F195 -> 0.1 | X92: =W92*U92 -> 0
H93: 8oz hot Cup Lids | I93: 1 | J93: pcs | K93: =INGREDIENTS!F24 -> 0.22 | L93: =K93*I93 -> 0.22 | N93: 12oz hot Cup Lids | O93: 1 | P93: pcs | Q93: =INGREDIENTS!F20 -> 0.22 | R93: =Q93*O93 -> 0.22 | T93: 16oz hot Cup Lids | U93: 1 | V93: pcs | W93: =INGREDIENTS!F207 -> 0.38 | X93: =W93*U93 -> 0.38
H94: Cocolate Syrup | I94: 15 | J94: gm | K94: ='KITCHEN Prep Cards'!C12 -> 0.019224242 | L94: =K94*I94 -> 0.28836364 | N94: Cocolate Syrup | O94: 15 | P94: gm | Q94: ='KITCHEN Prep Cards'!C12 -> 0.019224242 | R94: =Q94*O94 -> 0.28836364 | T94: Cocolate Syrup | U94: 15 | V94: gm | W94: ='KITCHEN Prep Cards'!C12 -> 0.019224242 | X94: =W94*U94 -> 0.28836364
L99: =SUM(L90:L98) -> 4.2731636 | R99: =SUM(R90:R98) -> 4.4857636 | X99: =SUM(X90:X98) -> 4.4683636
H100: Selling Price | I100: 8 | N100: Selling Price | O100: 8.5 | T100: Selling Price | U100: 11
H101: Cost Price | I101: =L99+5% -> 4.3231636 | J101: =I101/I100 -> 0.54039545 | N101: Cost Price | O101: =R99+5% -> 4.5357636 | P101: =O101/O100 -> 0.53361925 | T101: Cost Price | U101: =X99+5% -> 4.5183636 | V101: =U101/U100 -> 0.41076033
H102: Profit | I102: =I100-I101 -> 3.6768364 | N102: Profit | O102: =O100-O101 -> 3.9642364 | T102: Profit | U102: =U100-U101 -> 6.4816364
H105: Hot Chocolate | N105: Hot Chocolate | T105: Hot Chocolate
H107: Ingredients | I107: Quantity | J107: Unit | K107: Cost Price | L107: Total Price | N107: Ingredients | O107: Quantity | P107: Unit | Q107: Cost Price | R107: Total Price | T107: Ingredients | U107: Quantity | V107: Unit | W107: Cost Price | X107: Total Price
H108: Farm Fresh Milk | I108: 205 | J108: ML | K108: =INGREDIENTS!$F$38 -> 0.01426 | L108: =K108*I108 -> 2.9233 | N108: Farm Fresh Milk | O108: 215 | P108: ML | Q108: =INGREDIENTS!$F$38 -> 0.01426 | R108: =Q108*O108 -> 3.0659 | T108: Farm Fresh Milk | U108: 225 | V108: ML | W108: =INGREDIENTS!$F$38 -> 0.01426 | X108: =W108*U108 -> 3.2085
H109: 12oz Hot Cup | I109: 1 | J109: pcs | K109: =INGREDIENTS!$F$19 -> 0.32 | L109: =K109*I109 -> 0.32 | N109: 12oz Hot Cup | O109: 1 | P109: pcs | Q109: =INGREDIENTS!$F$19 -> 0.32 | R109: =Q109*O109 -> 0.32 | T109: 16oz Hot Cup | U109: 1 | V109: pcs | W109: =INGREDIENTS!F207 -> 0.38 | X109: =W109*U109 -> 0.38
H110: 12oz hot Cup Lids | I110: 1 | J110: pcs | K110: =INGREDIENTS!$F$20 -> 0.22 | L110: =K110*I110 -> 0.22 | N110: 12oz hot Cup Lids | O110: 1 | P110: pcs | Q110: =INGREDIENTS!$F$20 -> 0.22 | R110: =Q110*O110 -> 0.22 | T110: 16oz hot Cup Lids | U110: 1 | V110: pcs | W110: =INGREDIENTS!$F$20 -> 0.22 | X110: =W110*U110 -> 0.22
H111: Cocolate Syrup | I111: 25 | J111: gm | K111: ='KITCHEN Prep Cards'!$C$12 -> 0.019224242 | L111: =K111*I111 -> 0.48060606 | N111: Cocolate Syrup | O111: 25 | P111: gm | Q111: ='KITCHEN Prep Cards'!$C$12 -> 0.019224242 | R111: =Q111*O111 -> 0.48060606 | T111: Cocolate Syrup | U111: 25 | V111: gm | W111: ='KITCHEN Prep Cards'!$C$12 -> 0.019224242 | X111: =W111*U111 -> 0.48060606
L116: =SUM(L108:L111) -> 3.9439061 | R116: =SUM(R108:R111) -> 4.0865061 | X116: =SUM(X108:X111) -> 4.2891061
H117: Selling Price | I117: 8.5 | N117: Selling Price | O117: 8.5 | T117: Selling Price | U117: 11
H118: Cost Price | I118: =L116+5% -> 3.9939061 | J118: =I118/I117 -> 0.4698713 | N118: Cost Price | O118: =R116+5% -> 4.1365061 | P118: =O118/O117 -> 0.48664777 | T118: Cost Price | U118: =X116+5% -> 4.3391061 | V118: =U118/U117 -> 0.39446419
H119: Profit | I119: =I117-I118 -> 4.5060939 | N119: Profit | O119: =O117-O118 -> 4.3634939 | T119: Profit | U119: =U117-U118 -> 6.6608939
H122: Falcon Greens - Chai Tarek | N122: Falcon Greens - Chai Tarek | T122: Falcon Greens - Chai Tarek
H124: Ingredients | I124: Quantity | J124: Unit | K124: Cost Price | L124: Total Price | N124: Ingredients | O124: Quantity | P124: Unit | Q124: Cost Price | R124: Total Price | T124: Ingredients | U124: Quantity | V124: Unit | W124: Cost Price | X124: Total Price
H125: 8oz Hot Cup | I125: 1 | J125: pcs | K125: =INGREDIENTS!F23 -> 0.25 | L125: =K125*I125 -> 0.25 | N125: 12oz Hot Cup | O125: 1 | P125: pcs | Q125: =INGREDIENTS!F19 -> 0.32 | R125: =Q125*O125 -> 0.32 | T125: 16oz Hot Cup | U125: 1 | V125: pcs | W125: =INGREDIENTS!F207 -> 0.38 | X125: =W125*U125 -> 0.38
H126: 8oz hot Cup Lids | I126: 1 | J126: pcs | K126: =INGREDIENTS!F24 -> 0.22 | L126: =K126*I126 -> 0.22 | N126: 12oz hot Cup Lids | O126: 1 | P126: pcs | Q126: =INGREDIENTS!F20 -> 0.22 | R126: =Q126*O126 -> 0.22 | T126: 16oz hot Cup Lids | U126: 1 | V126: pcs | W126: =INGREDIENTS!F20 -> 0.22 | X126: =W126*U126 -> 0.22
H127: Chai Powder | I127: 15 | J127: gm | K127: =INGREDIENTS!F170 -> 0.125 | L127: =K127*I127 -> 1.875 | N127: Chai Powder | O127: 15 | P127: gm | Q127: =INGREDIENTS!F170 -> 0.125 | R127: =Q127*O127 -> 1.875 | T127: Chai Powder | U127: 15 | V127: gm | W127: =INGREDIENTS!F170 -> 0.125 | X127: =W127*U127 -> 1.875
H128: Condence Milk | I128: 20 | J128: ml | K128: =INGREDIENTS!F120 -> 0.011 | L128: =K128*I128 -> 0.22 | N128: Condence Milk | O128: 20 | P128: ml | Q128: =INGREDIENTS!F120 -> 0.011 | R128: =Q128*O128 -> 0.22 | T128: Condence Milk | U128: 20 | V128: ml | W128: =INGREDIENTS!F120 -> 0.011 | X128: =W128*U128 -> 0.22
H129: Lipton Tea | I129: 3 | J129: pcs | K129: =INGREDIENTS!F185 -> 0.4 | L129: =K129*I129 -> 1.2 | N129: Lipton Tea | O129: 3 | P129: pcs | Q129: =INGREDIENTS!F185 -> 0.4 | R129: =Q129*O129 -> 1.2 | T129: Lipton Tea | U129: 3 | V129: pcs | W129: =INGREDIENTS!F185 -> 0.4 | X129: =W129*U129 -> 1.2
L132: =SUM(L125:L131) -> 3.765 | R132: =SUM(R125:R131) -> 3.835 | X132: =SUM(X125:X131) -> 3.895
H133: Selling Price | I133: 8 | N133: Selling Price | O133: 10 | T133: Selling Price | U133: 12
H134: Cost Price | I134: =L132+5% -> 3.815 | J134: =I134/I133 -> 0.476875 | N134: Cost Price | O134: =R132+5% -> 3.885 | P134: =O134/O133 -> 0.3885 | T134: Cost Price | U134: =X132+5% -> 3.945 | V134: =U134/U133 -> 0.32875
H135: Profit | I135: =I133-I134 -> 4.185 | N135: Profit | O135: =O133-O134 -> 6.115 | T135: Profit | U135: =U133-U134 -> 8.055
H138: KIMIDORI MATCHA | N138: KIMIDORI MATCHA | T138: KIMIDORI MATCHA
H139: Ingredients | I139: Quantity | J139: Unit | K139: Cost Price | L139: Total Price | N139: Ingredients | O139: Quantity | P139: Unit | Q139: Cost Price | R139: Total Price | T139: Ingredients | U139: Quantity | V139: Unit | W139: Cost Price | X139: Total Price
H140: Kimidori Matcha | I140: 3 | J140: gm | K140: =INGREDIENTS!F190 -> 0.44 | L140: =K140*I140 -> 1.32 | N140: Kimidori Matcha | O140: 3 | P140: gm | Q140: =INGREDIENTS!F190 -> 0.44 | R140: =Q140*O140 -> 1.32 | T140: Kimidori Matcha | U140: 3 | V140: gm | W140: =INGREDIENTS!F190 -> 0.44 | X140: =W140*U140 -> 1.32
H141: Fresh Milk | I141: 205 | J141: ml | K141: =INGREDIENTS!F38 -> 0.01426 | L141: =K141*I141 -> 2.9233 | N141: Fresh Milk | O141: 215 | P141: ml | Q141: =INGREDIENTS!F38 -> 0.01426 | R141: =Q141*O141 -> 3.0659 | T141: Fresh Milk | U141: 225 | V141: ml | W141: =INGREDIENTS!F38 -> 0.01426 | X141: =W141*U141 -> 3.2085
H142: Hot Cup 8Oz | I142: 1 | J142: pcs | K142: =INGREDIENTS!F23 -> 0.25 | L142: =K142*I142 -> 0.25 | N142: Hot Cup 12Oz | O142: 1 | P142: pcs | Q142: =INGREDIENTS!F19 -> 0.32 | R142: =Q142*O142 -> 0.32 | T142: 16oz Hot Cup 16Oz | U142: 1 | V142: pcs | W142: =INGREDIENTS!F207 -> 0.38 | X142: =W142*U142 -> 0.38
H143: 8Oz Hot Cup Lids | I143: 1 | J143: pcs | K143: =INGREDIENTS!F24 -> 0.22 | L143: =K143*I143 -> 0.22 | N143: 12ozHot Cup Lids | O143: 1 | P143: pcs | Q143: =INGREDIENTS!F20 -> 0.22 | R143: =Q143*O143 -> 0.22 | T143: 12ozHot Cup Lids | U143: 1 | V143: pcs | W143: =INGREDIENTS!F20 -> 0.22 | X143: =W143*U143 -> 0.22
L146: =SUM(L140:L145) -> 4.7133 | R146: =SUM(R140:R145) -> 4.9259 | X146: =SUM(X140:X145) -> 5.1285
H147: Selling Price | I147: 13 | N147: Selling Price | O147: 15 | T147: Selling Price | U147: 17
H148: Cost Price | I148: =L146+5% -> 4.7633 | J148: =I148/I147 -> 0.36640769 | N148: Cost Price | O148: =R146+5% -> 4.9759 | P148: =O148/O147 -> 0.33172667 | T148: Cost Price | U148: =X146+5% -> 5.1785 | V148: =U148/U147 -> 0.30461765
H149: Profit | I149: =I147-I148 -> 8.2367 | N149: Profit | O149: =O147-O148 -> 10.0241 | T149: Profit | U149: =U147-U148 -> 11.8215
...

Sheet ICED Drinks 
B2: 12Oz | H2: 16Oz
B5: Falcon Greens - White Coffee Hot Without Flavor 120z | H5: Falcon Greens - White Coffee Hot Without Flavor 160z
B7: Ingredients | C7: Quantity | D7: Unit | E7: Cost Price | F7: Total Price | H7: Ingredients | I7: Quantity | J7: Unit | K7: Cost Price | L7: Total Price
B8: Coffee | C8: =16+(18*0.025) -> 16.45 | D8: gm | E8: =INGREDIENTS!F11 -> 0.07 | F8: =E8*C8 -> 1.1515 | H8: Coffee | I8: =16+(18*0.025) -> 16.45 | J8: gm | K8: =INGREDIENTS!F11 -> 0.07 | L8: =K8*I8 -> 1.1515
B9: Farm Fresh Milk | C9: 215 | D9: ML | E9: =INGREDIENTS!F38 -> 0.01426 | F9: =E9*C9 -> 3.0659 | H9: Farm Fresh Milk | I9: 225 | J9: ML | K9: =INGREDIENTS!F38 -> 0.01426 | L9: =K9*I9 -> 3.2085
B10: 12oz ICED Cup | C10: 1 | D10: pcs | E10: =INGREDIENTS!F21 -> 0.27 | F10: =E10*C10 -> 0.27 | H10: 16oz ICED Cup | I10: 1 | J10: pcs | K10: =INGREDIENTS!F26 -> 0.29 | L10: =K10*I10 -> 0.29
B11: 12oz ICED Cup Lids | C11: 1 | D11: pcs | E11: =INGREDIENTS!F22 -> 0.115 | F11: =E11*C11 -> 0.115 | H11: 16oz ICED Cup Lids | I11: 1 | J11: pcs | K11: =INGREDIENTS!F27 -> 0.15 | L11: =K11*I11 -> 0.15
B12: Straw | C12: 1 | D12: pcs | E12: =INGREDIENTS!F28 -> 0.058 | F12: =E12*C12 -> 0.058 | H12: Straw | I12: 1 | J12: pcs | K12: =INGREDIENTS!F28 -> 0.058 | L12: =K12*I12 -> 0.058
F13: =SUM(F8:F12) -> 4.6604 | L13: =SUM(L8:L12) -> 4.858
B14: Selling Price | C14: 8.5 | H14: Selling Price | I14: 11
B15: Cost Price | C15: =F13+5% -> 4.7104 | D15: =C15/C14 -> 0.55416471 | H15: Cost Price | I15: =L13+5% -> 4.908 | J15: =I15/I14 -> 0.44618182
B16: Profit | C16: =C14-C15 -> 3.7896 | H16: Profit | I16: =I14-I15 -> 6.092
B18: Falcon Greens - White Coffee With Flavor | H18: Falcon Greens - White Coffee With Flavor
B20: Ingredients | C20: Quantity | D20: Unit | E20: Cost Price | F20: Total Price | H20: Ingredients | I20: Quantity | J20: Unit | K20: Cost Price | L20: Total Price
B21: Coffee | C21: =16+(18*0.025) -> 16.45 | D21: gm | E21: =INGREDIENTS!F11 -> 0.07 | F21: =E21*C21 -> 1.1515 | H21: Coffee | I21: =16+(18*0.025) -> 16.45 | J21: gm | K21: =INGREDIENTS!$F$49 -> 0.0093 | L21: =K21*I21 -> 0.152985
B22: Farm Fresh Milk | C22: 215 | D22: ML | E22: =INGREDIENTS!$F$38 -> 0.01426 | F22: =E22*C22 -> 3.0659 | H22: Farm Fresh Milk | I22: 225 | J22: ML | K22: =INGREDIENTS!$F$38 -> 0.01426 | L22: =K22*I22 -> 3.2085
B23: 12oz ICED Cup | C23: 1 | D23: pcs | E23: =INGREDIENTS!F21 -> 0.27 | F23: =E23*C23 -> 0.27 | H23: 16oz ICED Cup | I23: 1 | J23: pcs | K23: =INGREDIENTS!F26 -> 0.29 | L23: =K23*I23 -> 0.29
B24: 12oz ICED Cup Lids | C24: 1 | D24: pcs | E24: =INGREDIENTS!F22 -> 0.115 | F24: =E24*C24 -> 0.115 | H24: 16oz ICED Cup Lids | I24: 1 | J24: pcs | K24: =INGREDIENTS!F21 -> 0.27 | L24: =K24*I24 -> 0.27
B25: Add On Any flavor | C25: 10 | D25: ml | E25: =INGREDIENTS!$F$58 -> 0.0695 | F25: =E25*C25 -> 0.695 | H25: Add On Any flavor | I25: 10 | J25: ml | K25: =INGREDIENTS!$F$58 -> 0.0695 | L25: =K25*I25 -> 0.695
B26: Straw | C26: 1 | D26: pcs | E26: =INGREDIENTS!F28 -> 0.058 | F26: =E26*C26 -> 0.058 | H26: Straw | I26: 1 | J26: pcs | K26: =INGREDIENTS!F28 -> 0.058 | L26: =K26*I26 -> 0.058
F30: =SUM(F21:F29) -> 5.3554 | L30: =SUM(L21:L29) -> 4.674485
B31: Selling Price | C31: 9.5 | H31: Selling Price | I31: 12
B32: Cost Price | C32: =F30+5% -> 5.4054 | D32: =C32/C31 -> 0.56898947 | H32: Cost Price | I32: =L30+5% -> 4.724485 | J32: =I32/I31 -> 0.39370708
B33: Profit | C33: =C31-C32 -> 4.0946 | H33: Profit | I33: =I31-I32 -> 7.275515
B36: Falcon Greens - White Coffee Mocha | H36: Falcon Greens - White Coffee Mocha
B38: Ingredients | C38: Quantity | D38: Unit | E38: Cost Price | F38: Total Price | H38: Ingredients | I38: Quantity | J38: Unit | K38: Cost Price | L38: Total Price
B39: Coffee | C39: =8+(18*0.025) -> 8.45 | D39: gm | E39: =INGREDIENTS!F11 -> 0.07 | F39: =E39*C39 -> 0.5915 | H39: Coffee | I39: =8+(18*0.025) -> 8.45 | J39: gm | K39: =INGREDIENTS!F11 -> 0.07 | L39: =K39*I39 -> 0.5915
B40: Farm Fresh Milk | C40: 215 | D40: ML | E40: =INGREDIENTS!F38 -> 0.01426 | F40: =E40*C40 -> 3.0659 | H40: Farm Fresh Milk | I40: 225 | J40: ML | K40: =INGREDIENTS!$F$38 -> 0.01426 | L40: =K40*I40 -> 3.2085
B41: 12oz ICED Cup | C41: 1 | D41: pcs | E41: =INGREDIENTS!F26 -> 0.29 | F41: =E41*C41 -> 0.29 | H41: 16oz ICED Cup | I41: 1 | J41: pcs | K41: =INGREDIENTS!F195 -> 0.1 | L41: =K41*I41 -> 0.1
B42: 12oz ICED Cup Lids | C42: 1 | D42: pcs | E42: =INGREDIENTS!F22 -> 0.115 | F42: =E42*C42 -> 0.115 | H42: 16oz ICED Cup Lids | I42: 1 | J42: pcs | K42: =INGREDIENTS!F20 -> 0.22 | L42: =K42*I42 -> 0.22
B43: Cocolate Syrup | C43: 15 | D43: gm | E43: ='KITCHEN Prep Cards'!C12 -> 0.019224242 | F43: =E43*C43 -> 0.28836364 | H43: Cocolate Syrup | I43: 15 | J43: gm | K43: ='KITCHEN Prep Cards'!C12 -> 0.019224242 | L43: =K43*I43 -> 0.28836364
B44: Straw | C44: 1 | D44: pcs | E44: =INGREDIENTS!F28 -> 0.058 | F44: =E44*C44 -> 0.058 | H44: Straw | I44: 1 | J44: pcs | K44: =INGREDIENTS!F28 -> 0.058 | L44: =K44*I44 -> 0.058
F48: =SUM(F39:F47) -> 4.4087636 | L48: =SUM(L39:L47) -> 4.4663636
B49: Selling Price | C49: 8.5 | H49: Selling Price | I49: 11
B50: Cost Price | C50: =F48+5% -> 4.4587636 | D50: =C50/C49 -> 0.52456043 | H50: Cost Price | I50: =L48+5% -> 4.5163636 | J50: =I50/I49 -> 0.41057851
B51: Profit | C51: =C49-C50 -> 4.0412364 | H51: Profit | I51: =I49-I50 -> 6.4836364
B54: ICED Chocolate | H54: ICED Chocolate
B56: Ingredients | C56: Quantity | D56: Unit | E56: Cost Price | F56: Total Price | H56: Ingredients | I56: Quantity | J56: Unit | K56: Cost Price | L56: Total Price
B57: Farm Fresh Milk | C57: 215 | D57: ML | E57: =INGREDIENTS!F38 -> 0.01426 | F57: =E57*C57 -> 3.0659 | H57: Farm Fresh Milk | I57: 225 | J57: ML | K57: =INGREDIENTS!F38 -> 0.01426 | L57: =K57*I57 -> 3.2085
B58: 12oz ICED Cup | C58: 1 | D58: pcs | E58: =INGREDIENTS!F21 -> 0.27 | F58: =E58*C58 -> 0.27 | H58: 16oz ICED Cup | I58: 1 | J58: pcs | K58: =INGREDIENTS!F26 -> 0.29 | L58: =K58*I58 -> 0.29
B59: 12oz ICED Cup Lids | C59: 1 | D59: pcs | E59: =INGREDIENTS!F22 -> 0.115 | F59: =E59*C59 -> 0.115 | H59: 16oz ICED Cup Lids | I59: 1 | J59: pcs | K59: =INGREDIENTS!F27 -> 0.15 | L59: =K59*I59 -> 0.15
B60: Cocolate Syrup | C60: 25 | D60: gm | E60: ='KITCHEN Prep Cards'!C12 -> 0.019224242 | F60: =E60*C60 -> 0.48060606 | H60: Cocolate Syrup | I60: 25 | J60: gm | K60: ='KITCHEN Prep Cards'!C12 -> 0.019224242 | L60: =K60*I60 -> 0.48060606
B61: Straw | C61: 1 | D61: pcs | E61: =INGREDIENTS!F28 -> 0.058 | F61: =E61*C61 -> 0.058 | H61: Straw | I61: 1 | J61: pcs | K61: =INGREDIENTS!F28 -> 0.058 | L61: =K61*I61 -> 0.058
F65: =SUM(F57:F64) -> 3.9895061 | L65: =SUM(L57:L64) -> 4.1871061
B66: Selling Price | C66: 8.5 | H66: Selling Price | I66: 11
B67: Cost Price | C67: =F65+5% -> 4.0395061 | D67: =C67/C66 -> 0.47523601 | H67: Cost Price | I67: =L65+5% -> 4.2371061 | J67: =I67/I66 -> 0.38519146
B68: Profit | C68: =C66-C67 -> 4.4604939 | H68: Profit | I68: =I66-I67 -> 6.7628939
B71: Sunrise Espresso | H71: Sunrise Espresso
B72: Ingredients | C72: Quantity | D72: Unit | E72: Cost Price | F72: Total Price | H72: Ingredients | I72: Quantity | J72: Unit | K72: Cost Price | L72: Total Price
B73: Double Espresso | C73: =16+(18*0.025) -> 16.45 | D73: gm | E73: =INGREDIENTS!F11 -> 0.07 | F73: =E73*C73 -> 1.1515 | H73: Double Espresso | I73: =16+(18*0.025) -> 16.45 | J73: gm | K73: =INGREDIENTS!F11 -> 0.07 | L73: =K73*I73 -> 1.1515
B74: Lemon Juice | C74: 20 | D74: ml | E74: =INGREDIENTS!F108 -> 0.0095 | F74: =E74*C74 -> 0.19 | H74: Lemon Juice | I74: 20 | J74: ml | K74: =INGREDIENTS!F108 -> 0.0095 | L74: =K74*I74 -> 0.19
B75: Mint Leaf | C75: 1 | D75: gm | E75: =INGREDIENTS!F134 -> 0.0888 | F75: =E75*C75 -> 0.0888 | H75: Mint Leaf | I75: 1 | J75: gm | K75: =INGREDIENTS!F134 -> 0.0888 | L75: =K75*I75 -> 0.0888
B76: Water | C76: 60 | D76: Ml | E76: 0 | F76: =E76*C76 -> 0 | H76: Water | I76: 60 | J76: Ml | K76: 0 | L76: =K76*I76 -> 0
B77: 12oz ICED Cup | C77: 1 | D77: pcs | E77: =INGREDIENTS!F21 -> 0.27 | F77: =E77*C77 -> 0.27 | H77: 16oz ICED Cup | I77: 1 | J77: pcs | K77: =INGREDIENTS!F26 -> 0.29 | L77: =K77*I77 -> 0.29
B78: 12oz ICED Cup Lids | C78: 1 | D78: pcs | E78: =INGREDIENTS!F22 -> 0.115 | F78: =E78*C78 -> 0.115 | H78: 16oz ICED Cup Lids | I78: 1 | J78: pcs | K78: =INGREDIENTS!F27 -> 0.15 | L78: =K78*I78 -> 0.15
B79: Straw | C79: 1 | D79: pcs | E79: =INGREDIENTS!$F$25 -> 0.054 | F79: =E79*C79 -> 0.054 | H79: Straw | I79: 1 | J79: pcs | K79: =INGREDIENTS!F28 -> 0.058 | L79: =K79*I79 -> 0.058
F81: =SUM(F73:F80) -> 1.8693 | L81: =SUM(L73:L80) -> 1.9283
B82: Selling Price | C82: 12 | H82: Selling Price | I82: 16
B83: Cost Price | C83: =F81+5% -> 1.9193 | D83: =C83/C82 -> 0.15994167 | H83: Cost Price | I83: =L81+5% -> 1.9783 | J83: =I83/I82 -> 0.12364375
B84: Profit | C84: =C82-C83 -> 10.0807 | H84: Profit | I84: =I82-I83 -> 14.0217
B87: Strawberry Lemon Yuzu | H87: Strawberry Lemon Yuzu
B88: Ingredients | C88: Quantity | D88: Unit | E88: Cost Price | F88: Total Price | H88: Ingredients | I88: Quantity | J88: Unit | K88: Cost Price | L88: Total Price
B89: Strawberry Pure | C89: 30 | D89: ML | E89: =INGREDIENTS!F64 -> 0.055 | F89: =E89*C89 -> 1.65 | H89: Strawberry Pure | I89: 30 | J89: ML | K89: =INGREDIENTS!F64 -> 0.055 | L89: =K89*I89 -> 1.65
B90: Lemon Juice | C90: 20 | D90: ml | E90: =INGREDIENTS!F108 -> 0.0095 | F90: =E90*C90 -> 0.19 | H90: Lemon Juice | I90: 20 | J90: ml | K90: =INGREDIENTS!F108 -> 0.0095 | L90: =K90*I90 -> 0.19
B91: Soda Water | C91: 120 | D91: ml | E91: =INGREDIENTS!F63 -> 0.0035 | F91: =E91*C91 -> 0.42 | H91: Soda Water | I91: 120 | J91: ml | K91: =INGREDIENTS!F63 -> 0.0035 | L91: =K91*I91 -> 0.42
B92: 12oz ice Cup | C92: 1 | D92: pcs | E92: =INGREDIENTS!F21 -> 0.27 | F92: =E92*C92 -> 0.27 | H92: 16oz ICED Cup | I92: 1 | J92: pcs | K92: =INGREDIENTS!F26 -> 0.29 | L92: =K92*I92 -> 0.29
B93: 12oz ice Cup Lids | C93: 1 | D93: pcs | E93: =INGREDIENTS!F22 -> 0.115 | F93: =E93*C93 -> 0.115 | H93: 16oz ICED Cup Lids | I93: 1 | J93: pcs | K93: =INGREDIENTS!F27 -> 0.15 | L93: =K93*I93 -> 0.15
B94: Straw | C94: 1 | D94: pcs | E94: =INGREDIENTS!F28 -> 0.058 | F94: =E94*C94 -> 0.058 | H94: Straw | I94: 1 | J94: pcs | K94: =INGREDIENTS!F28 -> 0.058 | L94: =K94*I94 -> 0.058
F97: =SUM(F89:F96) -> 2.703 | L97: =SUM(L89:L96) -> 2.758
B98: Selling Price | C98: 12 | H98: Selling Price | I98: 16
B99: Cost Price | C99: =F97+5% -> 2.753 | D99: =C99/C98 -> 0.22941667 | H99: Cost Price | I99: =L97+5% -> 2.808 | J99: =I99/I98 -> 0.1755
B100: Profit | C100: =C98-C99 -> 9.247 | H100: Profit | I100: =I98-I99 -> 13.192
B103: Blue Ocean | H103: Blue Ocean
B104: Ingredients | C104: Quantity | D104: Unit | E104: Cost Price | F104: Total Price | H104: Ingredients | I104: Quantity | J104: Unit | K104: Cost Price | L104: Total Price
B105: Blue Syrup | C105: 20 | D105: ml | E105: =INGREDIENTS!F73 -> 0.06 | F105: =E105*C105 -> 1.2 | H105: Blue Syrup | I105: 20 | J105: ml | K105: =INGREDIENTS!F73 -> 0.06 | L105: =K105*I105 -> 1.2
B106: Lemon Juice | C106: 20 | D106: ml | E106: =INGREDIENTS!F108 -> 0.0095 | F106: =E106*C106 -> 0.19 | H106: Lemon Juice | I106: 20 | J106: ml | K106: =INGREDIENTS!F108 -> 0.0095 | L106: =K106*I106 -> 0.19
B107: Sugar Syrup | C107: 20 | D107: ml | E107: =INGREDIENTS!F179 -> 0.0048 | F107: =E107*C107 -> 0.096 | H107: Sugar Syrup | I107: 20 | J107: ml | K107: =INGREDIENTS!F179 -> 0.0048 | L107: =K107*I107 -> 0.096
B108: Soda Water | C108: 120 | D108: ml | E108: =INGREDIENTS!F63 -> 0.0035 | F108: =E108*C108 -> 0.42 | H108: Soda Water | I108: 120 | J108: ml | K108: =INGREDIENTS!F63 -> 0.0035 | L108: =K108*I108 -> 0.42
B109: 12oz ice Cup | C109: 1 | D109: pcs | E109: =INGREDIENTS!F21 -> 0.27 | F109: =E109*C109 -> 0.27 | H109: 16oz ICED Cup | I109: 1 | J109: pcs | K109: =INGREDIENTS!F26 -> 0.29 | L109: =K109*I109 -> 0.29
B110: 12oz ice Cup Lids | C110: 1 | D110: pcs | E110: =INGREDIENTS!F22 -> 0.115 | F110: =E110*C110 -> 0.115 | H110: 16oz ICED Cup Lids | I110: 1 | J110: pcs | K110: =INGREDIENTS!F27 -> 0.15 | L110: =K110*I110 -> 0.15
B111: Straw | C111: 1 | D111: pcs | E111: =INGREDIENTS!F28 -> 0.058 | F111: =E111*C111 -> 0.058 | H111: Straw | I111: 1 | J111: pcs | K111: =INGREDIENTS!F28 -> 0.058 | L111: =K111*I111 -> 0.058
F113: =SUM(F105:F112) -> 2.349 | L113: =SUM(L105:L112) -> 2.404
B114: Selling Price | C114: 12 | H114: Selling Price | I114: 16
B115: Cost Price | C115: =F113+5% -> 2.399 | D115: =C115/C114 -> 0.19991667 | H115: Cost Price | I115: =L113+5% -> 2.454 | J115: =I115/I114 -> 0.153375
B116: Profit | C116: =C114-C115 -> 9.601 | H116: Profit | I116: =I114-I115 -> 13.546
B119: Spanish Latte | H119: Spanish Latte
B120: Ingredients | C120: Quantity | D120: Unit | E120: Cost Price | F120: Total Price | H120: Ingredients | I120: Quantity | J120: Unit | K120: Cost Price | L120: Total Price
B121: Double Espresso | C121: =8+(18*0.025) -> 8.45 | D121: Gm | E121: =INGREDIENTS!F11 -> 0.07 | F121: =E121*C121 -> 0.5915 | H121: Double Espresso | I121: =8+(18*0.025) -> 8.45 | J121: Gm | K121: =INGREDIENTS!F11 -> 0.07 | L121: =K121*I121 -> 0.5915
B122: Condence Milk | C122: 10 | D122: ml | E122: =INGREDIENTS!F120 -> 0.011 | F122: =E122*C122 -> 0.11 | H122: Condence Milk | I122: 10 | J122: ml | K122: =INGREDIENTS!F120 -> 0.011 | L122: =K122*I122 -> 0.11
B123: Avoporated Milk | C123: 10 | D123: ml | E123: =INGREDIENTS!F119 -> 0.011 | F123: =E123*C123 -> 0.11 | H123: Avoporated Milk | I123: 10 | J123: ml | K123: =INGREDIENTS!F119 -> 0.011 | L123: =K123*I123 -> 0.11
B124: Fresh Milk | C124: 100 | D124: ml | E124: =INGREDIENTS!F38 -> 0.01426 | F124: =E124*C124 -> 1.426 | H124: Fresh Milk | I124: 100 | J124: ml | K124: =INGREDIENTS!F38 -> 0.01426 | L124: =K124*I124 -> 1.426
B125: 12oz ice Cup | C125: 1 | D125: pcs | E125: =INGREDIENTS!F21 -> 0.27 | F125: =E125*C125 -> 0.27 | H125: 16oz ICED Cup | I125: 1 | J125: pcs | K125: =INGREDIENTS!F26 -> 0.29 | L125: =K125*I125 -> 0.29
B126: 12oz ice Cup Lids | C126: 1 | D126: pcs | E126: =INGREDIENTS!F22 -> 0.115 | F126: =E126*C126 -> 0.115 | H126: 16oz ICED Cup Lids | I126: 1 | J126: pcs | K126: =INGREDIENTS!F27 -> 0.15 | L126: =K126*I126 -> 0.15
B127: Straw | C127: 1 | D127: pcs | E127: =INGREDIENTS!F28 -> 0.058 | F127: =E127*C127 -> 0.058 | H127: Straw | I127: 1 | J127: pcs | K127: =INGREDIENTS!F28 -> 0.058 | L127: =K127*I127 -> 0.058
F129: =SUM(F121:F128) -> 2.6805 | L129: =SUM(L121:L128) -> 2.7355
B130: Selling Price | C130: 12 | H130: Selling Price | I130: 16
B131: Cost Price | C131: =F129+5% -> 2.7305 | D131: =C131/C130 -> 0.22754167 | H131: Cost Price | I131: =L129+5% -> 2.7855 | J131: =I131/I130 -> 0.17409375
B132: Profit | C132: =C130-C131 -> 9.2695 | H132: Profit | I132: =I130-I131 -> 13.2145
B135: Lemon Ice brew | H135: Lemon Ice brew
B136: Ingredients | C136: Quantity | D136: Unit | E136: Cost Price | F136: Total Price | H136: Ingredients | I136: Quantity | J136: Unit | K136: Cost Price | L136: Total Price
...

Sheet KITCHEN Prep Cards
B3: CHCOLATE SYRUP BATCH
B5: Ingredients | C5: Quantity | D5: Unit | E5: Cost Price | F5: Total Price
B6: Chocolate Powder | C6: 200 | D6: gm | E6: =50/1000 -> 0.05 | F6: =E6*C6 -> 10
B7: Cocoa Powder | C7: 300 | D7: gm | E7: =INGREDIENTS!F169 -> 0.07 | F7: =E7*C7 -> 21
B8: White Sugar | C8: 150 | D8: gm | E8: =INGREDIENTS!F164 -> 0.0048 | F8: =E8*C8 -> 0.72
B9: Water | C9: 1000 | D9: ml | E9: 0 | F9: =E9*C9 -> 0
B11: Total Production Yield | C11: =SUM(C6:C10) -> 1650 | F11: =SUM(F6:F10) -> 31.72
B12: Cost Per gm | C12: =F11/C11 -> 0.019224242
B15: COLD BREW BATCH
B17: Ingredients | C17: Quantity | D17: Unit | E17: Cost Price | F17: Total Price
B18: Coffee Ground | C18: 230 | D18: gm | E18: =INGREDIENTS!F11 -> 0.07 | F18: =E18*C18 -> 16.1
B19: Filter Water | C19: 3500 | D19: gm | E19: 0 | F19: =E19*C19 -> 0
B23: Total Production Yield | C23: 3500 | F23: =SUM(F18:F22) -> 16.1
B24: Production Per Ml | C24: =F23/C23 -> 0.0046
B27: Chilli Mayo Sauce
B29: Ingredients | C29: Quantity | D29: Unit | E29: Cost Price | F29: Total Price
B30: Mayonese | C30: 800 | D30: gm | E30: =INGREDIENTS!F109 -> 0.02 | F30: =E30*C30 -> 16
B31: Chilli Sauce | C31: 200 | D31: gm | E31: =INGREDIENTS!F138 -> 0.013819444 | F31: =E31*C31 -> 2.7638889
B32: Chilli Flakes | C32: 30 | D32: gm | E32: =INGREDIENTS!F124 -> 0.0048 | F32: =E32*C32 -> 0.144
B33: Sunflower Oil | C33: 10 | D33: ml | E33: =INGREDIENTS!F131 -> 0.010571429 | F33: =E33*C33 -> 0.10571429
B35: Total Production Yield | C35: 1000 | F35: =SUM(F30:F34) -> 19.013603
B36: Production Per Gm | C36: =F35/C35 -> 0.019013603
B39: Pesto Sauce
B41: Ingredients | C41: Quantity | D41: Unit | E41: Cost Price | F41: Total Price
B42: Parmesan cheese | C42: 30 | D42: gm | E42: =INGREDIENTS!F93 -> 0.07 | F42: =E42*C42 -> 2.1
B43: Almond | C43: 120 | D43: gm | E43: =INGREDIENTS!F158 -> 0.06 | F43: =E43*C43 -> 7.2
B44: Basil Leaf | C44: 100 | D44: gm | E44: =INGREDIENTS!F136 -> 0.086 | F44: =E44*C44 -> 8.6
B45: Garlic | C45: 30 | D45: gm | E45: =INGREDIENTS!F123 -> 0.01 | F45: =E45*C45 -> 0.3
B46: Salt | C46: 3 | D46: gm | E46: =INGREDIENTS!F133 -> 0.01 | F46: =E46*C46 -> 0.03
B47: Sunflower Oil | C47: 200 | D47: ml | E47: =INGREDIENTS!F131 -> 0.010571429 | F47: =E47*C47 -> 2.1142857
B48: Lemon Juice | C48: 10 | D48: ml | E48: =INGREDIENTS!F108 -> 0.0095 | F48: =E48*C48 -> 0.095
B49: Total Production Yield | C49: 400 | F49: =SUM(F42:F48) -> 20.439286
B50: Production Per Gm | C50: =F49/C49 -> 0.051098214
B53: Tomato Sauce
B55: Ingredients | C55: Quantity | D55: Unit | E55: Cost Price | F55: Total Price
B56: Fresh Tomato | C56: 250 | D56: gm | E56: =INGREDIENTS!F117 -> 0.0045 | F56: =E56*C56 -> 1.125
B57: Tomato Pest | C57: 125 | D57: gm | E57: =INGREDIENTS!F88 -> 0.0188 | F57: =E57*C57 -> 2.35
B58: Red Onion | C58: 120 | D58: gm | E58: =INGREDIENTS!F110 -> 0.0035 | F58: =E58*C58 -> 0.42
B59: Garlic | C59: 30 | D59: gm | E59: =INGREDIENTS!F123 -> 0.01 | F59: =E59*C59 -> 0.3
B60: Salt | C60: 10 | D60: gm | E60: =INGREDIENTS!F133 -> 0.01 | F60: =E60*C60 -> 0.1
B61: Brown Sugar | C61: 10 | D61: gm | E61: =INGREDIENTS!F165 -> 0.064 | F61: =E61*C61 -> 0.64
B62: Oregano | C62: 20 | D62: gm | E62: =INGREDIENTS!F89 -> 0.22 | F62: =E62*C62 -> 4.4
B63: Black Pepper | C63: 10 | D63: gm | E63: =INGREDIENTS!F91 -> 0.076 | F63: =E63*C63 -> 0.76
B64: Chilli Flakes | C64: 10 | D64: gm | E64: =INGREDIENTS!F124 -> 0.0048 | F64: =E64*C64 -> 0.048
B65: Tabasco Sauce | C65: 3 | D65: gm | E65: =INGREDIENTS!F130 -> 0.049 | F65: =E65*C65 -> 0.147
B66: Hot Water | C66: 1 | D66: L | E66: =0 -> 0 | F66: =E66*C66 -> 0
B67: Total Production Yield | C67: 1000 | F67: =SUM(F56:F66) -> 10.29
B68: Production Per Gm | C68: =F67/C67 -> 0.01029
B71: Mixed Berry Jam
B73: Ingredients | C73: Quantity | D73: Unit | E73: Cost Price | F73: Total Price
B74: Blackberry | C74: 500 | D74: gm | E74: =INGREDIENTS!#REF! -> #REF! | F74: =E74*C74 -> #REF!
B75: Blueberry | C75: 500 | D75: gm | E75: =INGREDIENTS!#REF! -> #REF! | F75: =E75*C75 -> #REF!
B76: Honey | C76: 60 | D76: ml | E76: =INGREDIENTS!$F$132 -> 0.016 | F76: =E76*C76 -> 0.96
B77: White Sugar | C77: 150 | D77: gm | E77: =INGREDIENTS!$F$164 -> 0.0048 | F77: =E77*C77 -> 0.72
B78: Lemon Juice | C78: 50 | D78: ml | E78: =INGREDIENTS!$F$108 -> 0.0095 | F78: =E78*C78 -> 0.475
B79: Salt | C79: 2 | D79: gm | E79: =INGREDIENTS!$F$133 -> 0.01 | F79: =E79*C79 -> 0.02
E80: 0 | F80: =E80*C80 -> 0
E81: 0 | F81: =E81*C81 -> 0
E82: 0 | F82: =E82*C82 -> 0
E83: 0 | F83: =E83*C83 -> 0
E84: =0 -> 0 | F84: =E84*C84 -> 0
B85: Total Production Yield | C85: 660
B86: Serving Per Portion | C86: =C85/15 -> 44
E88: Batch Cost: | F88: =SUM(F74:F83) -> #REF!
C89: Yield | D89: Sell Price | E89: COGS | F89: Batch Profit
C90: =C85/10 -> 66 | D90: 1.5 | E90: =F88/F90 -> #REF! | F90: =(C90*D90)-F88 -> #REF!
C91: =C85/15 -> 44 | D91: 1.5 | E91: =F88/F91 -> #REF! | F91: =(C91*D91)-F88 -> #REF!
C92: =C85/20 -> 33 | D92: 1.5 | E92: =F88/F92 -> #REF! | F92: =(C92*D92)-F88 -> #REF!
B95: Overnight Oats
B97: Ingredients | C97: Quantity | D97: Unit | E97: Cost Price | F97: Total Price
F98: =E98*C98 -> 0
F99: =E99*C99 -> 0
F100: =E100*C100 -> 0
F101: =E101*C101 -> 0
F102: =E102*C102 -> 0
F103: =E103*C103 -> 0
F104: =E104*C104 -> 0
F105: =E105*C105 -> 0
F106: =E106*C106 -> 0
F107: =SUM(F98:F106) -> 0
B108: Selling Price | C108: 18
B109: Cost Price | C109: =F107 -> 0 | D109: =C109/C108 -> 0
B110: Profit | C110: =C108-C109 -> 18
B113: Home Made Muesli
B115: Ingredients | C115: Quantity | D115: Unit | E115: Cost Price | F115: Total Price
F116: =E116*C116 -> 0
F117: =E117*C117 -> 0
F118: =E118*C118 -> 0
F119: =E119*C119 -> 0
F120: =E120*C120 -> 0
F121: =E121*C121 -> 0
F122: =E122*C122 -> 0
F123: =E123*C123 -> 0
F124: =E124*C124 -> 0
F125: =SUM(F116:F124) -> 0
B126: Selling Price | C126: 0
B127: Cost Price | C127: =F125 -> 0 | D127: =C127/C126 -> #DIV/0!
B128: Profit | C128: =C126-C127 -> 0
B131: Coconut & Cacao Granola
B133: Ingredients | C133: Quantity | D133: Unit | E133: Cost Price | F133: Total Price
...

Sheet SERVE Cards
B3: Cheese Toastie (white)
B5: Ingredients | C5: Quantity | D5: Unit | E5: Cost Price | F5: Total Price
B6: White Bread | C6: 1 | D6: portion | E6: =INGREDIENTS!$F$288 -> 0.62857143 | F6: =E6*C6 -> 0.62857143
B7: Cheese | C7: 1 | D7: slice | E7: =INGREDIENTS!$F$51 -> 0.41428571 | F7: =E7*C7 -> 0.41428571
B8: Palm Oil | F8: =E8*C8 -> 0
B9: Packaging | C9: 1 | E9: 0.25 | F9: =E9*C9 -> 0.25
F10: =E10*C10 -> 0
F11: =E11*C11 -> 0
F12: =E12*C12 -> 0
F13: =E13*C13 -> 0
F14: =E14*C14 -> 0
F15: =SUM(F6:F14) -> 1.2928571
B16: Selling Price | C16: 5.9
B17: Cost Price | C17: =F15 -> 1.2928571 | D17: =C17/C16 -> 0.21912833
B18: Profit | C18: =C16-C17 -> 4.6071429
B21: Tomato/Cheese Toastie (white)
B23: Ingredients | C23: Quantity | D23: Unit | E23: Cost Price | F23: Total Price
B24: White Bread | C24: 1 | D24: portion | E24: =INGREDIENTS!$F$288 -> 0.62857143 | F24: =E24*C24 -> 0.62857143
B25: Cheese | C25: 1 | D25: slice | E25: =INGREDIENTS!$F$51 -> 0.41428571 | F25: =E25*C25 -> 0.41428571
B26: Tomato | C26: 50 | D26: gram | E26: =INGREDIENTS!$F$117 -> 0.0045 | F26: =E26*C26 -> 0.225
B27: Palm Oil | F27: =E27*C27 -> 0
F28: =E28*C28 -> 0
B29: Packaging | C29: 1 | E29: 0.25 | F29: =E29*C29 -> 0.25
F30: =E30*C30 -> 0
F31: =E31*C31 -> 0
F32: =E32*C32 -> 0
F33: =SUM(F24:F32) -> 1.5178571
B34: Selling Price | C34: 6.9
B35: Cost Price | C35: =F33 -> 1.5178571 | D35: =C35/C34 -> 0.2199793
B36: Profit | C36: =C34-C35 -> 5.3821429
B39: Ham/Cheese Toastie (white)
B41: Ingredients | C41: Quantity | D41: Unit | E41: Cost Price | F41: Total Price
B42: White Bread | C42: 1 | D42: portion | E42: =INGREDIENTS!$F$288 -> 0.62857143 | F42: =E42*C42 -> 0.62857143
B43: Cheese | C43: 1 | D43: slice | E43: =INGREDIENTS!$F$51 -> 0.41428571 | F43: =E43*C43 -> 0.41428571
B44: Chicken Ham | C44: 1 | D44: each | E44: =INGREDIENTS!$F$50 -> 0.65333333 | F44: =E44*C44 -> 0.65333333
B45: Palm Oil | F45: =E45*C45 -> 0
F46: =E46*C46 -> 0
B47: Packaging | C47: 1 | E47: 0.25 | F47: =E47*C47 -> 0.25
F48: =E48*C48 -> 0
F49: =E49*C49 -> 0
F50: =E50*C50 -> 0
F51: =SUM(F42:F50) -> 1.9461905
B52: Selling Price | C52: 7.9
B53: Cost Price | C53: =F51 -> 1.9461905 | D53: =C53/C52 -> 0.24635322
B54: Profit | C54: =C52-C53 -> 5.9538095
B57: Ham/Cheese/Tomato Toastie (white)
B59: Ingredients | C59: Quantity | D59: Unit | E59: Cost Price | F59: Total Price
B60: White Bread | C60: 1 | D60: portion | E60: =INGREDIENTS!$F$288 -> 0.62857143 | F60: =E60*C60 -> 0.62857143
B61: Cheese | C61: 1 | D61: slice | E61: =INGREDIENTS!$F$51 -> 0.41428571 | F61: =E61*C61 -> 0.41428571
B62: Tomato | C62: 50 | D62: gram | E62: =INGREDIENTS!$F$117 -> 0.0045 | F62: =E62*C62 -> 0.225
B63: Chicken Ham | C63: 1 | D63: each | E63: =INGREDIENTS!$F$50 -> 0.65333333 | F63: =E63*C63 -> 0.65333333
B64: Palm Oil | F64: =E64*C64 -> 0
F65: =E65*C65 -> 0
B66: Packaging | C66: 1 | E66: 0.25 | F66: =E66*C66 -> 0.25
F67: =E67*C67 -> 0
F68: =E68*C68 -> 0
F69: =SUM(F60:F68) -> 2.1711905
B70: Selling Price | C70: 8.9
B71: Cost Price | C71: =F69 -> 2.1711905 | D71: =C71/C70 -> 0.24395399
B72: Profit | C72: =C70-C71 -> 6.7288095
B75: Overnight Oats - ELVIS
B77: Ingredients | C77: Quantity | D77: Unit | E77: Cost Price | F77: Total Price
B78: Rolled Oats | C78: 50 | D78: grams | F78: =E78*C78 -> 0
B79: Chia Seeds | C79: 5 | D79: grams | F79: =E79*C79 -> 0
B80: Greek Yogurt | C80: 50 | D80: grams | F80: =E80*C80 -> 0
B81: Milk | C81: 120 | D81: mls | F81: =E81*C81 -> 0
B82: Peanut Butter | D82: grams | F82: =E82*C82 -> 0
B83: Berry Jam | D83: grams | F83: =E83*C83 -> 0
F84: =E84*C84 -> 0
F85: =E85*C85 -> 0
B86: Packaging | C86: 1 | E86: 3.5 | F86: =E86*C86 -> 3.5
F87: =SUM(F78:F86) -> 3.5
B88: Selling Price | C88: 9.5
B89: Cost Price | C89: =F87 -> 3.5 | D89: =C89/C88 -> 0.36842105
B90: Profit | C90: =C88-C89 -> 6
B93: Overnight Oats - APPLE PIE
B95: Ingredients | C95: Quantity | D95: Unit | E95: Cost Price | F95: Total Price
B96: Rolled Oats | C96: 50 | D96: grams | F96: =E96*C96 -> 0
B97: Chia Seeds | C97: 5 | D97: grams | F97: =E97*C97 -> 0
B98: Greek Yogurt | C98: 50 | D98: grams | F98: =E98*C98 -> 0
B99: Milk | C99: 120 | D99: mls | F99: =E99*C99 -> 0
B100: Cinnamon Apples | F100: =E100*C100 -> 0
F101: =E101*C101 -> 0
F102: =E102*C102 -> 0
F103: =E103*C103 -> 0
B104: Packaging | C104: 1 | E104: 3.5 | F104: =E104*C104 -> 3.5
F105: =SUM(F96:F104) -> 3.5
B106: Selling Price | C106: 9.5
B107: Cost Price | C107: =F105 -> 3.5 | D107: =C107/C106 -> 0.36842105
B108: Profit | C108: =C106-C107 -> 6
B111: Overnight Oats - TIRAMISU
B113: Ingredients | C113: Quantity | D113: Unit | E113: Cost Price | F113: Total Price
B114: Rolled Oats | C114: 50 | D114: grams | F114: =E114*C114 -> 0
B115: Chia Seeds | C115: 5 | D115: grams | F115: =E115*C115 -> 0
B116: Greek Yogurt | C116: 50 | D116: grams | F116: =E116*C116 -> 0
B117: Milk | C117: 120 | D117: mls | F117: =E117*C117 -> 0
B118: Premade Espresso | C118: 20 | D118: grams | F118: =E118*C118 -> 0
B119: Cocoa Powder | C119: 5 | D119: grams | F119: =E119*C119 -> 0
B120: Vanila Syrup | C120: 20 | D120: mls | F120: =E120*C120 -> 0
F121: =E121*C121 -> 0
...

Sheet meals 1
B2: SCRAMBLE EGGS HAM ON TOAST
B4: Ingredients | C4: Quantity | D4: Unit | E4: Cost Price | F4: Total Price
B5: Chicken Ham | C5: 1 | D5: pcs | E5: =INGREDIENTS!$F$50 -> 0.65333333 | F5: =E5*C5 -> 0.65333333
B6: Bega Cheese | C6: 1 | D6: pcs | E6: =INGREDIENTS!$F$51 -> 0.41428571 | F6: =E6*C6 -> 0.41428571
B7: Egg | C7: 3 | D7: pcs | E7: =INGREDIENTS!$F$112 -> 0.53 | F7: =E7*C7 -> 1.59
B8: Fresh Milk | C8: 20 | D8: gm | E8: =INGREDIENTS!$F$38 -> 0.01426 | F8: =E8*C8 -> 0.2852
B9: Bread | C9: 1 | D9: pcs | E9: =INGREDIENTS!$F$77 -> 2.2857143 | F9: =E9*C9 -> 2.2857143
B10: Salt | C10: 1 | D10: gm | E10: =INGREDIENTS!F133 -> 0.01 | F10: =E10*C10 -> 0.01
B11: Black Pepper | C11: 1 | D11: gm | E11: =INGREDIENTS!F91 -> 0.076 | F11: =E11*C11 -> 0.076
B12: Sunflower Oil | C12: 15 | D12: ml | E12: =INGREDIENTS!F131 -> 0.010571429 | F12: =E12*C12 -> 0.15857143
F14: =SUM(F5:F13) -> 5.4731048
B15: Selling Price | C15: 18
B16: Cost Price | C16: =F14+5% -> 5.5231048 | D16: =C16/C15 -> 0.30683915
B17: Profit | C17: =C15-C16 -> 12.476895
B20: HAM & CHEESE OMLETTE
B22: Ingredients | C22: Quantity | D22: Unit | E22: Cost Price | F22: Total Price
B23: Bega Cheese | C23: 1 | D23: pcs | E23: =INGREDIENTS!$F$51 -> 0.41428571 | F23: =E23*C23 -> 0.41428571
B24: Egg | C24: 3 | D24: pcs | E24: =INGREDIENTS!$F$112 -> 0.53 | F24: =E24*C24 -> 1.59
B25: Bread | C25: 0.5 | D25: pcs | E25: =INGREDIENTS!$F$77 -> 2.2857143 | F25: =E25*C25 -> 1.1428571
B26: Chicken Ham | C26: 2 | D26: pcs | E26: =INGREDIENTS!$F$50 -> 0.65333333 | F26: =E26*C26 -> 1.3066667
B27: Onion | C27: 5 | D27: gm | E27: =INGREDIENTS!F110 -> 0.0035 | F27: =E27*C27 -> 0.0175
B28: Green Chilli Padi | C28: 5 | D28: gm | E28: =INGREDIENTS!F127 -> 0.013 | F28: =E28*C28 -> 0.065
B29: Salt | C29: 1 | D29: gm | E29: =INGREDIENTS!$F$133 -> 0.01 | F29: =E29*C29 -> 0.01
B30: Black Pepper | C30: 1 | D30: gm | E30: =INGREDIENTS!$F$115 -> 0.0043 | F30: =E30*C30 -> 0.0043
B31: Sunflower Oil | C31: 15 | D31: ml | E31: =INGREDIENTS!$F$131 -> 0.010571429 | F31: =E31*C31 -> 0.15857143
F32: =SUM(F23:F31) -> 4.709181
B33: Selling Price | C33: 18
B34: Cost Price | C34: =F32+5% -> 4.759181 | D34: =C34/C33 -> 0.26439894
B35: Profit | C35: =C33-C34 -> 13.240819
B38: MUSHROOM & CHEESE OMLETTE
B40: Ingredients | C40: Quantity | D40: Unit | E40: Cost Price | F40: Total Price
B41: Bega Cheese | C41: 1 | D41: pcs | E41: =INGREDIENTS!F51 -> 0.41428571 | F41: =E41*C41 -> 0.41428571
B42: Egg | C42: 3 | D42: pcs | E42: =INGREDIENTS!$F$112 -> 0.53 | F42: =E42*C42 -> 1.59
B43: Bread | C43: 0.5 | D43: pcs | E43: =INGREDIENTS!$F$77 -> 2.2857143 | F43: =E43*C43 -> 1.1428571
B44: Oyster Mushroom | C44: 80 | D44: gm | E44: =INGREDIENTS!F128 -> 0.019 | F44: =E44*C44 -> 1.52
B45: Green Chilli Padi | C45: 0 | D45: gm | E45: =INGREDIENTS!F163 -> 0.0508 | F45: =E45*C45 -> 0
B46: Red Onion | C46: 0 | D46: gm | E46: =INGREDIENTS!F127 -> 0.013 | F46: =E46*C46 -> 0
B47: Salt | C47: 1 | D47: gm | E47: =INGREDIENTS!$F$133 -> 0.01 | F47: =E47*C47 -> 0.01
B48: Black Pepper | C48: 1 | D48: gm | E48: =INGREDIENTS!$F$115 -> 0.0043 | F48: =E48*C48 -> 0.0043
B49: Sunflower Oil | C49: 15 | D49: ml | E49: =INGREDIENTS!$F$131 -> 0.010571429 | F49: =E49*C49 -> 0.15857143
F50: =SUM(F41:F49) -> 4.8400143
B51: Selling Price | C51: 18
B52: Cost Price | C52: =F50+5% -> 4.8900143 | D52: =C52/C51 -> 0.27166746
B53: Profit | C53: =C51-C52 -> 13.109986
B56: Carbonara
B58: Ingredients | C58: Quantity | D58: Unit | E58: Cost Price | F58: Total Price
B59: Spaghetti | C59: 130 | D59: gm | E59: =INGREDIENTS!F122 -> 0.012 | F59: =E59*C59 -> 1.56
B60: Mushroom | C60: 50 | D60: gm | E60: =INGREDIENTS!F128 -> 0.019 | F60: =E60*C60 -> 0.95
B61: WhippING Cream | C61: 60 | D61: gm | E61: =INGREDIENTS!F90 -> 0.026 | F61: =E61*C61 -> 1.56
B62: Egg Yolk | C62: 1 | D62: pcs | E62: =INGREDIENTS!F112 -> 0.53 | F62: =E62*C62 -> 0.53 | G62: FREEZED MENU FOR NOW
B63: Chicken ham | C63: 1 | D63: slice | E63: =INGREDIENTS!F50 -> 0.65333333 | F63: =E63*C63 -> 0.65333333
B64: Salt | C64: 2 | D64: gm | E64: =INGREDIENTS!F133 -> 0.01 | F64: =E64*C64 -> 0.02
B65: Black Peper | C65: 2 | D65: gm | E65: =INGREDIENTS!F91 -> 0.076 | F65: =E65*C65 -> 0.152
F67: =SUM(F59:F66) -> 5.4253333
B68: Selling Price | C68: 18
B69: Cost Price | C69: =F67+5% -> 5.4753333 | D69: =C69/C68 -> 0.30418519
B70: Profit | C70: =C68-C69 -> 12.524667
B73: Cookies combo
B75: Ingredients | C75: Quantity | D75: Unit | E75: Cost Price | F75: Total Price
B76: Any Cookie | C76: 1 | D76: pcs | E76: =INGREDIENTS!$F$149 -> 7.5 | F76: =E76*C76 -> 7.5
B77: Satchel Paper Bag-white | C77: 1 | D77: pcs | E77: =INGREDIENTS!$F$25 -> 0.054 | F77: =E77*C77 -> 0.054
B78: Combo Drinks | C78: 1 | D78: cup | E78: 4.05 | F78: =E78*C78 -> 4.05
F85: =SUM(F76:F84) -> 11.604
B86: Selling Price | C86: 18
B87: Cost Price | C87: =F85+5% -> 11.654 | D87: =C87/C86 -> 0.64744444
B88: Profit | C88: =C86-C87 -> 6.346
B91: Cakes Cambo
B93: Ingredients | C93: Quantity | D93: Unit | E93: Cost Price | F93: Total Price
B94: Any Cake | C94: 1 | D94: pcs | E94: =INGREDIENTS!$F$78 -> 4.25 | F94: =E94*C94 -> 4.25
B95: Satchel Paper Bag-white | C95: 1 | D95: pcs | E95: =INGREDIENTS!$F$25 -> 0.054 | F95: =E95*C95 -> 0.054
B96: Combo Drinks | C96: 1 | D96: cup | E96: 4.05 | F96: =E96*C96 -> 4.05
F103: =SUM(F94:F102) -> 8.354
B104: Selling Price | C104: 18
B105: Cost Price | C105: =F103+5% -> 8.404 | D105: =C105/C104 -> 0.46688889
B106: Profit | C106: =C104-C105 -> 9.596

Sheet meals 2
B21: Home Made Apricot Muesli
B23: Ingredients | C23: Quantity | D23: Unit | E23: Cost Price | F23: Total Price
B24: Rolled Oats | C24: 500 | D24: grams | F24: =E24*C24 -> 0
B25: Shredded Coconut | C25: 80 | D25: grams | F25: =E25*C25 -> 0
B26: Sesame Seeds | C26: 50 | D26: grams | F26: =E26*C26 -> 0
B27: Cashews | C27: 120 | D27: grams | F27: =E27*C27 -> 0
B28: Slivered Almonds | C28: 50 | D28: grams | F28: =E28*C28 -> 0
B29: Dried Apricot | C29: 150 | D29: grams | F29: =E29*C29 -> 0
B30: Dried Cranberry | C30: 50 | D30: grams | F30: =E30*C30 -> 0
F31: =E31*C31 -> 0
F32: =E32*C32 -> 0
F33: =SUM(F24:F32) -> 0
B34: Selling Price | C34: 18
B35: Cost Price | C35: =F33 -> 0 | D35: =C35/C34 -> 0
B36: Profit | C36: =C34-C35 -> 18
B38: Cacao & Coconut Granola
B40: Ingredients | C40: Quantity | D40: Unit | E40: Cost Price | F40: Total Price
B41: House Made Granola | F41: =E41*C41 -> 0
F42: =E42*C42 -> 0
F43: =E43*C43 -> 0
F44: =E44*C44 -> 0
F45: =E45*C45 -> 0
F46: =E46*C46 -> 0
F47: =E47*C47 -> 0
F48: =E48*C48 -> 0
F49: =E49*C49 -> 0
F50: =SUM(F41:F49) -> 0
B51: Selling Price | C51: 18
B52: Cost Price | C52: =F50 -> 0 | D52: =C52/C51 -> 0
B53: Profit | C53: =C51-C52 -> 18
B55: Eggs on Toast
B57: Ingredients | C57: Quantity | D57: Unit | E57: Cost Price | F57: Total Price
B58: Eggs | C58: 2 | D58: each | F58: =E58*C58 -> 0
B59: Sourdough | C59: 2 | D59: slice | F59: =E59*C59 -> 0
F60: =E60*C60 -> 0
F61: =E61*C61 -> 0
F62: =E62*C62 -> 0
F63: =E63*C63 -> 0
F64: =E64*C64 -> 0
F65: =E65*C65 -> 0
F66: =E66*C66 -> 0
F67: =SUM(F58:F66) -> 0
B68: Selling Price | C68: 18
B69: Cost Price | C69: =F67 -> 0 | D69: =C69/C68 -> 0
B70: Profit | C70: =C68-C69 -> 18
B74: Chicken Ham Frittata
B76: Ingredients | C76: Quantity | D76: Unit | E76: Cost Price | F76: Total Price
B77: Egg | C77: 4 | D77: pcs | E77: =INGREDIENTS!F112 -> 0.53 | F77: =E77*C77 -> 2.12
B78: Ham | C78: 2 | D78: slice | E78: =INGREDIENTS!F50 -> 0.65333333 | F78: =E78*C78 -> 1.3066667
B79: Bega Cheese | C79: 1 | D79: pcs | E79: =INGREDIENTS!F51 -> 0.41428571 | F79: =E79*C79 -> 0.41428571
B80: Tomato | C80: 30 | D80: gm | E80: =INGREDIENTS!F117 -> 0.0045 | F80: =E80*C80 -> 0.135
B81: Sunflower oil | C81: 15 | D81: ml | E81: =INGREDIENTS!F131 -> 0.010571429 | F81: =E81*C81 -> 0.15857143
B82: Salt | C82: 1 | D82: gm | E82: =INGREDIENTS!F133 -> 0.01 | F82: =E82*C82 -> 0.01
B83: Black Papper | C83: 1 | D83: gm | E83: =INGREDIENTS!F94 -> 0.076 | F83: =E83*C83 -> 0.076
B84: Origano | C84: 1 | D84: gm | E84: =INGREDIENTS!F145 -> 0.0196 | F84: =E84*C84 -> 0.0196
F85: =E85*C85 -> 0
F86: =SUM(F77:F85) -> 4.2401238
B87: Selling Price | C87: 18
B88: Cost Price | C88: 4.24 | D88: =C88/C87 -> 0.23555556
B89: Profit | C89: =C87-C88 -> 13.76
B94: Mushroom Soup | H94: Pumpkin Soup
B96: Ingredients | C96: Quantity | D96: Unit | E96: Cost Price | F96: Total Price | H96: Ingredients | I96: Quantity | J96: Unit | K96: Cost Price | L96: Total Price
B97: Button Mushroom | C97: 600 | D97: gm | E97: =INGREDIENTS!F144 -> 0.028 | F97: =E97*C97 -> 16.8 | H97: Pumpkin | I97: 1000 | J97: kg | K97: =INGREDIENTS!F142 -> 0.0043 | L97: =K97*I97 -> 4.3
B98: Milk | C98: 500 | D98: ml | E98: =INGREDIENTS!F38 -> 0.01426 | F98: =E98*C98 -> 7.13 | H98: Sunflower Oil | I98: 90 | J98: ml | K98: =INGREDIENTS!F131 -> 0.010571429 | L98: =K98*I98 -> 0.95142857
B99: Cream | C99: 100 | D99: ml | E99: =INGREDIENTS!F53 -> 0.0212 | F99: =E99*C99 -> 2.12 | H99: Thyme Leaf | I99: 15 | J99: gm | K99: =INGREDIENTS!F143 -> 0.021 | L99: =K99*I99 -> 0.315
B100: Self Flour | C100: 50 | D100: gm | E100: =INGREDIENTS!F101 -> 0.0045 | F100: =E100*C100 -> 0.225 | H100: Salt | I100: 10 | J100: gm | K100: =INGREDIENTS!F133 -> 0.01 | L100: =K100*I100 -> 0.1
B101: Salt | C101: 5 | D101: gm | E101: =INGREDIENTS!F133 -> 0.01 | F101: =E101*C101 -> 0.05 | H101: Black Papper fine | I101: 15 | J101: gm | K101: =INGREDIENTS!F91 -> 0.076 | L101: =K101*I101 -> 1.14
B102: Thyme leaf | C102: 2 | D102: gm | E102: =INGREDIENTS!F143 -> 0.021 | F102: =E102*C102 -> 0.042 | H102: Fresh Milk | I102: 200 | J102: ml | K102: =INGREDIENTS!F38 -> 0.01426 | L102: =K102*I102 -> 2.852
B103: Black Pepper | C103: 3 | D103: gm | E103: =INGREDIENTS!F94 -> 0.076 | F103: =E103*C103 -> 0.228 | H103: Whipping Cream | I103: 100 | J103: ml | K103: =INGREDIENTS!F53 -> 0.0212 | L103: =K103*I103 -> 2.12
B104: Water | C104: 700 | D104: ml | E104: 0 | F104: =E104*C104 -> 0 | H104: Water | I104: 500 | J104: ml | K104: 0 | L104: =K104*I104 -> 0
E105: 0 | F105: =E105*C105 -> 0 | K105: 0 | L105: =K105*I105 -> 0
E106: 0 | F106: =E106*C106 -> 0 | K106: 0 | L106: =K106*I106 -> 0
E107: =0 -> 0 | F107: =E107*C107 -> 0 | K107: =0 -> 0 | L107: =K107*I107 -> 0
B108: Total Production Yield | C108: 1600 | H108: Total Production Yield | I108: 1375
B109: Per Serving | C109: 150 | H109: Per Serving | I109: 150
E111: Batch Cost: | F111: =SUM(F97:F107) -> 26.595 | K111: Batch Cost: | L111: =SUM(L97:L106) -> 11.778429
C112: Yield | D112: Sell Price | E112: COGS | F112: Batch Profit | I112: Yield | J112: Sell Price | K112: COGS | L112: Batch Profit
C113: 10 | D113: 18 | E113: =F111/F113 -> 0.17336462 | F113: =(C113*D113)-F111 -> 153.405 | I113: 9 | J113: 15 | K113: =L111/L113 -> 0.095587391 | L113: =(I113*J113)-L111 -> 123.22157
C114: 20 | D114: 18 | E114: =F111/F114 -> 0.07976785 | F114: =(C114*D114)-F111 -> 333.405 | I114: 18 | J114: 15 | K114: =L111/L114 -> 0.045613651 | L114: =(I114*J114)-L111 -> 258.22157
C115: 30 | D115: 18 | E115: =F111/F115 -> 0.05180121 | F115: =(C115*D115)-F111 -> 513.405 | I115: 27 | J115: 15 | K115: =L111/L115 -> 0.029953668 | L115: =(I115*J115)-L111 -> 393.22157
B118: Salmon Omelette
B120: Ingredients | C120: Quantity | D120: Unit | E120: Cost Price | F120: Total Price
B121: Egg | C121: 4 | D121: pcs | E121: =INGREDIENTS!F112 -> 0.53 | F121: =E121*C121 -> 2.12
B122: Smoke Salmon | C122: 30 | D122: gm | E122: =INGREDIENTS!F102 -> 0.12 | F122: =E122*C122 -> 3.6
B123: Sunflower oil | C123: 15 | D123: ml | E123: =INGREDIENTS!F131 -> 0.010571429 | F123: =E123*C123 -> 0.15857143
B124: Salt | C124: 1 | D124: gm | E124: =INGREDIENTS!F133 -> 0.01 | F124: =E124*C124 -> 0.01
B125: Black Papper | C125: 1 | D125: gm | E125: =INGREDIENTS!F94 -> 0.076 | F125: =E125*C125 -> 0.076
F126: =E126*C126 -> 0
F127: =E127*C127 -> 0
F128: =SUM(F121:F127) -> 5.9645714
B129: Selling Price | C129: 18
B130: Cost Price | C130: =F128 -> 5.9645714 | D130: =C130/C129 -> 0.33136508
B131: Profit | C131: =C129-C130 -> 12.035429
B135: Salmon Frittata | H135: Mushroom Frittata
B137: Ingredients | C137: Quantity | D137: Unit | E137: Cost Price | F137: Total Price | H137: Ingredients | I137: Quantity | J137: Unit | K137: Cost Price | L137: Total Price
B138: Egg | C138: 4 | D138: pcs | E138: =INGREDIENTS!F112 -> 0.53 | F138: =E138*C138 -> 2.12 | H138: Egg | I138: 4 | J138: pcs | K138: =INGREDIENTS!F112 -> 0.53 | L138: =K138*I138 -> 2.12
B139: Smoke Salmon | C139: 30 | D139: gm | E139: =INGREDIENTS!F102 -> 0.12 | F139: =E139*C139 -> 3.6 | H139: Mushroom Oyester | I139: 60 | J139: gm | K139: =INGREDIENTS!F128 -> 0.019 | L139: =K139*I139 -> 1.14
B140: Bega Cheese | C140: 1 | D140: pcs | E140: =INGREDIENTS!F51 -> 0.41428571 | F140: =E140*C140 -> 0.41428571 | H140: Bega Cheese | I140: 1 | J140: pcs | K140: =INGREDIENTS!F51 -> 0.41428571 | L140: =K140*I140 -> 0.41428571
B141: Tomato | C141: 30 | D141: gm | E141: =INGREDIENTS!F117 -> 0.0045 | F141: =E141*C141 -> 0.135 | H141: Tomato | I141: 30 | J141: gm | K141: =INGREDIENTS!F117 -> 0.0045 | L141: =K141*I141 -> 0.135
B142: Sunflower oil | C142: 15 | D142: ml | E142: =INGREDIENTS!F131 -> 0.010571429 | F142: =E142*C142 -> 0.15857143 | H142: Sunflower oil | I142: 15 | J142: ml | K142: =INGREDIENTS!F131 -> 0.010571429 | L142: =K142*I142 -> 0.15857143
...

Sheet Brownie
B4: GF Dark Choc Walnut Brownie (fudge)
B6: Ingredients | E6: Quantity | F6: Unit | G6: COST
B7: Brown Sugar | E7: 0.36 | F7: KG | G7: =INGREDIENTS!$D$223*E7 -> 2.124
B8: Cocoa Powder | E8: 0.08 | F8: KG | G8: =INGREDIENTS!$D$251*E8 -> 3.992
B9: Almond Meal | E9: 0.06 | F9: KG | G9: =INGREDIENTS!$D$226*E9 -> 2.394
B10: Dark Chocolate Buttons | E10: 0.1 | F10: KG | G10: =INGREDIENTS!$D$252*E10 -> 10
B11: Hazelnuts (or Walnuts) | E11: 0.1 | F11: KG | G11: =INGREDIENTS!$D$227*E11 -> 3.59
B12: Unsalted Butter (melted) | E12: 0.25 | F12: KG | G12: =INGREDIENTS!$D$230*E12 -> 12.95
B13: Eggs | E13: 4 | F13: each | G13: =INGREDIENTS!#REF!*E13 -> #REF!
F14: Batch Cost: | G14: =SUM(G6:G13) -> #REF!
B15: Yield | E15: Sell Price | F15: COGS | G15: Batch Profit
B16: 16 | E16: 8 | F16: =G14/G16 -> #REF! | G16: =(B16*E16)-G14 -> #REF!
B17: 24 | E17: 5 | F17: =G14/G17 -> #REF! | G17: =(B17*E17)-G14 -> #REF!
B18: 30 | E18: 3.5 | F18: =G14/G18 -> #REF! | G18: =(B18*E18)-G14 -> #REF!
B27: GF White Chocolate Cranberry Brownie
B29: Ingredients | C29: Quantity | D29: Unit | E29: Quantity | F29: Unit | G29: COST
B30: 1 COMBINE;
B31: Unsalted Butter (melted) | C31: 125 | D31: GRAMS | E31: 0.125 | F31: KG | G31: =INGREDIENTS!$D$230*E31 -> 6.475
B32: Rice Bran Oil | C32: 125 | D32: MLS | E32: 0.125 | F32: LITRE | G32: =INGREDIENTS!#REF!*E32 -> #REF!
B33: Brown Sugar | C33: 150 | D33: GRAMS | E33: 0.15 | F33: KG | G33: =INGREDIENTS!$D$223*E33 -> 0.885
B34: Castor Sugar | C34: 150 | D34: GRAMS | E34: 0.15 | F34: KG | G34: =INGREDIENTS!$D$223*E34 -> 0.885
B35: 2 BEAT (2-3 mins);
B36: Eggs | C36: 4 | D36: EACH | E36: 4 | F36: each | G36: =INGREDIENTS!$F$112*E36 -> 2.12
B37: 3 SIFT;
B38: Cocoa Powder (regular) | C38: 80 | D38: GRAMS | E38: 0.08 | F38: KG | G38: =INGREDIENTS!$D$225*E38 -> 2.92
B39: Almond Meal | C39: 60 | D39: GRAMS | E39: 0.06 | F39: KG | G39: =INGREDIENTS!$D$226*E39 -> 2.394
B40: 4 COMBINE ALL PLUS:
B41: Desiccated Coconut | C41: 30 | D41: GRAMS | E41: 0.03 | F41: KG | G41: =INGREDIENTS!$D$228*E41 -> 0.297
B42: White Chocolate Buttons (compound) | C42: 80 | D42: GRAMS | E42: 0.08 | F42: KG | G42: =INGREDIENTS!$D$236*E42 -> 1.992
B43: Dried Cranberries | C43: 60 | D43: GRAMS | E43: 0.06 | F43: KG | G43: =INGREDIENTS!$D$229*E43 -> 1.494
C44: YIELD: | D44: 16
C45: PRICE: | D45: 10.9 | F45: Batch Cost: | G45: =SUM(G30:G44) -> #REF!
C46: COMBO (with any drink): | D46: 9.9
B47: Yield | E47: Sell Price | F47: COGS | G47: Batch Profit
B48: 16 | E48: 10.9 | F48: =G45/G48 -> #REF! | G48: =(B48*E48)-G45 -> #REF!
B49: 16 | E49: 9.9 | F49: =G45/G49 -> #REF! | G49: =(B49*E49)-G45 -> #REF!
B50: 16 | E50: 8.9 | F50: =G45/G50 -> #REF! | G50: =(B50*E50)-G45 -> #REF!
B55: OG recipe | I55: thin: unflavoured budget MYR3-4 each | N55: tall size: for flavoured premium MYR8-12 each
B57: Belgium Brownie (chewy) no AF | I57: Belgium Brownie (chewy) no AF | N57: 1.5 X Belgium Brownie (chewy) no AF
B59: Ingredients | E59: Quantity | F59: Unit | G59: COST | I59: Ingredients | J59: Quantity | K59: Unit | L59: COST | N59: Ingredients | O59: Quantity | P59: Unit | Q59: COST
B60: Unsalted Butter (melted) | E60: 0.14 | F60: KG | G60: =INGREDIENTS!$D$230*E60 -> 7.252 | I60: Unsalted Butter (melted) | J60: 0.12 | K60: KG | L60: =INGREDIENTS!$D$230*J60 -> 6.216 | N60: Unsalted Butter (melted) | O60: =E60*1.5 -> 0.21 | P60: KG | Q60: =INGREDIENTS!$D$230*O60 -> 10.878
B61: Rice Bran Oil | E61: 0.15 | F61: LITRE | G61: =INGREDIENTS!#REF!*E61 -> #REF! | I61: Rice Bran Oil | J61: 0.1 | K61: LITRE | L61: =INGREDIENTS!#REF!*J61 -> #REF! | N61: Rice Bran Oil | O61: =E61*1.5 -> 0.225 | P61: LITRE | Q61: =INGREDIENTS!#REF!*O61 -> #REF!
B62: Brown Sugar | E62: 0.3 | F62: KG | G62: =INGREDIENTS!$D$223*E62 -> 1.77 | I62: Brown Sugar | J62: 0.26 | K62: KG | L62: =INGREDIENTS!$D$223*J62 -> 1.534 | N62: Brown Sugar | O62: =E62*1.5 -> 0.45 | P62: KG | Q62: =INGREDIENTS!$D$223*O62 -> 2.655
B63: Castor Sugar | E63: 0.3 | F63: KG | G63: =INGREDIENTS!$D$223*E63 -> 1.77 | I63: Castor Sugar | J63: 0.26 | K63: KG | L63: =INGREDIENTS!$D$223*J63 -> 1.534 | N63: Castor Sugar | O63: =E63*1.5 -> 0.45 | P63: KG | Q63: =INGREDIENTS!$D$223*O63 -> 2.655
B64: Salt | E64: 0.002 | F64: KG | I64: Salt | J64: =E64*2 -> 0.004 | K64: KG | N64: Salt | O64: =E64*1.5 -> 0.003 | P64: KG
B65: Espresso Shot | E65: 2 | F65: each | G65: ='HOT Drinks '!$R$8 -> 0.6646301 | I65: Espresso Shot | J65: 2 | K65: each | L65: ='HOT Drinks '!$R$8 -> 0.6646301 | N65: Espresso Shot | O65: =E65*1.5 -> 3 | P65: each | Q65: ='HOT Drinks '!$R$8 -> 0.6646301
B66: Eggs | E66: 4 | F66: each | G66: =INGREDIENTS!#REF!*E66 -> #REF! | I66: Eggs | J66: 4 | K66: each | L66: =INGREDIENTS!#REF!*J66 -> #REF! | N66: Eggs | O66: =E66*1.5 -> 6 | P66: each | Q66: =INGREDIENTS!#REF!*O66 -> #REF!
B67: Egg Yolks | E67: 2 | F67: each | G67: =INGREDIENTS!#REF!*E67 -> #REF! | I67: Egg Yolks | J67: 2 | K67: each | L67: =INGREDIENTS!#REF!*J67 -> #REF! | N67: Egg Yolks | O67: =E67*1.5 -> 3 | P67: each | Q67: =INGREDIENTS!#REF!*O67 -> #REF!
B68: Cocoa Powder | E68: 0.1 | F68: KG | G68: =INGREDIENTS!$D$225*E68 -> 3.65 | I68: Cocoa Powder | J68: 0.1 | K68: KG | L68: =INGREDIENTS!$D$225*J68 -> 3.65 | N68: Cocoa Powder | O68: =E68*1.5 -> 0.15 | P68: KG | Q68: =INGREDIENTS!$D$225*O68 -> 5.475
B69: Cake Wheat Flour | Eureka Mills | E69: 0.22 | F69: KG | G69: =INGREDIENTS!#REF!*E69 -> #REF! | I69: Cake Wheat Flour | Eureka Mills | J69: 0.25 | K69: KG | L69: =INGREDIENTS!#REF!*J69 -> #REF! | N69: Cake Wheat Flour | Eureka Mills | O69: =E69*1.5 -> 0.33 | P69: KG | Q69: =INGREDIENTS!#REF!*O69 -> #REF!
B70: Corn Starch | E70: 0.014 | F70: KG | G70: =INGREDIENTS!#REF!*E70 -> #REF! | I70: Corn Starch | J70: 0.014 | K70: KG | L70: =INGREDIENTS!#REF!*J70 -> #REF! | N70: Corn Starch | O70: =E70*1.5 -> 0.021 | P70: KG | Q70: =INGREDIENTS!#REF!*O70 -> #REF!
B71: Dark Chocolate Buttons | E71: 0.02 | F71: KG | G71: =INGREDIENTS!$D$252*E71 -> 2 | I71: Dark Chocolate Buttons | J71: 0.02 | K71: KG | L71: =INGREDIENTS!$D$252*J71 -> 2 | N71: Dark Chocolate Buttons | O71: =E71*1.5 -> 0.03 | P71: KG | Q71: =INGREDIENTS!$D$252*O71 -> 3
F72: Batch Cost: | G72: =SUM(G60:G71) -> #REF! | K72: Batch Cost: | L72: =SUM(L60:L71) -> #REF! | P72: Batch Cost: | Q72: =SUM(Q60:Q71) -> #REF!
B73: Yield | E73: Sell Price | F73: COGS | G73: Batch Profit | I73: Yield | J73: Sell Price | K73: COGS | L73: Batch Profit | N73: Yield | O73: Sell Price | P73: COGS | Q73: Batch Profit
B74: 40 | E74: 3.5 | F74: =G72/G74 -> #REF! | G74: =(B74*E74)-G72 -> #REF! | I74: 30 | J74: 3.5 | K74: =L72/L74 -> #REF! | L74: =(I74*J74)-L72 -> #REF! | N74: 24 | O74: 7.5 | P74: =Q72/Q74 -> #REF! | Q74: =(N74*O74)-Q72 -> #REF!
B80: Thunder: thin | MYR5-10 each
B82: Salted Caramel Brownie (chewy)
B84: Ingredients | E84: Quantity | F84: Unit | G84: COST
B85: 1 COMBINE;
B86: Unsalted Butter (melted) | E86: 0.12 | F86: KG | G86: =INGREDIENTS!$D$230*E86 -> 6.216
B87: Rice Bran Oil | E87: 0.1 | F87: LITRE | G87: =INGREDIENTS!#REF!*E87 -> #REF!
B88: Brown Sugar | E88: 0.25 | F88: KG | G88: =INGREDIENTS!$D$223*E88 -> 1.475
B89: Castor Sugar | E89: 0.25 | F89: KG | G89: =INGREDIENTS!$D$223*E89 -> 1.475
B90: 2 BEAT (2-3 mins);
B91: Eggs | E91: 4 | F91: each | G91: =INGREDIENTS!#REF!*E91 -> #REF!
B92: Egg Yolks | E92: 2 | F92: each | G92: =INGREDIENTS!#REF!*E92 -> #REF!
B93: 3 SIFT, THEN COMBINE ALL;
B94: Salt | E94: 0.00025 | F94: KG
B95: Espresso Shot | E95: 2 | F95: each | G95: ='HOT Drinks '!$R$8 -> 0.6646301
B96: Cocoa Powder | E96: 0.1 | F96: KG | G96: =INGREDIENTS!$D$225*E96 -> 3.65
B97: Cake Wheat Flour | Eureka Mills | E97: 0.25 | F97: KG | G97: =INGREDIENTS!#REF!*E97 -> #REF!
B98: Corn Starch | E98: 0.014 | F98: KG | G98: =INGREDIENTS!#REF!*E98 -> #REF!
B99: 4 TRAY, THEN TOP WITH;
B100: Dark Chocolate Buttons | E100: 0.02 | F100: KG | G100: =INGREDIENTS!$D$252*E100 -> 2
B101: 5 BAKE
B102: 6 SLICE
B103: 7 GARNISH;
B104: Salted Caramel Sauce
B105: Caramel Crunch | E105: 0.0003 | F105: KG | G105: =INGREDIENTS!$F$255*E105 -> 0.076714286
B106: Salt Flakes | E106: 0.00025 | F106: KG
F107: Batch Cost: | G107: =SUM(G85:G100) -> #REF!
B108: Yield | E108: Sell Price | F108: COGS | G108: Batch Profit
B109: 30 | E109: 3.8 | F109: =G$107/G109 -> #REF! | G109: =(B109*E109)-G107 -> #REF!
B110: 24 | E110: 5 | F110: =G$107/G110 -> #REF! | G110: =(B110*E110)-G$107 -> #REF!
B111: 16 | E111: 6 | F111: =G$107/G111 -> #REF! | G111: =(B111*E111)-G$107 -> #REF!
B112: 12 | E112: 12 | F112: =G$107/G112 -> #REF! | G112: =(B112*E112)-G$107 -> #REF!
B114: Thunder: thin / unflavoured | MYR2-4 each - too thick / cement like
B116: Belgium Brownie (chewy) no AF
B118: Ingredients | E118: Quantity | F118: Unit | G118: COST
B119: Unsalted Butter (melted) | E119: 0.11 | F119: KG | G119: =INGREDIENTS!$D$230*E119 -> 5.698
B120: Rice Bran Oil | E120: 0.11 | F120: LITRE | G120: =INGREDIENTS!#REF!*E120 -> #REF!
B121: Brown Sugar | E121: 0.26 | F121: KG | G121: =INGREDIENTS!$D$223*E121 -> 1.534
B122: Castor Sugar | E122: 0.26 | F122: KG | G122: =INGREDIENTS!$D$223*E122 -> 1.534
B123: Salt | E123: 0.0025 | F123: KG
B124: Eggs | E124: 4 | F124: each | G124: =INGREDIENTS!$F$112*E124 -> 2.12
B125: Egg Yolks | E125: 2 | F125: each | G125: =INGREDIENTS!$F$112*E125 -> 1.06
B126: Espresso Shot | E126: 2 | F126: each | G126: ='HOT Drinks '!$R$8 -> 0.6646301
B127: Cocoa Powder | E127: 0.1 | F127: KG | G127: =INGREDIENTS!$D$225*E127 -> 3.65
B128: Cake Wheat Flour | Eureka Mills | E128: 0.24 | F128: KG | G128: =INGREDIENTS!#REF!*E128 -> #REF!
B129: Corn Starch | E129: 0.014 | F129: KG | G129: =INGREDIENTS!#REF!*E129 -> #REF!
...

Sheet Baked Goods
B2: BIG | G2: MINI | L2: Bite Size
B4: Banana Cinnamon Muffin | G4: Banana Cinnamon Muffin | L4: Banana Cinnamon Muffin
B6: Ingredients | C6: Quantity | D6: Unit | E6: COST | G6: Ingredients | H6: Quantity | I6: Unit | J6: COST | L6: Ingredients | M6: Quantity | N6: Unit | O6: COST
B7: 1 CREATE DRY MIX: SIFT; | G7: 1 CREATE DRY MIX: SIFT; | L7: 1 CREATE DRY MIX: SIFT;
B8: SR Flour | C8: 0.25 | D8: KG | E8: =INGREDIENTS!$D$240*C8 -> 1.55 | G8: SR Flour | H8: 0.25 | I8: KG | J8: =INGREDIENTS!$D$240*H8 -> 1.55 | L8: SR Flour | M8: 0.25 | N8: KG | O8: =INGREDIENTS!$D$240*M8 -> 1.55
B9: 2 ADD; | G9: 2 ADD; | L9: 2 ADD;
B10: Raw Sugar | C10: 0.11 | D10: KG | E10: =INGREDIENTS!$D$273*C10 -> 0.5555 | G10: Raw Sugar | H10: 0.08 | I10: KG | J10: =INGREDIENTS!$D$273*H10 -> 0.404 | L10: Raw Sugar | M10: 0.08 | N10: KG | O10: =INGREDIENTS!$D$273*M10 -> 0.404
B11: Desiccated Coconut | C11: 0.03 | D11: KG | E11: =INGREDIENTS!$D$228*C11 -> 0.297 | G11: Desiccated Coconut | H11: 0.03 | I11: KG | J11: =INGREDIENTS!$D$228*H11 -> 0.297 | L11: Desiccated Coconut | M11: 0.03 | N11: KG | O11: =INGREDIENTS!$D$228*M11 -> 0.297
B12: Salt | C12: 0.005 | D12: KG | E12: 0.1 | G12: Salt | H12: 0.005 | I12: KG | J12: 0.1 | L12: Salt | M12: 0.005 | N12: KG | O12: 0.1
B13: Cinnamon | C13: 0.005 | D13: KG | E13: 0.2 | G13: Cinnamon | H13: 0.005 | I13: KG | J13: 0.2 | L13: Cinnamon | M13: 0.005 | N13: KG | O13: 0.2
B14: 3 CREATE WET MIX; | G14: 3 CREATE WET MIX; | L14: 3 CREATE WET MIX;
B15: Eggs | C15: 3 | D15: each | E15: =INGREDIENTS!$F$112*C15 -> 1.59 | G15: Eggs | H15: 3 | I15: each | J15: =INGREDIENTS!$F$112*H15 -> 1.59 | L15: Eggs | M15: 3 | N15: each | O15: =INGREDIENTS!$F$112*M15 -> 1.59
B16: Milk | C16: 120 | D16: ML | E16: =INGREDIENTS!$F$38*C16 -> 1.7112 | G16: Milk | H16: 120 | I16: ML | J16: =INGREDIENTS!$F$38*H16 -> 1.7112 | L16: Milk | M16: 120 | N16: ML | O16: =INGREDIENTS!$F$38*M16 -> 1.7112
B17: Rice Bran Oil | C17: 130 | D17: ML | E17: =INGREDIENTS!#REF!*C17 -> #REF! | G17: Rice Bran Oil | H17: 120 | I17: ML | J17: =INGREDIENTS!#REF!*H17 -> #REF! | L17: Rice Bran Oil | M17: 120 | N17: ML | O17: =INGREDIENTS!#REF!*M17 -> #REF!
B18: 4 ADD FLAVOUR; | G18: 4 ADD FLAVOUR; | L18: 4 ADD FLAVOUR;
B19: Banana | C19: 2 | D19: each | E19: =INGREDIENTS!#REF!*C19 -> #REF! | G19: Banana | H19: 2 | I19: each | J19: =INGREDIENTS!#REF!*H19 -> #REF! | L19: Banana | M19: 2 | N19: each | O19: =INGREDIENTS!#REF!*M19 -> #REF!
B20: 4 COMBINE (fold, careful not to activate gluten) | G20: 4 COMBINE (fold, careful not to activate gluten) | L20: 4 COMBINE (fold, careful not to activate gluten)
B21: 5 TRAY (using 2 spoons with a "pluck" and "place" method) | G21: 5 TRAY (using 2 spoons with a "pluck" and "place" method) | L21: 5 TRAY (using 2 spoons with a "pluck" and "place" method)
B22: 6 BAKE (regular size: 24 mins / mini size: 15 mins) | G22: 6 BAKE (regular size: 24 mins / mini size: 15 mins) | L22: 6 BAKE (regular size: 24 mins / mini size: 15 mins)
B23: 7 GARNISH | G23: 7 GARNISH | L23: 7 GARNISH
B24: Icing Sugar | C24: 0.025 | D24: KG | E24: =INGREDIENTS!$D$233*C24 -> 0.145 | G24: Icing Sugar | H24: 0.025 | I24: KG | J24: =INGREDIENTS!$D$233*H24 -> 0.145 | L24: Icing Sugar | M24: 0.025 | N24: KG | O24: =INGREDIENTS!$D$233*M24 -> 0.145
D25: Batch Cost: | E25: =SUM(E7:E24) -> #REF! | I25: Batch Cost: | J25: =SUM(J7:J24) -> #REF! | N25: Batch Cost: | O25: =SUM(O7:O24) -> #REF!
D26: Yield: | E26: 12 | I26: Yield: | J26: 24 | N26: Yield: | O26: 48
D27: Unit Cost: | E27: =E25/E26 -> #REF! | I27: Unit Cost: | J27: =J25/J26 -> #REF! | N27: Unit Cost: | O27: =O25/O26 -> #REF!
B28: Batch Profit | C28: Sell Price | D28: COGS | E28: Unit Profit | G28: Batch Profit | H28: Sell Price | I28: COGS | J28: Unit Profit | L28: Batch Profit | M28: Sell Price | N28: COGS | O28: Unit Profit
B29: =E29*E26 -> #REF! | C29: 5.8 | D29: =E27/C29 -> #REF! | E29: =C29-E27 -> #REF! | G29: =J29*J26 -> #REF! | H29: 3 | I29: =J27/H29 -> #REF! | J29: =H29-J27 -> #REF! | L29: =O29*O26 -> #REF! | M29: 2.5 | N29: =O27/M29 -> #REF! | O29: =M29-O27 -> #REF!
B30: =E30*E26 -> #REF! | C30: 4.8 | D30: =E27/C30 -> #REF! | E30: =C30-E27 -> #REF! | G30: =J30*J26 -> #REF! | H30: 2.5 | I30: =J27/H30 -> #REF! | J30: =H30-J27 -> #REF! | L30: =O30*O26 -> #REF! | M30: 2 | N30: =O27/M30 -> #REF! | O30: =M30-O27 -> #REF!
B32: BIG | G32: MINI | L32: MINI
B34: Tripple Choc Muffin | G34: Tripple Choc Muffin | L34: Tripple Choc Muffin
B36: Ingredients | C36: Quantity | D36: Unit | E36: COST | G36: Ingredients | H36: Quantity | I36: Unit | J36: COST | L36: Ingredients | M36: Quantity | N36: Unit | O36: COST
B37: 1 CREATE DRY MIX: SIFT; | G37: 1 CREATE DRY MIX: SIFT; | L37: 1 CREATE DRY MIX: SIFT;
B38: SR Flour | C38: 0.35 | D38: KG | E38: =INGREDIENTS!$D$240*C38 -> 2.17 | G38: SR Flour | H38: 0.25 | I38: KG | J38: =INGREDIENTS!$D$240*H38 -> 1.55 | L38: SR Flour | M38: 0.25 | N38: KG | O38: =INGREDIENTS!$D$240*M38 -> 1.55
B39: 2 ADD; | G39: 2 ADD; | L39: 2 ADD;
B40: Raw Sugar | C40: 0.22 | D40: KG | E40: =INGREDIENTS!$D$273*C40 -> 1.111 | G40: Raw Sugar | H40: 0.08 | I40: KG | J40: =INGREDIENTS!$D$273*H40 -> 0.404 | L40: Raw Sugar | M40: 0.08 | N40: KG | O40: =INGREDIENTS!$D$273*M40 -> 0.404
B41: Cocao Powder | C41: 0.015 | D41: KG | E41: =INGREDIENTS!$D$225*C41 -> 0.5475 | G41: Cocao Powder | H41: 0.015 | I41: KG | J41: =INGREDIENTS!$D$225*H41 -> 0.5475 | L41: Cocao Powder | M41: 0.015 | N41: KG | O41: =INGREDIENTS!$D$225*M41 -> 0.5475
B42: Desiccated Coconut | C42: 0.25 | D42: KG | E42: =INGREDIENTS!$D$228*C42 -> 2.475 | G42: Desiccated Coconut | H42: 0.02 | I42: KG | J42: =INGREDIENTS!$D$228*H42 -> 0.198 | L42: Desiccated Coconut | M42: 0.02 | N42: KG | O42: =INGREDIENTS!$D$228*M42 -> 0.198
B43: Salt | C43: 0.005 | D43: KG | E43: 0.1 | G43: Salt | H43: 0.005 | I43: KG | J43: 0.1 | L43: Salt | M43: 0.005 | N43: KG | O43: 0.1
B44: 3 CREATE WET MIX; | G44: 3 CREATE WET MIX; | L44: 3 CREATE WET MIX;
B45: Eggs | C45: 3 | D45: each | E45: =INGREDIENTS!$F$112*C45 -> 1.59 | G45: Eggs | H45: 3 | I45: each | J45: =INGREDIENTS!$F$112*H45 -> 1.59 | L45: Eggs | M45: 3 | N45: each | O45: =INGREDIENTS!$F$112*M45 -> 1.59
B46: Milk | C46: 150 | D46: ML | E46: =INGREDIENTS!$F$38*C46 -> 2.139 | G46: Milk | H46: 120 | I46: ML | J46: =INGREDIENTS!$F$38*H46 -> 1.7112 | L46: Milk | M46: 120 | N46: ML | O46: =INGREDIENTS!$F$38*M46 -> 1.7112
B47: Rice Bran Oil | C47: 180 | D47: ML | E47: =INGREDIENTS!#REF!*C47 -> #REF! | G47: Rice Bran Oil | H47: 120 | I47: ML | J47: =INGREDIENTS!#REF!*H47 -> #REF! | L47: Rice Bran Oil | M47: 120 | N47: ML | O47: =INGREDIENTS!#REF!*M47 -> #REF!
B48: 4 ADD FLAVOUR; | G48: 4 ADD FLAVOUR; | L48: 4 ADD FLAVOUR;
B49: Dark Chcolate Buttons (compound) | C49: 0.05 | D49: each | E49: =INGREDIENTS!$D$237*C49 -> 1.025 | G49: Dark Chcolate Buttons (compound) | H49: 0.05 | I49: each | J49: =INGREDIENTS!$D$237*H49 -> 1.025 | L49: Dark Chcolate Buttons (compound) | M49: 0.05 | N49: each | O49: =INGREDIENTS!$D$237*M49 -> 1.025
B50: Milk Chocolate Buttons (compound) | C50: 0.05 | D50: KG | E50: =INGREDIENTS!$D$235*C50 -> 1.125 | G50: Milk Chocolate Buttons (compound) | H50: 0.05 | I50: KG | J50: =INGREDIENTS!$D$235*H50 -> 1.125 | L50: Milk Chocolate Buttons (compound) | M50: 0.05 | N50: KG | O50: =INGREDIENTS!$D$235*M50 -> 1.125
B51: 4 COMBINE (fold, careful not to activate gluten) | G51: 4 COMBINE (fold, careful not to activate gluten) | L51: 4 COMBINE (fold, careful not to activate gluten)
B52: 5 TRAY (using 2 spoons with a "pluck" and "place" method) | G52: 5 TRAY (using 2 spoons with a "pluck" and "place" method) | L52: 5 TRAY (using 2 spoons with a "pluck" and "place" method)
B53: 6 BAKE (regular size: 24 mins / mini size: 15 mins) | G53: 6 BAKE (regular size: 24 mins / mini size: 15 mins) | L53: 6 BAKE (regular size: 24 mins / mini size: 15 mins)
B54: 7 GARNISH | G54: 7 GARNISH | L54: 7 GARNISH
B55: Icing Sugar | C55: 0.025 | D55: KG | E55: =INGREDIENTS!$D$233*C55 -> 0.145 | G55: Icing Sugar | H55: 0.025 | I55: KG | J55: =INGREDIENTS!$D$233*H55 -> 0.145 | L55: Icing Sugar | M55: 0.025 | N55: KG | O55: =INGREDIENTS!$D$233*M55 -> 0.145
D56: Batch Cost: | E56: =SUM(E37:E55) -> #REF! | I56: Batch Cost: | J56: =SUM(J37:J55) -> #REF! | N56: Batch Cost: | O56: =SUM(O37:O55) -> #REF!
D57: Yield: | E57: 12 | I57: Yield: | J57: 24 | N57: Yield: | O57: 48
D58: Unit Cost: | E58: =E56/E57 -> #REF! | I58: Unit Cost: | J58: =J56/J57 -> #REF! | N58: Unit Cost: | O58: =O56/O57 -> #REF!
B59: Batch Profit | C59: Sell Price | D59: COGS | E59: Unit Profit | G59: Batch Profit | H59: Sell Price | I59: COGS | J59: Unit Profit | L59: Batch Profit | M59: Sell Price | N59: COGS | O59: Unit Profit
B60: =E60*E57 -> #REF! | C60: 5.8 | D60: =E58/C60 -> #REF! | E60: =C60-E58 -> #REF! | G60: =J60*J57 -> #REF! | H60: 3 | I60: =J58/H60 -> #REF! | J60: =H60-J58 -> #REF! | L60: =O60*O57 -> #REF! | M60: 2.5 | N60: =O58/M60 -> #REF! | O60: =M60-O58 -> #REF!
B61: =E61*E57 -> #REF! | C61: 4.8 | D61: =E58/C61 -> #REF! | E61: =C61-E58 -> #REF! | G61: =J61*J57 -> #REF! | H61: 2.5 | I61: =J58/H61 -> #REF! | J61: =H61-J58 -> #REF! | L61: =O61*O57 -> #REF! | M61: 2 | N61: =O58/M61 -> #REF! | O61: =M61-O58 -> #REF!
B64: BIG | G64: BIG
B66: Berry Muffin | G66: Banana Muffin
B68: Ingredients | C68: Quantity | D68: Unit | E68: COST | G68: Ingredients | H68: Quantity | I68: Unit | J68: COST
B69: 1 CREATE DRY MIX: SIFT; | G69: 1 CREATE DRY MIX: SIFT;
B70: SR Flour | C70: 0.35 | D70: KG | E70: =INGREDIENTS!$D$240*C70 -> 2.17 | G70: SR Flour | H70: 0.35 | I70: KG | J70: =INGREDIENTS!$D$240*H70 -> 2.17
B71: 2 ADD; | G71: 2 ADD;
B72: Raw Sugar | C72: 0.2 | D72: KG | E72: =INGREDIENTS!$D$273*C72 -> 1.01 | G72: Raw Sugar | H72: 0.2 | I72: KG | J72: =INGREDIENTS!$D$273*H72 -> 1.01
B73: Desiccated Coconut | C73: 0.03 | D73: KG | E73: =INGREDIENTS!$D$228*C73 -> 0.297 | G73: Desiccated Coconut | H73: 0.03 | I73: KG | J73: =INGREDIENTS!$D$228*H73 -> 0.297
B74: Salt | C74: 0.005 | D74: KG | E74: 0.1 | G74: Salt | H74: 0.005 | I74: KG | J74: 0.1
B75: 3 CREATE WET MIX; | G75: 3 CREATE WET MIX;
B76: Eggs | C76: 3 | D76: each | E76: =INGREDIENTS!$F$112*C76 -> 1.59 | G76: Eggs | H76: 3 | I76: each | J76: =INGREDIENTS!$F$112*H76 -> 1.59
B77: Milk | C77: 150 | D77: ML | E77: =INGREDIENTS!$F$38*C77 -> 2.139 | G77: Milk | H77: 150 | I77: ML | J77: =INGREDIENTS!$F$38*H77 -> 2.139
B78: Rice Bran Oil | C78: 180 | D78: ML | E78: =INGREDIENTS!#REF!*C78 -> #REF! | G78: Rice Bran Oil | H78: 180 | I78: ML | J78: =INGREDIENTS!#REF!*H78 -> #REF!
B79: 4 ADD FLAVOUR; | G79: 4 ADD FLAVOUR;
B80: Berry (frozen) | C80: 0.1 | D80: KG | E80: =INGREDIENTS!$D$270*C80 -> 2.3 | G80: Banana | H80: 2 | I80: each | J80: =INGREDIENTS!#REF!*H80 -> #REF!
B81: Chocolate Buttons (compound) | C81: 0.06 | D81: each | E81: =INGREDIENTS!$D$237*C81 -> 1.23 | G81: Chocolate Buttons (compound) | H81: 0.06 | I81: each | J81: =INGREDIENTS!$D$237*H81 -> 1.23
B82: 4 COMBINE (fold, careful not to activate gluten) | G82: 4 COMBINE (fold, careful not to activate gluten)
B83: 5 TRAY (using 2 spoons with a "pluck" and "place" method) | G83: 5 TRAY (using 2 spoons with a "pluck" and "place" method)
B84: 6 BAKE (regular size: 24 mins / mini size: 15 mins) | G84: 6 BAKE (regular size: 24 mins / mini size: 15 mins)
B85: 7 GARNISH | G85: 7 GARNISH
B86: Icing Sugar | C86: 0.025 | D86: KG | E86: =INGREDIENTS!$D$233*C86 -> 0.145 | G86: Icing Sugar | H86: 0.025 | I86: KG | J86: =INGREDIENTS!$D$233*H86 -> 0.145
D87: Batch Cost: | E87: =SUM(E69:E86) -> #REF! | I87: Batch Cost: | J87: =SUM(J69:J86) -> #REF!
D88: Yield: | E88: 12 | I88: Yield: | J88: 12
D89: Unit Cost: | E89: =E87/E88 -> #REF! | I89: Unit Cost: | J89: =J87/J88 -> #REF!
B90: Batch Profit | C90: Sell Price | D90: COGS | E90: Unit Profit | G90: Batch Profit | H90: Sell Price | I90: COGS | J90: Unit Profit
B91: =E91*E88 -> #REF! | C91: 5.8 | D91: =E89/C91 -> #REF! | E91: =C91-E89 -> #REF! | G91: =J91*J88 -> #REF! | H91: 5.8 | I91: =J89/H91 -> #REF! | J91: =H91-J89 -> #REF!
B92: =E92*E88 -> #REF! | C92: 4.8 | D92: =E89/C92 -> #REF! | E92: =C92-E89 -> #REF! | G92: =J92*J88 -> #REF! | H92: 4.8 | I92: =J89/H92 -> #REF! | J92: =H92-J89 -> #REF!
B94: BIG
B96: Banana, Cinnamon, Dark Chocolate
B98: Ingredients | C98: Quantity | D98: Unit | E98: COST
B99: 1 CREATE DRY MIX: SIFT;
B100: SR Flour | C100: 0.35 | D100: KG | E100: =INGREDIENTS!$D$240*C100 -> 2.17
B101: 2 ADD;
B102: Raw Sugar | C102: 0.2 | D102: KG | E102: =INGREDIENTS!$D$273*C102 -> 1.01
B103: Desiccated Coconut | C103: 0.03 | D103: KG | E103: =INGREDIENTS!$D$228*C103 -> 0.297
B104: Salt | C104: 0.005 | D104: KG | E104: 0.1
B105: 3 CREATE WET MIX;
B106: Eggs | C106: 3 | D106: each | E106: =INGREDIENTS!$F$112*C106 -> 1.59
B107: Milk | C107: 150 | D107: ML | E107: =INGREDIENTS!$F$38*C107 -> 2.139
B108: Rice Bran Oil | C108: 180 | D108: ML | E108: =INGREDIENTS!#REF!*C108 -> #REF!
B109: 4 ADD FLAVOUR;
B110: Blueberry (frozen) | C110: 0.08 | D110: KG | E110: =INGREDIENTS!$D$271*C110 -> 2.112
B111: 4 COMBINE (fold, careful not to activate gluten)
B112: 5 TRAY (using 2 spoons with a "pluck" and "place" method)
B113: 6 BAKE (regular size: 24 mins / mini size: 15 mins)
...

Sheet Test Items

Sheet Other
B4: Orange Cookie
B6: Ingredients | C6: Quantity | D6: Unit | E6: COST
B7: Unsalted Butter (melted) | C7: 0.22 | D7: KG | E7: =INGREDIENTS!$D$230*C7 -> 11.396
B8: Icing Sugar | C8: 0.08 | D8: KG | E8: =INGREDIENTS!$D$233*C8 -> 0.464
B9: Cardamom | C9: 0.005 | D9: KG | E9: =INGREDIENTS!$D$240*C9 -> 0.031
B10: Flour | C10: 0.25 | D10: KG | E10: =INGREDIENTS!#REF!*C10 -> #REF!
B11: Orange Zest | C11: 2 | D11: each | E11: =INGREDIENTS!#REF!*C11 -> #REF!
B12: Corn Starch | C12: 0.1 | D12: KG | E12: 15
B13: Icing Sugar | C13: 0.05 | D13: KG | E13: =INGREDIENTS!$D$239*C13 -> 1.295
B14: Orange Juice | C14: 1 | D14: each | E14: =INGREDIENTS!$D$277*C14 -> 32.93
D19: Batch Cost: | E19: =SUM(E7:E18) -> #REF!
D20: Yield: | E20: 18
D21: Unit Cost: | E21: =E19/E20 -> #REF!
B22: Batch Profit | C22: Sell Price | D22: COGS | E22: Unit Profit
B23: =E23*E20 -> #REF! | C23: 6 | D23: =E21/C23 -> #REF! | E23: =C23-E21 -> #REF!
B24: =E24*E20 -> #REF! | C24: 5 | D24: =E21/C24 -> #REF! | E24: =C24-E21 -> #REF!
B28: Salted Egg Cookie
B30: Ingredients | C30: Quantity | D30: Unit | E30: COST
B31: Unsalted Butter (melted) | C31: 0.17 | D31: KG | E31: =INGREDIENTS!$D$230*C31 -> 8.806
B32: Icing Sugar | C32: 0.08 | D32: KG | E32: =INGREDIENTS!$D$233*C32 -> 0.464
B33: Flour | C33: 0.25 | D33: KG | E33: =INGREDIENTS!#REF!*C33 -> #REF!
B34: Corn Starch | C34: 0.1 | D34: KG | E34: 15
B35: Salt | C35: 2 | D35: each | E35: =INGREDIENTS!#REF!*C35 -> #REF!
B36: Cream | C36: 0.1 | D36: KG | E36: 15
B37: Icing Sugar | C37: 0.05 | D37: KG | E37: =INGREDIENTS!$D$239*C37 -> 1.295
B38: Lemon Zest | C38: 1 | D38: each | E38: =INGREDIENTS!$D$277*C38 -> 32.93
B42: Salted Egg Yolks | C42: 4 | D42: each | E42: =1.5*C42 -> 6
D43: Batch Cost: | E43: =SUM(E31:E42) -> #REF!
D44: Yield: | E44: 18
D45: Unit Cost: | E45: =E43/E44 -> #REF!
B46: Batch Profit | C46: Sell Price | D46: COGS | E46: Unit Profit
B47: =E47*E44 -> #REF! | C47: 6 | D47: =E45/C47 -> #REF! | E47: =C47-E45 -> #REF!
B48: =E48*E44 -> #REF! | C48: 5 | D48: =E45/C48 -> #REF! | E48: =C48-E45 -> #REF!
B54: Rocky Road
B56: Ingredients | C56: Quantity | D56: Unit | E56: Quantity | F56: Unit | G56: COST
B57: 1 MELT;
B58: Milk Chocolate Buttons (compound) | C58: 250 | D58: GRAMS | E58: 0.25 | F58: KG | G58: =INGREDIENTS!$D$240*E58 -> 1.55
B59: Dark Chocolate Buttons (compound) | C59: 250 | D59: GRAMS | E59: 0.25 | F59: KG | G59: =INGREDIENTS!$D$240*E59 -> 1.55
B60: Rice Bran Oil | C60: 100 | D60: MLS | E60: 100 | F60: ML | G60: =INGREDIENTS!#REF!*E60 -> #REF!
B61: 2 EVENLY PLACE INGREDIENTS IN TRAY;
B62: Cashew | C62: 100 | D62: GRAMS | E62: 0.1 | F62: KG | G62: =INGREDIENTS!$D$248*E62 -> 4.5
B63: Marshamallow | C63: 50 | D63: GRAMS | E63: 0.05 | F63: KG | G63: =INGREDIENTS!$D$239*E63 -> 1.295
B64: Red Jubes | C64: 80 | D64: GRAMS | E64: 0.08 | F64: KG | G64: =INGREDIENTS!$D$277*E64 -> 2.6344
B65: Desiccated Coconut | C65: 25 | D65: GRAMS | E65: 0.025 | F65: KG | G65: =INGREDIENTS!$D$228*E65 -> 0.2475
B66: 3 POUR CHOCOLATE (careful not to move the ingredients around)
B67: 4 GARNISH;
B68: Desiccated Coconut | C68: 10 | D68: GRAMS | E68: 0.01 | F68: KG | G68: =INGREDIENTS!$D$228*E68 -> 0.099
C69: YIELD: | D69: 8 | F69: Batch Cost: | G69: =SUM(G57:G68) -> #REF!
C70: PRICE: | D70: 10.9 | F70: Yield: | G70: 8
C71: COMBO PRICE: | D71: 9.9 | F71: Unit Cost: | G71: =G69/G70 -> #REF!
B72: Batch Profit | E72: Sell Price | F72: COGS | G72: Unit Profit
B73: =G73*G70 -> #REF! | E73: 9.9 | F73: =G71/E73 -> #REF! | G73: =E73-G71 -> #REF!
B74: =G74*G70 -> #REF! | E74: 8.9 | F74: =G71/E74 -> #REF! | G74: =E74-G71 -> #REF!

Sheet WEEKLY INVENTORY FILE 
A1: THUNDER STOCK BALANCE REPORT 2025
A6: OUTLET ITEM CODE | B6: ITEM DESCRIPTION | C6: SUPLIER UOM | D6: CONVERTED UOM | E6: PRICE | F6: CATEGORY | G6: STOCK BALANCE OF 18072025 | H6: VALUE | I6: CATEGORY TOTAL
B7: YUZU LEMON SYURUP | C7: BTL/1000ML | D7: BTL/1000ML | E7: 69.5 | F7: SYRUP | G7: 0.9 | H7: =G7*E7 -> 62.55 | I7: =SUM(H7:H15) -> 654.9
B8: MONTENNE MANGO REAL FRUIT MIX | C8: BTL/1000ML | D8: BTL/1000ML | E8: 55 | G8: 1 | H8: =G8*E8 -> 55
B9: MONTENNE BANANA REAL FRUIT MIX | C9: BTL/1000ML | D9: BTL/1000ML | E9: 55 | G9: 1.5 | H9: =G9*E9 -> 82.5
B10: MONTENNE KIWI REAL FRUIT MIX | C10: BTL/1000ML | D10: BTL/1000ML | E10: 55 | G10: 1 | H10: =G10*E10 -> 55
B11: MONTENNE MIXBERRIES REAL FRUIT MIX | C11: BTL/1000ML | D11: BTL/1000ML | E11: 55 | G11: 0.7 | H11: =G11*E11 -> 38.5
B12: 1883 RE WATERMELON SYRUP | C12: BTL/1000ML | D12: BTL/1000ML | E12: 69.5 | G12: 1.3 | H12: =G12*E12 -> 90.35
B13: MONTENNE SOURSOP REAL FRUIT MIX | C13: BTL/1000ML | D13: BTL/1000ML | E13: 55 | G13: 1 | H13: =G13*E13 -> 55
B14: MONTENNE STRAWBERRY REAL FRUIT MIX | C14: BTL/1000ML | D14: BTL/1000ML | E14: 40 | G14: 5.4 | H14: =G14*E14 -> 216
H15: =G15*E15 -> 0
B16: 12OZ ICE CUP | C16: CTN/40ROLLS | D16: ROLL/25PCS | E16: 6.75 | F16: DISPOSABLE | G16: 8 | H16: =G16*E16 -> 54 | I16: =SUM(H16:H23) -> 480.5
B17: 12OZ DOUBLE WALL HOT CUP - PLAIN WHITE | C17: CTN/20ROLLS | D17: ROLL/25PCS | E17: 8 | G17: 12 | H17: =G17*E17 -> 96
B18: 80Z HOT CUP | C18: CTN/400ROLLS | D18: ROLL/25PCS | E18: 6.25 | G18: 30 | H18: =G18*E18 -> 187.5
B19: 12OZ HOT CUP LIDS | C19: CTN/20ROLLS | D19: ROLLS/50PCS | E19: =220/20 -> 11 | G19: 7 | H19: =G19*E19 -> 77
B20: 12OZ ICE CUP LIDS | C20: CTN/20ROLLS | D20: ROLLS/100PCS | E20: =230/20 -> 11.5 | G20: 6 | H20: =G20*E19 -> 66
B21: 8OZ ICE CUP LIDS | C21: CTN/20ROLLS | D21: ROLLS/50PCS | E21: =220/50 -> 4.4 | H21: =G21*E23 -> 0
B22: PAPER STRAW 6MM WITH WRAPPER | C22: CTN/20 PKT | D22: PKT/50PCS | E22: =270/20 -> 13.5
B23: COCKTAIL BROWN NAPKIN | C23: CTN/50PKT | D23: PKT/100S | E23: =130/50 -> 2.6 | H23: =G23*E24 -> 0
B24: OATSIDE PLAIN OAT MILK BARISTA | C24: BTL/1000ML | D24: BTL/1000ML | E24: 9.3 | F24: DAIRY PRODUCTS | G24: 10 | H24: =G24*E24 -> 93 | I24: =SUM(H24:H28) -> 904.12
B25: FARM FRESH MILK | C25: BTL/2000ML | D25: BTL/2000ML | E25: 14.26 | G25: 52 | H25: =G25*E25 -> 741.52
B26: BEGA COLOURED BURGER CHEDDAR SLICE | C26: PKT/1KG | D26: PKT/1KG | E26: 34.8 | G26: 2 | H26: =G26*E26 -> 69.6
H27: =G27*E27 -> 0
H28: =G28*E28 -> 0
B29: ACEDAMY ROASTED BLEND COFFEE | C29: PKT/KG | D29: PKT/KG | E29: 60 | F29: COFFEE & POWDER | G29: 6.5 | H29: =G29*E29 -> 390 | I29: =SUM(H29:H31) -> 390
B30: SPICE CHAI | C30: PKT/KG | D30: PKT/KG | E30: 120 | H30: =G30*E30 -> 0
B31: CHCOLATE POWDER | C31: PKR/KG | D31: PKT/KG | E31: 70 | H31: =G31*E31 -> 0
B32: MARBLE CAKE | C32: LOAF | D32: PCS | E32: 4 | F32: CAKE & COKIES | H32: =G32*E32 -> 0 | I32: =SUM(H32:H39) -> 238
B33: LEMON CAKE | C33: LOAF | D33: PCS | E33: 4 | G33: 3 | H33: =G33*E33 -> 12
B34: BANANA CAKE | C34: LOAF | D34: PCS | E34: 4 | G34: 4 | H34: =G34*E34 -> 16
B35: SCHIACCIATA | C35: TRAY | D35: PCS | E35: 2 | H35: =G35*E35 -> 0
B36: NUTELLA | C36: PCS | D36: PCS | E36: 7.5 | G36: 7 | H36: =G36*E36 -> 52.5
B37: MATCHA | C37: PCS | D37: PCS | E37: 7.5 | G37: 7 | H37: =G37*E37 -> 52.5
B38: RASPHERRY DOUBLE CHOCO | C38: PCS | D38: PCS | E38: 7.5 | G38: 5 | H38: =G38*E38 -> 37.5
B39: WALNUT | C39: PCS | D39: PCS | E39: 7.5 | G39: 9 | H39: =G39*E39 -> 67.5
B40: AVAPORATED MILK F&N | C40: CAN/ | D40: CAN/ | E40: 5.5 | F40: DRY INGREDIENTS | G40: 5 | H40: =G40*E40 -> 27.5 | I40: =SUM(H40:H43) -> 47
B41: SPAGHETTI | C41: PKT/ | D41: PKT/ | E41: 4.8 | G41: 1 | H41: =G41*E41 -> 4.8
B42: TUNA AYAM BRAND | C42: CAN | D42: CAN | E42: 8.8 | H42: =G42*E42 -> 0
B43: TABASCO SAUCE | C43: BTL/ | D43: BTL/ | E43: 9.8 | G43: 1.5 | H43: =G43*E43 -> 14.7
B44: EGG | C44: TRY | D44: TRAY | E44: 13.5 | F44: FRUITS & VAGETABLES | G44: 1.5 | H44: =G44*E44 -> 20.25 | I44: =SUM(H44:H55) -> 225.78
B45: PARSLEY | C45: KG/GM | D45: KG/GM | E45: 12 | G45: 0.1 | H45: =G45*E45 -> 1.2
B46: TOMATO WHOLE | C46: KG/GM | D46: KG/GM | E46: 4.5 | G46: 10 | H46: =G46*E46 -> 45
B47: LEMON | C47: KG/GM | D47: KG/GM | E47: 9.5 | G47: 2 | H47: =G47*E47 -> 19
B48: MUSHROOM OYSTER FRESH | C48: PKT/500GM | D48: PKT/500GM | E48: 9.5 | G48: 2 | H48: =G48*E48 -> 19
B49: RED ONION | C49: KG/GM | D49: KG/GM | E49: 3.5 | G49: 1.5 | H49: =G49*E49 -> 5.25
B50: GARLIC WHOLE | C50: KG/GM | D50: KG/GM | E50: 10 | G50: 4 | H50: =G50*E50 -> 40
B51: ORNAGE | C51: NOS | D51: NOS | E51: 1.5 | G51: 26 | H51: =G51*E51 -> 39
B52: COCONUT POWDER | C52: PKT/ | D52: PKT/ | E52: 3.5 | G52: 3 | H52: =G52*E52 -> 10.5
B53: CHILLU FLAKES | C53: PKT/ | D53: PKT/ | E53: 4.8 | G53: 4 | H53: =G53*E53 -> 19.2
B54: CHILLI SAUCE | C54: PKT/ | D54: PKT/ | E54: 6.5 | G54: 1 | H54: =G54*E54 -> 6.5
B55: MINT LEAF | C55: KG | D55: KG | E55: 8.8 | G55: 0.1 | H55: =G55*E55 -> 0.88
B56: CHICKEN HAM SLCED | C56: PKT/800GM | D56: KG/GM | E56: 19.6 | F56: MEAT PRODUCTS | G56: 6 | H56: =G56*E56 -> 117.6 | I56: =SUM(H56:H60) -> 117.6
H57: =G57*E57 -> 0
H58: =G58*E58 -> 0
H59: =G59*E59 -> 0
H60: =G60*E60 -> 0
G61: TOTAL | I61: =SUM(I7:I60) -> 3057.9
